Workbook

Sheet Producto
A1: Producto | B1: Fecha | C1: No. de Factura | D1: Cantidad | E1: Nombre del Paciente | F1: Tratamiento | G1: Forma de Pago | H1: Total
B3: 45296 | C3: 3555935180 | D3: 1 | E3: Claudia Castillo | F3: Frasco de protocol colageno con acido hialuronico | G3: Visa | H3: 550
B4: 45296 | C4: 3555935180 | D4: 1 | E4: Claudia Castillo | F4: Beauty collagen advanced (Protocol) | G4: Visa | H4: 850
B5: 45296 | C5: 889341831 | D5: 2 | E5: Mario Rafael Gonzalez / Andrea López | F5: Frasco de protocol colageno con acido hialuronico | G5: Efectivo | H5: 1100
B6: 45296 | C6: 889341831 | D6: 2 | E6: Mario Rafael Gonzalez / Andrea López | F6: Beauty collagen advanced (Protocol) | G6: Efectivo | H6: 1700
B7: 45307 | C7: 2980136370 | D7: 1 | E7: Norma De Barquin | F7: Beauty collagen advanced (Protocol) | G7: Efectivo | H7: 850
B8: 45307 | C8: 1221872685 | D8: 2 | E8: Claudia Arrecis | F8: Avene agua termal | G8: Efectivo | H8: 580
B9: 45307 | C9: 2186233116 | D9: 1 | E9: Olga Lucia Torres De Tercero | F9: Frasco de protocol colageno con acido hialuronico | G9: Credomatic | H9: 550
B10: 45309 | C10: 2259435610 | D10: 2 | E10: Vilma Brown Ochoa | F10: Frasco de capsulas heliocare Ultra-D | G10: Efectivo | H10: 900
B11: 45315 | C11: 4134423119 | D11: 1 | E11: Claudia Maria De León | F11: Beauty collagen advanced (Protocol) | G11: Visa | H11: 850
B12: 45315 | C12: 4134423119 | D12: 1 | E12: Claudia Maria De León | F12: Protecto solar gel oil-freee 360 (Heliocare) | G12: Visa | H12: 420
B13: 45322 | C13: 1725254502 | D13: 1 | E13: Jose Palacios | F13: Crema daeses (Sesderma) | G13: Credomatic | H13: 880
B14: 45327 | C14: 1349075359 | D14: 1 | E14: Maritza Lopez | F14: Xxtralash | G14: Credomatic | H14: 850
... B170: 45646 | C170: 2668052871 | D170: 1 | E170: Edna Dubon | F170: Mascara by Dabalash | G170: Credomatic | H170: 250
E171: Total | H171: =SUM(H3:H170) -> 111886.97

Sheet Acido hialuronico
A1: Acido hialuronico | B1: Fecha | C1: No. de Factura | D1: Cantidad | E1: Nombre del Paciente | F1: Tratamiento | G1: Forma de Pago | H1: Total
B3: 45329 | C3: 1305628463 | D3: 1 | E3: Cecilia Guerrero | F3: Aplicación de acido hialuronico | G3: Credomatic | H3: 3000
B4: 45349 | C4: 2784511046 | D4: 1 | E4: Carolina Orellana | F4: Aplicación acido hialuronico nariz | G4: Credomatic | H4: 3000
B5: 45357 | C5: 1820083695 | D5: 1 | E5: Marcela Salazar | F5: Aplicación de acido hialuronico nariz | G5: Efectivo | H5: 2900
B6: 45357 | C6: 3603776325 | D6: 1 | E6: Claudia Eugenia Alburez | F6: Apliación de acido hiluronio surcos | G6: Visa | H6: 3000
B7: 45370 | C7: 85806448 | D7: 1 | E7: Sandra De Fain | F7: Abono aplicación de acido hialuronico menton | G7: Credomatic | H7: 2360
B8: 45370 | C8: 85806448 | D8: 1 | E8: Sandra De Fain | F8: Cancelación aplicación de acido hialuronico menton | G8: Efectivo $ | H8: 140
B9: 45370 | C9: 85806448 | D9: 1 | E9: Sandra De Fain | F9: Aplicación de acido hialuronico surcos | G9: Efectivo $ | H9: 2900
B10: 45370 | C10: 2385464532 | D10: 1 | E10: Ana Maria Lopez De Perez | F10: Aplicación acido hialorunico labios | G10: Visa | H10: 2800
B11: 45370 | C11: 3223601791 | D11: 1 | E11: Aisha Sanchez | F11: Aplicación acido hialorunico labios | G11: Visa | H11: 2800
B12: 45383 | C12: 571951273 | D12: 1 | E12: Ada Briceño | F12: Aplicación acido hialuronico nariz | G12: Visa | H12: 3000
B13: 45383 | C13: 571951273 | D13: 1 | E13: Ada Briceño | F13: Aplicación acido hialuronico surco | G13: Visa | H13: 3000
B14: 45384 | C14: 173884984 | D14: 3 | E14: Ruth Sazo | F14: Aplicación acido hialuronico manos | G14: Visa | H14: 8100
... B31: 45512 | C31: 1190873165 | D31: 1 | E31: Sol Lopez | F31: Aplicación acido hialuronico labios | G31: Credomatic | H31: 2800
B32: 22/08/20204 | C32: 1199655280 | D32: 1 | E32: Sara Bolaños | F32: Aplicación acido hialuronico surcos | G32: Efectivo | H32: 3500
B33: 45532 | C33: 804668852 | D33: 1 | E33: Melissa Portillo | F33: Aplicación acido hialuronico surcos | G33: Visa | H33: 2800
B34: 45533 | C34: 3663872342 | D34: 1 | E34: Melanie Guerra | F34: Aplicación acido hialuronico ojeras | G34: Visa L. | H34: 3000
B35: 45544 | C35: 1271613573 | D35: 2 | E35: Andrea Dougherty | F35: Aplicación acido hialuronico manos | G35: Visa | H35: 5000
B36: 45545 | C36: 1401375998 | D36: 1 | E36: Mabby Morales | F36: Aplicación acido hialuronico nariz | G36: Visa | H36: 3000
B37: 45546 | C37: 1064910985 | D37: 1 | E37: Lucrecia Gonzalez | F37: Aplicación acido hialuronico ojeras | G37: Credomatic | H37: 3000
B38: 45546 | C38: 1129333725 | D38: 1 | E38: Virginia Castillo | F38: Aplicación acido hialuronico labios | G38: Visa | H38: 2800
B39: 45546 | C39: 1129333725 | D39: 1 | E39: Virginia Castillo | F39: Aplicación acido hialuronico pomulos | G39: Visa | H39: 3000
B40: 45554 | C40: 1348027477 | D40: 1 | E40: Lidia Coronado | F40: Aplicación de acido hialuronico labios | G40: Credomatic | H40: 2800
B41: 45554 | C41: 2768388204 | D41: 2 | E41: Ruth Sazo | F41: Aplicación acido hialuronico manos | G41: Visa | H41: 5000
B42: 45559 | C42: 2260618812 | D42: 1 | E42: Wendy Serrano de Quintana | F42: Aplicación de acido hialuronico ojeras | G42: Deposito | H42: 3000
B43: 45572 | C43: 106120757 | D43: 1 | E43: Lidia Coronado | F43: Aplicación de acido hialuronico | G43: Visa | H43: 1350
B44: 45572 | C44: 2708360389 | D44: 2 | E44: Doris Pozadas | F44: Aplicación de acido hialuronico pomulos | G44: Visa | H44: 5800
... B68: 45642 | C68: 2150059189 | D68: 1 | E68: Ana Paola Solates | F68: Aplicación acido hialuronico labios | G68: Visa | H68: 2800
E69: Total | H69: =SUM(H3:H68) -> 259696

Sheet Depilación
A1: Depilación | B1: Fecha | C1: No. de Factura | D1: Cantidad | E1: Nombre del Paciente | F1: Tratamiento | G1: Forma de Pago | H1: Total
B3: 45299 | C3: 1796296041 | D3: 4 | E3: Michelle Muñoz | F3: Depilación axila | G3: Visa L. | H3: 700
B4: 45303 | C4: 2664123217 | D4: 4 | E4: Maria Elena Gonzalez | F4: Depilación bikini | G4: Efectivo | H4: 925
B5: 45303 | C5: 2664123217 | D5: 4 | E5: Maria Elena Gonzalez | F5: Depilación axila | G5: Efectivo | H5: 700
B6: 45303 | C6: 2664123217 | D6: 4 | E6: Maria Elena Gonzalez | F6: Depilación bigote | G6: Efectivo | H6: 600
B7: 45306 | C7: 2969323793 | D7: 4 | E7: Ivanna Leticia Flores | F7: Depilación glúteos | G7: Visa L. | H7: 800
B8: 45321 | C8: 1497121117 | D8: 4 | E8: Maria Veliz Ortega | F8: Depilación bikini | G8: Visa L. | H8: 925
B9: 45348 | C9: 967132962 | D9: 4 | E9: Sherlee Perez | F9: Depilación bikini | G9: Visa | H9: 925
B10: 45350 | C10: 1167212614 | D10: 4 | E10: Aura Estela Herrera | F10: Depilación bigote y menton | G10: Cheque | H10: 700
B11: 45364 | C11: 983714375 | D11: 4 | E11: Adriana Caceres | F11: Depilación piernas | G11: Credomatic | H11: 1250
B12: 45364 | C12: 983714375 | D12: 4 | E12: Adriana Caceres | F12: Depilación axila | G12: Credomatic | H12: 700
B13: 45371 | C13: 3505670277 | D13: 2 | E13: Ivanna Flores | F13: Depilación rostro completo | G13: Visa L. | H13: 500
B14: 45371 | C14: 3505670277 | D14: 2 | E14: Ivanna Flores | F14: Depilación brazos | G14: Visa L. | H14: 625
... B61: 45523 | C61: 1344160453 | D61: 4 | E61: Ximena Ventura | F61: Depilación espalda | G61: Visa | H61: 1000
B62: 22/08/20204 | C62: 1092043841 | D62: 4 | E62: Gabriel Lozano | F62: Depilación interglutea | G62: Visa L. | H62: 700
B63: 45530 | C63: 3222487896 | D63: 4 | E63: Daylin Noemi Arevalo | F63: Depilación piernas | G63: Deposito | H63: 1250
B64: 45530 | C64: 3222487896 | D64: 4 | E64: Daylin Noemi Arevalo | F64: Depilación axila | G64: Deposito | H64: 700
B65: 45530 | C65: 3222487896 | D65: 4 | E65: Daylin Noemi Arevalo | F65: Depilación bikini | G65: Deposito | H65: 925
B66: 45530 | C66: 3222487896 | D66: 4 | E66: Daylin Noemi Arevalo | F66: Depilación espalda baja | G66: Deposito | H66: 1025
B67: 45530 | C67: 3222487896 | D67: 4 | E67: Daylin Noemi Arevalo | F67: Depilación rostro completo | G67: Deposito | H67: 1000
B68: 45530 | C68: 3222487896 | D68: 4 | E68: Daylin Noemi Arevalo | F68: Depilación línea de abdomen | G68: Deposito | H68: 600
B69: 45531 | C69: 2991214010 | D69: 2 | E69: Sonia Marisol Yol | F69: Depilación piernas | G69: Credomatic | H69: 625
B70: 45531 | C70: 2991214010 | D70: 2 | E70: Sonia Marisol Yol | F70: Depilación axila | G70: Credomatic | H70: 350
B71: 45531 | C71: 2991214010 | D71: 4 | E71: Sonia Marisol Yol | F71: Depilación rostro completo | G71: Credomatic | H71: 1000
B72: 45531 | C72: 2991214010 | D72: 4 | E72: Dilsia Revolorio | F72: Depilación piernas | G72: Credomatic | H72: 1250
B73: 45531 | C73: 2991214010 | D73: 4 | E73: Dilsia Revolorio | F73: Depilación bikini | G73: Credomatic | H73: 975
B74: 45531 | C74: 2991214010 | D74: 4 | E74: Dilsia Revolorio | F74: Depilación axila | G74: Credomatic | H74: 700
... B106: 45645 | C106: 4025501645 | D106: 4 | E106: Ana Elisa Gonzalez | F106: Depilación bikini | G106: Visa L. | H106: 975
E107: Total | H107: =SUM(H3:H106) -> 88154

Sheet PRESENTACIÓN DE RESULTADOS
A1: Tratamiendo | B1: Enero | C1: Febrero | D1: Marzo | E1: Abril | F1: Mayo | G1: Junio | H1: Julio | I1: Agosto | J1: Septiembre | K1: Octubre | L1: Noviembre | M1: Diciembre | N1: Total
A2: Producto | B2: =SUM(Producto!H3:H13) -> 9230 | C2: =SUM(Producto!H14:H28) -> 11627.72 | D2: =SUM(Producto!H29:H43) -> 7836 | E2: =SUM(Producto!H44:H63) -> 11530 | F2: =SUM(Producto!H64:H71) -> 4560 | G2: =SUM(Producto!H72:H85) -> 10550 | H2: =SUM(Producto!H86:H105) -> 11670 | I2: =SUM(Producto!H106:H116) -> 8430 | J2: =SUM(Producto!H117:H125) -> 6000 | K2: =SUM(Producto!H126:H140) -> 11100 | L2: =SUM(Producto!H141:H164) -> 14305.25 | M2: =SUM(Producto!H165:H170) -> 5048 | N2: =SUM(B2:M2) -> 111886.97 | O2: =+Producto!H171 -> 111886.97 | P2: =+O2-N2 -> 0
A3: Acido hialuronico | B3: 0 | C3: =SUM('Acido hialuronico'!H3:H4) -> 6000 | D3: =SUM('Acido hialuronico'!H5:H11) -> 16900 | E3: =SUM('Acido hialuronico'!H12:H17) -> 26200 | F3: =SUM('Acido hialuronico'!H18) -> 2800 | G3: 0 | H3: =SUM('Acido hialuronico'!H19:H26) -> 24400 | I3: =SUM('Acido hialuronico'!H27:H34) -> 25400 | J3: =SUM('Acido hialuronico'!H35:H42) -> 27600 | K3: =SUM('Acido hialuronico'!H43:H54) -> 43750 | L3: =SUM('Acido hialuronico'!H55:H65) -> 81046 | M3: =SUM('Acido hialuronico'!H66:H68) -> 5600 | N3: =SUM(B3:M3) -> 259696 | O3: =+'Acido hialuronico'!H69 -> 259696 | P3: =+O3-N3 -> 0
A4: Depilación | B4: =SUM(Depilación!H3:H8) -> 4650 | C4: =SUM(Depilación!H9:H10) -> 1625 | D4: =SUM(Depilación!H11:H17) -> 4512.5 | E4: =SUM(Depilación!H18:H26) -> 8395 | F4: =SUM(Depilación!H27:H42) -> 13429 | G4: =SUM(Depilación!H43:H49) -> 6462.5 | H4: =SUM(Depilación!H50:H59) -> 9825 | I4: =SUM(Depilación!H60:H79) -> 16204 | J4: =SUM(Depilación!H80:H83) -> 3900 | K4: =SUM(Depilación!H84:H90) -> 6300 | L4: =SUM(Depilación!H91:H98) -> 7097 | M4: =SUM(Depilación!H99:H106) -> 5754 | N4: =SUM(B4:M4) -> 88154 | O4: =+Depilación!H107 -> 88154 | P4: =+O4-N4 -> 0
A5: Emsculpt | B5: =SUM(Emsculpt!H3:H4) -> 13500 | C5: =SUM(Emsculpt!H5:H9) -> 33750 | D5: =SUM(Emsculpt!H10) -> 6750 | E5: =SUM(Emsculpt!H11:H13) -> 18000 | F5: =SUM(Emsculpt!H14:H16) -> 13750 | G5: =SUM(Emsculpt!H17:H22) -> 33750 | H5: 0 | I5: =SUM(Emsculpt!H23) -> 6750 | J5: 0 | K5: =SUM(Emsculpt!H24) -> 6750 | L5: 0 | M5: 0 | N5: =SUM(B5:M5) -> 133000 | O5: =+Emsculpt!H25 -> 133000 | P5: =+O5-N5 -> 0
A6: Emtone | B6: =SUM(Emtone!H3) -> 5000 | C6: =SUM(Emtone!H4:H6) -> 10525 | D6: =SUM(Emtone!H7:H8) -> 10000 | E6: =SUM(Emtone!H9:H10) -> 11000 | F6: =SUM(Emtone!H11:H14) -> 19000 | G6: =SUM(Emtone!H15:H17) -> 15000 | H6: =SUM(Emtone!H18:H21) -> 20000 | I6: =SUM(Emtone!H22:H24) -> 10950 | J6: =SUM(Emtone!H25:H27) -> 12500 | K6: =SUM(Emtone!H28:H33) -> 20000 | L6: =SUM(Emtone!H34:H35) -> 10000 | M6: =SUM(Emtone!H36) -> 5000 | N6: =SUM(B6:M6) -> 148975 | O6: =+Emtone!H51 -> 148975 | P6: =+O6-N6 -> 0
A7: Exilis | B7: =SUM(Exilis!H3:H9) -> 45500 | C7: =SUM(Exilis!H10:H17) -> 39890.54 | D7: =SUM(Exilis!H18:H19) -> 9750 | E7: =SUM(Exilis!H20:H26) -> 45500 | F7: =SUM(Exilis!H27:H36) -> 52375 | G7: =SUM(Exilis!H37:H44) -> 33600 | H7: =SUM(Exilis!H45:H46) -> 3800 | I7: =SUM(Exilis!H47:H52) -> 19237 | J7: =SUM(Exilis!H53:H57) -> 23300 | K7: =SUM(Exilis!H58:H62) -> 23500 | L7: =SUM(Exilis!H63:H67) -> 19500 | M7: =SUM(Exilis!H68:H70) -> 16250 | N7: =SUM(B7:M7) -> 332202.54 | O7: =+Exilis!H79 -> 332202.54 | P7: =+O7-N7 -> 0
A8: Exfoliación | B8: 0 | C8: 0 | D8: 0 | E8: 0 | F8: 0 | G8: 0 | H8: 0 | I8: 0 | J8: 0 | K8: 0 | L8: 0 | M8: 0 | N8: =SUM(B8:M8) -> 0 | O8: =+Exfoliación!H4 -> 0 | P8: =+O8-N8 -> 0
A9: Facial purificante | B9: =SUM('Facial purificante'!H3:H5) -> 3075 | C9: =SUM('Facial purificante'!H6:H9) -> 2175 | D9: =SUM('Facial purificante'!H10:H12) -> 1750 | E9: =SUM('Facial purificante'!H13:H16) -> 1600 | F9: =SUM('Facial purificante'!H17:H20) -> 2875 | G9: =SUM('Facial purificante'!H21:H29) -> 9165 | H9: =SUM('Facial purificante'!H30) -> 575 | I9: =SUM('Facial purificante'!H31:H35) -> 2875 | J9: =SUM('Facial purificante'!H36) -> 575 | K9: =SUM('Facial purificante'!H37:H43) -> 4000 | L9: =SUM('Facial purificante'!H44:H47) -> 1782.5 | M9: =SUM('Facial purificante'!H48:H51) -> 2750 | N9: =SUM(B9:M9) -> 33197.5 | O9: =+'Facial purificante'!H78 -> 33197.5 | P9: =+O9-N9 -> 0
A10: Hifu microson | B10: =SUM(Hifu!H3) -> 3000 | C10: =SUM(Hifu!H4) -> 3000 | D10: 0 | E10: =SUM(Hifu!H5) -> 3000 | F10: =SUM(Hifu!H6) -> 3000 | G10: =SUM(Hifu!H7) -> 3000 | H10: =SUM(Hifu!H8:H10) -> 6000 | I10: =SUM(Hifu!H11:H14) -> 12000 | J10: 0 | K10: 0 | L10: 0 | M10: 0 | N10: =SUM(B10:M10) -> 33000 | O10: =+Hifu!H16 -> 33000 | P10: =+O10-N10 -> 0
A11: Hydrafacial | B11: =SUM(Hydrafacial!H3:H6) -> 7167.6 | C11: =SUM(Hydrafacial!H7) -> 834 | D11: =SUM(Hydrafacial!H8:H10) -> 4502 | E11: =SUM(Hydrafacial!H11) -> 834 | F11: =SUM(Hydrafacial!H12:H19) -> 7077.6 | G11: =SUM(Hydrafacial!H20) -> 1668 | H11: =SUM(Hydrafacial!H21:H22) -> 1794 | I11: =SUM(Hydrafacial!H23:H27) -> 5902 | J11: =SUM(Hydrafacial!H28:H30) -> 3252 | K11: =SUM(Hydrafacial!H31:H33) -> 2502 | L11: =SUM(Hydrafacial!H34:H37) -> 4317.8 | M11: =SUM(Hydrafacial!H38:H42) -> 5402 | N11: =SUM(B11:M11) -> 45253 | O11: =+Hydrafacial!H53 -> 45253 | P11: =+O11-N11 -> 0
A12: Laboratorios | B12: =SUM(Laboratorios!H3) -> 750 | C12: 0 | D12: 0 | E12: 0 | F12: 0 | G12: =SUM(Laboratorios!H4) -> 1200 | H12: 0 | I12: =SUM(Laboratorios!H5) -> 1200 | J12: =SUM(Laboratorios!H6) -> 1200 | K12: =SUM(Laboratorios!H7) -> 1200 | L12: 0 | M12: 0 | N12: =SUM(B12:M12) -> 5550 | O12: =+Laboratorios!H18 -> 5550 | P12: =+O12-N12 -> 0
A13: Masaje linfatico | B13: =SUM('Masaje linfatico'!H3:H5) -> 4200 | C13: =SUM('Masaje linfatico'!H6:H10) -> 8899.9999 | D13: =SUM('Masaje linfatico'!H11) -> 200 | E13: =SUM('Masaje linfatico'!H12:H18) -> 4800 | F13: =SUM('Masaje linfatico'!H19:H22) -> 7200 | G13: =SUM('Masaje linfatico'!H23:H24) -> 4500 | H13: =SUM('Masaje linfatico'!H25) -> 2000 | I13: =SUM('Masaje linfatico'!H26:H27) -> 1600 | J13: =SUM('Masaje linfatico'!H28:H29) -> 1250 | K13: 0 | L13: =SUM('Masaje linfatico'!H30:H35) -> 2100 | M13: =SUM('Masaje linfatico'!H36:H38) -> 600 | N13: =SUM(B13:M13) -> 37350 | O13: =+'Masaje linfatico'!H58 -> 37350 | P13: =+O13-N13 -> 0
A14: Mesoterapia | B14: =SUM(Mesoterapia!H3) -> 3120 | C14: =SUM(Mesoterapia!H4) -> 5500 | D14: =SUM(Mesoterapia!H5:H8) -> 10986 | E14: =SUM(Mesoterapia!H9:H11) -> 9184 | F14: =SUM(Mesoterapia!H12) -> 3800 | G14: =SUM(Mesoterapia!H13:H14) -> 1440 | H14: =SUM(Mesoterapia!H15:H18) -> 6446 | I14: =SUM(Mesoterapia!H19:H20) -> 7000 | J14: =SUM(Mesoterapia!H21:H25) -> 18940 | K14: =SUM(Mesoterapia!H26:H29) -> 14060 | L14: =SUM(Mesoterapia!H30:H31) -> 5500 | M14: =SUM(Mesoterapia!H32) -> 2000 | N14: =SUM(B14:M14) -> 87976 | O14: =+Mesoterapia!H33 -> 87976 | P14: =+O14-N14 -> 0
A15: Morpheus | B15: =SUM(Morpheus!H3:H6) -> 40000 | C15: =SUM(Morpheus!H7:H18) -> 114460 | D15: =SUM(Morpheus!H19:H27) -> 73500 | E15: =SUM(Morpheus!H28) -> 10000 | F15: =SUM(Morpheus!H29:H33) -> 40000 | G15: =SUM(Morpheus!H34:H43) -> 104000 | H15: =SUM(Morpheus!H44:H51) -> 92500 | I15: =SUM(Morpheus!H52:H54) -> 30000 | J15: =SUM(Morpheus!H55:H60) -> 45000 | K15: =SUM(Morpheus!H61:H65) -> 45000 | L15: =SUM(Morpheus!H66:H72) -> 65000 | M15: =SUM(Morpheus!H73:H78) -> 55000 | N15: =SUM(B15:M15) -> 714460 | O15: =+Morpheus!H82 -> 714460 | P15: =+O15-N15 -> 0
A16: Pico-láser | B16: 0 | C16: 0 | D16: 0 | E16: 0 | F16: 0 | G16: 0 | H16: 0 | I16: 0 | J16: 0 | K16: 0 | L16: 0 | M16: 0 | N16: =SUM(B16:M16) -> 0 | O16: =+'Pico-láser'!H6 -> 0 | P16: =+O16-N16 -> 0
A17: Profhilo | B17: =SUM(Profhilo!H3:H9) -> 32500 | C17: 0 | D17: =SUM(Profhilo!H10) -> 5000 | E17: =SUM(Profhilo!H11) -> 5000 | F17: =SUM(Profhilo!H12) -> 5000 | G17: 0 | H17: =SUM(Profhilo!H13) -> 5000 | I17: =SUM(Profhilo!H14:H17) -> 20000 | J17: =SUM(Profhilo!H18:H22) -> 20000 | K17: =SUM(Profhilo!H23:H27) -> 20000 | L17: =SUM(Profhilo!H28) -> 5000 | M17: =SUM(Profhilo!H29) -> 5000 | N17: =SUM(B17:M17) -> 122500 | O17: =+Profhilo!H30 -> 122500 | P17: =+O17-N17 -> 0
A18: PRP | B18: =SUM(PRP!H3:H13) -> 23400 | C18: =SUM(PRP!H14:H20) -> 14120 | D18: =SUM(PRP!H21:H32) -> 22300 | E18: =SUM(PRP!H33:H59) -> 42400 | F18: =SUM(PRP!H60:H79) -> 42760 | G18: =SUM(PRP!H80:H85) -> 16400 | H18: =SUM(PRP!H86:H91) -> 11500 | I18: =SUM(PRP!H92:H106) -> 30300 | J18: =SUM(PRP!H107:H114) -> 20100 | K18: =SUM(PRP!H115:H121) -> 12860 | L18: =SUM(PRP!H122:H130) -> 17900 | M18: =SUM(PRP!H131:H146) -> 50200 | N18: =SUM(B18:M18) -> 304240 | O18: =+PRP!H147 -> 304240 | P18: =+O18-N18 -> 0
A19: Radiofrecuencia | B19: =SUM(Radiofrecuencia!H3:H9) -> 17670 | C19: =SUM(Radiofrecuencia!H10:H13) -> 11325.5 | D19: =SUM(Radiofrecuencia!H14) -> 1780 | E19: =SUM(Radiofrecuencia!H15:H16) -> 3560 | F19: =SUM(Radiofrecuencia!H17:H21) -> 16710 | G19: =SUM(Radiofrecuencia!H22:H27) -> 13408 | H19: =SUM(Radiofrecuencia!H28) -> 10680 | I19: =SUM(Radiofrecuencia!H29:H31) -> 9180 | J19: =SUM(Radiofrecuencia!H32:H33) -> 3700 | K19: =SUM(Radiofrecuencia!H34:H40) -> 39776 | L19: =SUM(Radiofrecuencia!H41:H43) -> 8900 | M19: =SUM(Radiofrecuencia!H44:H49) -> 20600 | N19: =SUM(B19:M19) -> 157289.5 | O19: =+Radiofrecuencia!H50 -> 157289.5 | P19: =+O19-N19 -> 0
A20: Ultrasonido | B20: =SUM(Ultrasonido!H3:H4) -> 2700 | C20: =SUM(Ultrasonido!H5:H7) -> 5400 | D20: =SUM(Ultrasonido!H8) -> 900 | E20: =SUM(Ultrasonido!H9:H10) -> 2700 | F20: =SUM(Ultrasonido!H11:H13) -> 4680 | G20: 0 | H20: =SUM(Ultrasonido!H14) -> 1200 | I20: 0 | J20: 0 | K20: =SUM(Ultrasonido!H15) -> 1800 | L20: =SUM(Ultrasonido!H16) -> 900 | M20: =SUM(Ultrasonido!H17) -> 1440 | N20: =SUM(B20:M20) -> 21720 | O20: =+Ultrasonido!H18 -> 21720 | P20: =+O20-N20 -> 0
A21: Velo de acido hialuronico | B21: 0 | C21: 0 | D21: 0 | E21: 0 | F21: 0 | G21: 0 | H21: 0 | I21: 0 | J21: 0 | K21: 0 | L21: 0 | M21: =SUM('Velo de acido hialuronico'!H3:H4) -> 1300 | N21: =SUM(B21:M21) -> 1300 | O21: =+'Velo de acido hialuronico'!H5 -> 1300 | P21: =+O21-N21 -> 0
A22: Velox | B22: 0 | C22: 0 | D22: =SUM(Velox!H3) -> 3500 | E22: 0 | F22: =SUM(Velox!H4:H6) -> 9040 | G22: =SUM(Velox!H7:H9) -> 7910 | H22: 0 | I22: 0 | J22: 0 | K22: 0 | L22: 0 | M22: 0 | N22: =SUM(B22:M22) -> 20450 | O22: =+Velox!H10 -> 20450 | P22: =+O22-N22 -> 0
A23: Vitamina C intravenosa | B23: =SUM('Vitamina C intravenosa'!H3:H14) -> 12840 | C23: =SUM('Vitamina C intravenosa'!H15:H25) -> 13316 | D23: =SUM('Vitamina C intravenosa'!H26:H31) -> 6285 | E23: =SUM('Vitamina C intravenosa'!H32:H50) -> 18031 | F23: =SUM('Vitamina C intravenosa'!H51:H56) -> 7866 | G23: =SUM('Vitamina C intravenosa'!H57:H69) -> 15515 | H23: =SUM('Vitamina C intravenosa'!H70:H78) -> 12630 | I23: =SUM('Vitamina C intravenosa'!H79:H95) -> 15356 | J23: =SUM('Vitamina C intravenosa'!H96:H105) -> 10541 | K23: =SUM('Vitamina C intravenosa'!H106:H122) -> 13246 | L23: =SUM('Vitamina C intravenosa'!H123:H131) -> 7485 | M23: =SUM('Vitamina C intravenosa'!H132:H145) -> 12295 | N23: =SUM(B23:M23) -> 145406 | O23: =+'Vitamina C intravenosa'!H146 -> 145406 | P23: =+O23-N23 -> 0
A24: Ciclo coolsculpting | B24: 0 | C24: =SUM('Ciclo coolsculpting'!H3) -> 9000 | D24: =SUM('Ciclo coolsculpting'!H4:H5) -> 27000 | E24: 0 | F24: 0 | G24: 0 | H24: =SUM('Ciclo coolsculpting'!H6) -> 9000 | I24: 0 | J24: 0 | K24: 0 | L24: 0 | M24: 0 | N24: =SUM(B24:M24) -> 45000 | O24: =+'Ciclo coolsculpting'!H7 -> 45000 | P24: =+O24-N24 -> 0
A25: Dermapen | B25: 0 | C25: =SUM(Dermapen!H3) -> 3000 | D25: 0 | E25: 0 | F25: 0 | G25: =SUM(Dermapen!H4) -> 3600 | H25: =SUM(Dermapen!H5) -> 3600 | I25: 0 | J25: 0 | K25: 0 | L25: 0 | M25: 0 | N25: =SUM(B25:M25) -> 10200 | O25: =+Dermapen!H6 -> 10200 | P25: =+O25-N25 -> 0
A26: Láser CO2 | B26: 0 | C26: 0 | D26: =SUM('Láser CO2'!H3) -> 6500 | E26: =SUM('Láser CO2'!H4) -> 1800 | F26: 0 | G26: 0 | H26: =SUM('Láser CO2'!H5:H6) -> 6000 | I26: 0 | J26: =SUM('Láser CO2'!H7) -> 6000 | K26: 0 | L26: =SUM('Láser CO2'!H8) -> 5000 | M26: 0 | N26: =SUM(B26:M26) -> 25300 | O26: =+'Láser CO2'!H9 -> 25300 | P26: =+O26-N26 -> 0
A27: Masaje relajante | B27: =SUM('Masaje relajante'!H3:H4) -> 2850 | C27: =SUM('Masaje relajante'!H5) -> 3000 | D27: 0 | E27: =SUM('Masaje relajante'!H6:H7) -> 700 | F27: =SUM('Masaje relajante'!H8:H10) -> 1050 | G27: =SUM('Masaje relajante'!H11:H14) -> 7750 | H27: =SUM('Masaje relajante'!H15) -> 250 | I27: =SUM('Masaje relajante'!H16:H19) -> 2050 | J27: =SUM('Masaje relajante'!H20) -> 350 | K27: =SUM('Masaje relajante'!H21:H22) -> 1950 | L27: =SUM('Masaje relajante'!H23) -> 1500 | M27: =SUM('Masaje relajante'!H24) -> 3500 | N27: =SUM(B27:M27) -> 24950 | O27: =+'Masaje relajante'!H25 -> 24950 | P27: =+O27-N27 -> 0
A28: Oligoelementos | B28: 0 | C28: 0 | D28: 0 | E28: 0 | F28: 0 | G28: 0 | H28: 0 | I28: 0 | J28: 0 | K28: 0 | L28: 0 | M28: =SUM(Oligoelementos!H3) -> 1400 | N28: =SUM(B28:M28) -> 1400 | O28: =+Oligoelementos!H4 -> 1400 | P28: =+O28-N28 -> 0
A29: Grow | B29: =SUM(Grow!H3:H5) -> 7912.09 | C29: =SUM(Grow!H6:H9) -> 9112.09 | D29: =SUM(Grow!H10:H12) -> 7912.09 | E29: =SUM(Grow!H13:H15) -> 7912.09 | F29: =SUM(Grow!H16:H18) -> 7912.09 | G29: =SUM(Grow!H19:H21) -> 7912.09 | H29: =SUM(Grow!H22:H24) -> 7912.09 | I29: =SUM(Grow!H25:H27) -> 7912.09 | J29: =SUM(Grow!H28:H30) -> 7912.09 | K29: =SUM(Grow!H31:H33) -> 7912.09 | L29: =SUM(Grow!H34:H36) -> 7912.09 | M29: =SUM(Grow!H37:H39) -> 7912.09 | N29: =SUM(B29:M29) -> 96145.08 | O29: =+Grow!H40 -> 96145.08 | P29: =+O29-N29 -> 0
A30: Abonos | B30: 0 | C30: 0 | D30: =SUM('Abonos a tratamientos'!H3) -> 1000 | E30: 0 | F30: 0 | G30: 0 | H30: 0 | I30: 0 | J30: 0 | K30: 0 | L30: 0 | M30: 0 | N30: =SUM(B30:M30) -> 1000 | O30: =+'Abonos a tratamientos'!H4 -> 1000 | P30: =+O30-N30 -> 0
A31: Celulas madre | B31: =SUM('Celulas madre'!H3) -> 17750 | C31: 0 | D31: 0 | E31: 0 | F31: 0 | G31: =SUM('Celulas madre'!H4) -> 17750 | H31: 0 | I31: =SUM('Celulas madre'!H5) -> 25838 | J31: =SUM('Celulas madre'!H6) -> 23160 | K31: =SUM('Celulas madre'!H7) -> 23160 | L31: 0 | M31: 0 | N31: =SUM(B31:M31) -> 107658 | O31: =+'Celulas madre'!H12 -> 107658 | P31: =+O31-N31 -> 0
A32: Peeling | B32: 0 | C32: 0 | D32: 0 | E32: =SUM(Peeling!H3:H5) -> 5500 | F32: =SUM(Peeling!H6:H7) -> 6350 | G32: =SUM(Peeling!H8) -> 3800 | H32: =SUM(Peeling!H9:H12) -> 5050 | I32: =SUM(Peeling!H13) -> 450 | J32: =SUM(Peeling!H14:H22) -> 5245 | K32: =SUM(Peeling!H23:H24) -> 2600 | L32: 0 | M32: =SUM(Peeling!H25) -> 800 | N32: =SUM(B32:M32) -> 29795 | O32: =+Peeling!H29 -> 29795 | P32: =+O32-N32 -> 0
A33: Spectra ginecologico | B33: 0 | C33: 0 | D33: 0 | E33: =SUM('Spectra ginecologico'!H3:H5) -> 18000 | F33: 0 | G33: 0 | H33: =SUM('Spectra ginecologico'!H6) -> 6000 | I33: =SUM('Spectra ginecologico'!H7:H8) -> 5500 | J33: =SUM('Spectra ginecologico'!H9:H10) -> 2900 | K33: =SUM('Spectra ginecologico'!H11:H13) -> 1400 | L33: 0 | M33: 0 | N33: =SUM(B33:M33) -> 33800 | O33: =+'Spectra ginecologico'!H32 -> 33800 | P33: =+O33-N33 -> 0
A34: Elimación de lunares | B34: 0 | C34: 0 | D34: 0 | E34: 0 | F34: 0 | G34: 0 | H34: 0 | I34: 0 | J34: 0 | K34: 0 | L34: 0 | M34: 0 | N34: =SUM(B34:M34) -> 0 | O34: =+'Eliminación de lunares'!H4:H4 -> 0 | P34: =+O34-N34 -> 0
A35: Botox | B35: =SUM(Botox!H3:H4) -> 4345 | C35: =SUM(Botox!H5:H6) -> 5720 | D35: =SUM(Botox!H7:H115) -> 230505 | E35: 0 | F35: 0 | G35: 0 | H35: =SUM(Botox!H116:H210) -> 195915 | I35: =SUM(Botox!H211:H213) -> 14740 | J35: =SUM(Botox!H214:H221) -> 14630 | K35: =SUM(Botox!H222:H223) -> 4455 | L35: =SUM(Botox!H224:H348) -> 280350 | M35: 0 | N35: =SUM(B35:M35) -> 750659.99 | O35: =+Botox!H349 -> 750659.99 | P35: =+O35-N35 -> 0
A36: Encimas | B36: 0 | C36: 0 | D36: 0 | E36: 0 | F36: 0 | G36: 0 | H36: 0 | I36: 0 | J36: 0 | K36: 0 | L36: 0 | M36: 0 | N36: =SUM(B36:M36) -> 0 | O36: =+Encimas!H4 -> 0 | P36: =+O36-N36 -> 0
A37: Cambio de tratamiento | B37: 0 | C37: =SUM('Cambio de tratamiento'!H3) -> 1500 | D37: 0 | E37: 0 | F37: 0 | G37: 0 | H37: 0 | I37: 0 | J37: 0 | K37: 0 | L37: 0 | M37: 0 | N37: =SUM(B37:M37) -> 1500 | O37: =+'Cambio de tratamiento'!H8 -> 1500 | P37: =+O37-N37 -> 0
A38: Microdermoabrasión | B38: 0 | C38: 0 | D38: 0 | E38: 0 | F38: =SUM(Microdermoabrasión!H3) -> 350 | G38: 0 | H38: 0 | I38: 0 | J38: 0 | K38: 0 | L38: 0 | M38: 0 | N38: =SUM(B38:M38) -> 350 | O38: =+Microdermoabrasión!H5 -> 350 | P38: =+O38-N38 -> 0
A39: Terapia Luminica | B39: 0 | C39: 0 | D39: 0 | E39: 0 | F39: 0 | G39: 0 | H39: 0 | I39: 0 | J39: 0 | K39: 0 | L39: 0 | M39: 0 | N39: =SUM(B39:M39) -> 0 | O39: =+'Terapia Luminica'!H4 -> 0 | P39: =+O39-N39 -> 0
A40: Oscilacion | B40: =SUM(Oscilación!H3:H10) -> 19060 | C40: =SUM(Oscilación!H11:H15) -> 18000 | D40: =SUM(Oscilación!H16:H18) -> 5000 | E40: =SUM(Oscilación!H19:H20) -> 4500 | F40: =SUM(Oscilación!H21:H23) -> 8000 | G40: =SUM(Oscilación!H24:H26) -> 3000 | H40: =SUM(Oscilación!H27:H33) -> 14000 | I40: =SUM(Oscilación!H34:H36) -> 4550 | J40: =SUM(Oscilación!H37) -> 2500 | K40: =SUM(Oscilación!H38:H41) -> 9500 | L40: =SUM(Oscilación!H42) -> 2500 | M40: 0 | N40: =SUM(B40:M40) -> 90610 | O40: =+Oscilación!H53 -> 90610 | P40: =+O40-N40 -> 0
A41: Sueros | B41: =SUM(Sueros!H3:H10) -> 7500 | C41: =SUM(Sueros!H11:H19) -> 10500 | D41: =SUM(Sueros!H20:H25) -> 5000 | E41: =SUM(Sueros!H26:H35) -> 11250 | F41: =SUM(Sueros!H36:H38) -> 3750 | G41: =SUM(Sueros!H39:H47) -> 6900 | H41: =SUM(Sueros!H48:H52) -> 4920 | I41: =SUM(Sueros!H53:H59) -> 7250 | J41: =SUM(Sueros!H60:H67) -> 6750 | K41: =SUM(Sueros!H68:H75) -> 6750 | L41: =SUM(Sueros!H76:H77) -> 1500 | M41: =SUM(Sueros!H78:H83) -> 6000 | N41: =SUM(B41:M41) -> 78070 | O41: =+Sueros!H91 -> 78070 | P41: =+O41-N41 -> 0
A42: Presoterapia | B42: 0 | C42: 0 | D42: 0 | E42: 0 | F42: 0 | G42: 0 | H42: =SUM(Presoterapia!H3) -> 250 | I42: 0 | J42: 0 | K42: 0 | L42: 0 | M42: 0 | N42: =SUM(B42:M42) -> 250 | O42: =+Presoterapia!H6 -> 250 | P42: =+N42-O42 -> 0
A43: Nioo | B43: =SUM(Nioo!H3) -> 3000 | C43: =SUM(Nioo!H4) -> 4368 | D43: 0 | E43: =SUM(Nioo!H5:H7) -> 7488 | F43: 0 | G43: 0 | H43: 0 | I43: 0 | J43: 0 | K43: 0 | L43: 0 | M43: 0 | N43: =SUM(B43:M43) -> 14856 | O43: =+Nioo!H40 -> 14856 | P43: =+N43-O43 -> 0
A44: Sedación | B44: 0 | C44: 0 | D44: 0 | E44: =SUM(Sedación!H3) -> 500 | F44: =SUM(Sedación!H4) -> 400 | G44: =SUM(Sedación!H5) -> 400 | H44: =SUM(Sedación!H6) -> 410 | I44: 0 | J44: 0 | K44: 0 | L44: =SUM(Sedación!H7:H8) -> 800 | M44: =SUM(Sedación!H9) -> 400 | N44: =SUM(B44:M44) -> 2910 | O44: =+Sedación!H10 -> 2910 | P44: =+N44-O44 -> 0
A45: Masaje reflexologia | B45: 0 | C45: =SUM('Masaje reflexologia'!H3) -> 200 | D45: 0 | E45: 0 | F45: 0 | G45: 0 | H45: 0 | I45: 0 | J45: 0 | K45: 0 | L45: 0 | M45: 0 | N45: =SUM(B45:M45) -> 200 | O45: =+'Masaje reflexologia'!H4 -> 200 | P45: =+N45-O45 -> 0
A46: Intrasure post-operatorio | B46: 0 | C46: =SUM('Intrasure post-operatorio'!H3) -> 5000 | D46: =SUM('Intrasure post-operatorio'!H4:H6) -> 12500 | E46: =SUM('Intrasure post-operatorio'!H7:H8) -> 7000 | F46: =SUM('Intrasure post-operatorio'!H9:H11) -> 9500 | G46: =SUM('Intrasure post-operatorio'!H12:H20) -> 30500 | H46: =SUM('Intrasure post-operatorio'!H21:H31) -> 30700 | I46: =SUM('Intrasure post-operatorio'!H32:H35) -> 11800 | J46: =SUM('Intrasure post-operatorio'!H36:H43) -> 28500 | K46: =SUM('Intrasure post-operatorio'!H44:H54) -> 41500 | L46: =SUM('Intrasure post-operatorio'!H55:H59) -> 9000 | M46: =SUM('Intrasure post-operatorio'!H60:H65) -> 19600 | N46: =SUM(B46:M46) -> 205600 | O46: =+'Intrasure post-operatorio'!H66 -> 205600 | P46: =+N46-O46 -> 0
A47: Mascarilla | B47: 0 | C47: =SUM(Mascarilla!H3) -> 650 | D47: =SUM(Mascarilla!H4) -> 150 | E47: 0 | F47: 0 | G47: 0 | H47: 0 | I47: 0 | J47: 0 | K47: 0 | L47: 0 | M47: 0 | N47: =SUM(B47:M47) -> 800 | O47: =SUM(Mascarilla!H5) -> 800 | P47: =+N47-O47 -> 0
A48: Hifu Ultra-forme | B48: 0 | C48: =SUM('Hifu Ultra-forme'!H3) -> 3840 | D48: =SUM('Hifu Ultra-forme'!H4:H8) -> 16200 | E48: =SUM('Hifu Ultra-forme'!H9:H22) -> 38700 | F48: =SUM('Hifu Ultra-forme'!H23:H43) -> 83200 | G48: =SUM('Hifu Ultra-forme'!H44:H45) -> 7500 | H48: =SUM('Hifu Ultra-forme'!H46:H49) -> 36400 | I48: =SUM('Hifu Ultra-forme'!H50:H51) -> 6000 | J48: 0 | K48: =SUM('Hifu Ultra-forme'!H52) -> 10400 | L48: =SUM('Hifu Ultra-forme'!H53:H57) -> 13405 | M48: =SUM('Hifu Ultra-forme'!H58:H61) -> 10400 | N48: =SUM(B48:M48) -> 226045 | O48: =+'Hifu Ultra-forme'!H62 -> 226045 | P48: =+N48-O48 -> 0
A49: Powershape | B49: 0 | C49: 0 | D49: 0 | E49: =SUM(Powershape!H3) -> 4000 | F49: =SUM(Powershape!H4:H6) -> 9800 | G49: =SUM(Powershape!H7:H13) -> 25368 | H49: =SUM(Powershape!H14) -> 5000 | I49: 0 | J49: =SUM(Powershape!H15:H16) -> 8168 | K49: =SUM(Powershape!H17) -> 5460 | L49: =SUM(Powershape!H18:H19) -> 6000 | M49: 0 | N49: =SUM(B49:M49) -> 63796 | O49: =+Powershape!H20 -> 63796 | P49: =+N49-O49 -> 0
A50: Emsculpt NEO | B50: 0 | C50: 0 | D50: 0 | E50: 0 | F50: 0 | G50: 0 | H50: =SUM('Emsculpt NEO'!H3:H6) -> 20000 | I50: =SUM('Emsculpt NEO'!H7:H7) -> 9999.9996 | J50: =SUM('Emsculpt NEO'!H8:H11) -> 20000 | K50: =SUM('Emsculpt NEO'!H12:H15) -> 15000 | L50: =SUM('Emsculpt NEO'!H16:H24) -> 49999.996 | M50: 0 | N50: =SUM(B50:M50) -> 115000 | O50: =+'Emsculpt NEO'!H25 -> 115000 | P50: =+N50-O50 -> 0
A51: Exion | B51: 0 | C51: 0 | D51: 0 | E51: 0 | F51: 0 | G51: 0 | H51: =SUM(Exion!H3:H5) -> 29000 | I51: =SUM(Exion!H6:H12) -> 63000 | J51: =SUM(Exion!H13:H15) -> 18000 | K51: =SUM(Exion!H16:H17) -> 16000 | L51: 0 | M51: 0 | N51: =SUM(B51:M51) -> 126000 | O51: =+Exion!H18 -> 126000 | P51: =+N51-O51 -> 0
P52: =+O52-N52 -> 0
A53: Total | B53: =SUM(B2:B52) -> 290719.69 | C53: =SUM(C2:C52) -> 356338.85 | D53: =SUM(D2:D52) -> 498218.59 | E53: =SUM(E2:E52) -> 329084.09 | F53: =SUM(F2:F52) -> 386234.69 | G53: =SUM(G2:G52) -> 392048.59 | H53: =SUM(H2:H52) -> 594427.09 | I53: =SUM(I2:I52) -> 381474.09 | ... N53: =SUM(N2:N52) -> 4855501.6 | P53: =+O53-N53 -> -4855501.6
B54: =+'[1]Enero 24'!$B$141 -> 290719.59 | C54: =+'[1]Febrero 24'!$B$146 -> 356338.85 | D54: =+'[1]Marzo 24'!$B$217 -> 498218.59 | E54: =+'[1]Abril 24'!$B$159 -> 329084.09 | F54: =+'[1]Mayo 24'!$B$143 -> 386234.69 | G54: =+'[1]Junio 24'!$B$136 -> 392048.59 | H54: =+'[1]Julio 24'!$B$240 -> 594427.09 | I54: =+'[1]Agosto 24'!$B$153 -> 381474.09 | J54: =+'[1]Septiembre 24'!$B$138 -> 341973.09 | K54: =+'[1]Octubre 24'!$B$171 -> 411931.09 | L54: =+'[1]Noviembre 24'!$B$271 -> 628800.64 | M54: =+'[1]Diciembre 24'!$B$111 -> 244251.09
B55: =+B53-B54 -> 0.1 | C55: =+C53-C54 -> -4.9999973e-05 | D55: =+D53-D54 -> -0.00408 | E55: =+E53-E54 -> 0 | F55: =+F53-F54 -> 0 | G55: =+G53-G54 -> 0 | H55: =+H53-H54 -> -0.0037999999 | I55: =+I53-I54 -> -0.00040000008 | ... K55: =+K53-K54 -> 0

Sheet Emsculpt
A1: Emsculpt | B1: Fecha | C1: No. de Factura | D1: Cantidad | E1: Nombre del Paciente | F1: Tratamiento | G1: Forma de Pago | H1: Total
B3: 45307 | C3: 3945351926 | D3: 3 | E3: Karen Orellana | F3: Emsculpt glúteos | G3: Visa L. | H3: 6750
B4: 45315 | C4: 193940475 | D4: 3 | E4: Jennifer Lima | F4: Emsculpt abdomen | G4: Visa | H4: 6750
B5: 45341 | C5: 3320006423 | D5: 3 | E5: Gilma Valdez | F5: Emsculpt glúteos | G5: Credomatic | H5: 6750
B6: 45345 | C6: 3893709192 | D6: 3 | E6: Maria Jose Herrera | F6: Emsculpt abdomen | G6: Visa | H6: 6750
B7: 45349 | C7: 2695384338 | D7: 3 | E7: Melissica Cohen | F7: Emsculpt abdomen | G7: Visa | H7: 6750
B8: 45351 | C8: 1004686758 | D8: 3 | E8: Dulce Mendoza | F8: Emsculpt abdomen | G8: Visa | H8: 6750
B9: 45351 | C9: 1879460739 | D9: 3 | E9: Marisol Coronado | F9: Emsculpt abdomen | G9: Visa | H9: 6750
B10: 45369 | C10: 2710651286 | D10: 3 | E10: Nadia Zimeria Chacama | F10: Emsculpt abdomen | G10: Visa | H10: 6750
B11: 45386 | C11: 3479391061 | D11: 3 | E11: Cesibel Alejos Hidalgo | F11: Emsculpt abdomen | G11: Credomatic | H11: 6750
B12: 45393 | C12: 3140305740 | D12: 3 | E12: Dalia Maribel Diaz De Diaz | F12: Emsculpt triceps | G12: Visa | H12: 4500
B13: 45405 | C13: 1550797207 | D13: 3 | E13: Estefany Marion Villatoro | F13: Emsculpt abdomen | G13: Visa | H13: 6750
B14: 45414 | C14: 139018633 | D14: 3 | E14: Ana Lucia De Robles | F14: Emsculpt abdomen | G14: Deposito | H14: 6750
... B24: 45568 | C24: 3482797528 | D24: 3 | E24: Fabiola De Reyes | F24: Emsculpt glúteos | G24: Visa L. | H24: 6750
E25: Total | H25: =SUM(H3:H24) -> 133000

Sheet Emtone
A1: Emtone | B1: Fecha | C1: No. de Factura | D1: Cantidad | E1: Nombre del Paciente | F1: Tratamiento | G1: Forma de Pago | H1: Total
B3: 45315 | C3: 2555792518 | D3: 8 | E3: Esther Pacheco | F3: Emtone corporal | G3: Deposito | H3: 5000
B4: 45342 | C4: 2195147469 | D4: 8 | E4: Vanessa de Mancilla | F4: Emtone chaparreras, banana roll y parte posterior de la pierna | G4: Visa | H4: 5000
B5: 45344 | C5: 502022384 | D5: 7 | E5: Marcela Duran | F5: Emtone medias piernas completas | G5: Visa | H5: 4830
B6: 45344 | C6: 502022384 | D6: 1 | E6: Marcela Duran | F6: Emtone medias piernas completas | G6: Visa | H6: 695
B7: 45364 | C7: 3967897459 | D7: 8 | E7: Rocio Margarita Molina | F7: Emtone medias piernas completas | G7: Visa | H7: 5000
B8: 45369 | C8: 538726094 | D8: 8 | E8: Cynthia Castillo de Zelaya | F8: Emtone abdomen superior e inferior | G8: Credomatic | H8: 5000
B9: 45384 | C9: 848252474 | D9: 8 | E9: Maggie Villeda | F9: Emtone abdomen y cintura | G9: Visa | H9: 5000
B10: 45400 | C10: 2825798556 | D10: 8 | E10: Maria Ines Verdugo | F10: Emtone medias piernas completas | G10: Visa | H10: 6000
B11: 45414 | C11: 606227387 | D11: 8 | E11: Yanci Palma Ortiz | F11: Emtone abdomen, cintura y parte posterior de la pierna | G11: Visa | H11: 5000
B12: 45426 | C12: 1007568992 | D12: 8 | E12: Marta De Rosales | F12: Emtone medias piernas completas | G12: Visa L. | H12: 5000
B13: 45426 | C13: 1132217046 | D13: 8 | E13: Sergio Rosales | F13: Powershape abdomen, cintura y espalda | G13: Visa L. | H13: 4000
B14: 45429 | C14: 3745074608 | D14: 8 | E14: Jose Estuardo Galvez | F14: Emtone abdomen, cintura y espalda baja | G14: Visa L. | H14: 5000
... B36: 45645 | C36: 4111942926 | D36: 8 | E36: Francias Cuellar | F36: Emtone entrepierna, chaparrera y parte posterior de la pierna | G36: Visa L. | H36: 5000
E51: Total | H51: =SUM(H3:H50) -> 148975

Sheet Exilis
A1: Exilis | B1: Fecha | C1: No. de Factura | D1: Cantidad | E1: Nombre del Paciente | F1: Tratamiento | G1: Forma de Pago | H1: Total
B3: 45296 | C3: 2127908022 | D3: 8 | E3: Margarita Wever | F3: Exilis abdomen y cintura | G3: Visa L. | H3: 6500
B4: 45299 | C4: 1796296041 | D4: 8 | E4: Michelle Muñoz | F4: Exilis abdomen, cintura, espalda completa y parte posterior de la pierna | G4: Visa L. | H4: 6500
B5: 45308 | C5: 3003859790 | D5: 8 | E5: Julia Marina Valdez | F5: Exilis abdomen, cintura y espalda alta | G5: Visa | H5: 6500
B6: 45309 | C6: 1410354994 | D6: 8 | E6: Iris Veronica Aroche | F6: Exilis abdomen completo, cintura y espalda completa | G6: Credomatic | H6: 6500
B7: 45310 | C7: 1306282846 | D7: 8 | E7: José Antonio Corrales | F7: Exilis abdomen, cintura y espalda | G7: Visa L. | H7: 6500
B8: 45314 | C8: 3983101787 | D8: 8 | E8: Silvia Martinez De Garza | F8: Exilis abdomen, cintura, espalda alta y brazos | G8: Visa | H8: 6500
B9: 45322 | C9: 1725254502 | D9: 8 | E9: Jose Palacios | F9: Exilis abdomen, cintura y pectoral | G9: Credomatic | H9: 6500
B10: 45323 | C10: 986597912 | D10: 4 | E10: Gabriela Toledo | F10: Exilis abdomen, cintura y espalda | G10: Credomatic | H10: 3250
B11: 45327 | C11: 3952822158 | D11: 8 | E11: Luis Garrido | F11: Exilis abdomen, cintura y pectoral | G11: Visa | H11: 6500
B12: 45328 | C12: 1239304704 | D12: 8 | E12: Zoila Esperanza Valencia | F12: Exilis abdomen, cintura, chaparrera, entrepierna, parte posterior de la pierna y glúteos | G12: Credomatic | H12: 6500
B13: 45338 | C13: 516246032 | D13: 7 | E13: Nurith De Farrach | F13: Exilis rostro y cuello | G13: Cheque $ | H13: 3360
B14: 45338 | C14: 516246032 | D14: 1 | E14: Nurith De Farrach | F14: Exilis rostro y cuello | G14: Cheque $ | H14: 480.54
... B51: 45556 | C51: 157538858 | D51: 1 | E51: Gladys Montenegro Dubon | F51: Exilis rostro y cuello | G51: Visa L. | H51: 635
B52: 22/08/20204 | C52: 2854306162 | D52: 8 | E52: Marilyn Ivonne Barascout | F52: Exilis abdomen, cintura y espalda alta | G52: Visa | H52: 6500
B53: 45544 | C53: 1271613573 | D53: 8 | E53: Andrea Dougherty | F53: Exilis abdomen, cintura, gorditos espalda alta y brazos | G53: Visa | H53: 6500
B54: 45546 | C54: 335039904 | D54: 5 | E54: Maria Paola Gonzalez De Wever | F54: Exilis rostro y cuello | G54: Visa | H54: 3165
B55: 45546 | C55: 335039904 | D55: 1 | E55: Maria Paola Gonzalez De Wever | F55: Exilis rostro y cuello | G55: Visa | H55: 635
B56: 45555 | C56: 81545079 | D56: 8 | E56: Jessica Rubio Montes De Leal | F56: Exilis flancos, abdomen bajo y medias piernas completas | G56: Visa | H56: 6500
B57: 45560 | C57: 3055439433 | D57: 8 | E57: Josselyn Paola Iyescas | F57: Exilis abdomen completo, cintura y espalda baja | G57: Visa | H57: 6500
B58: 45576 | C58: 3519170775 | D58: 8 | E58: Patricia de Mejicanos | F58: Exilis abdomen, cintura, espalda alta y brazos | G58: Deposito | H58: 6500
B59: 45576 | C59: 3519170775 | D59: 1 | E59: Patricia de Mejicanos | F59: Abono a mesoterapia rodilla interna | G59: Deposito | H59: 100
B60: 45582 | C60: 3135849503 | D60: 6 | E60: Alma Regina Gandara | F60: Exilis rostro y cuello | G60: Visa | H60: 3900
B61: 45588 | C61: 2549305079 | D61: 8 | E61: Lissette Cifuentes | F61: Exilis abdomen, cintura y entrepierna | G61: Visa | H61: 6500
B62: 45590 | C62: 3811854562 | D62: 8 | E62: Ruth Noemi Valdez | F62: Exilis abdomen, cintura y espalda alta | G62: Visa | H62: 6500
B63: 45614 | C63: 3523429021 | D63: 8 | E63: Rene De Fumagalli | F63: Exilis abdomen, cintura, espalda alta y brazos | G63: Visa | H63: 6500
B64: 45624 | C64: 2682211199 | D64: 2 | E64: Oscar Catu | F64: Exilis abdomen, cintura, espalda | G64: Efectivo | H64: 1625
... B70: 45639 | C70: 390939710 | D70: 4 | E70: Ileana De Carrera | F70: Exilis piernas | G70: Visa | H70: 3250
E79: Total | H79: =SUM(H3:H78) -> 332202.54

Sheet Exfoliación
A1: Exfoliación | B1: Fecha | C1: No. de Factura | D1: Cantidad | E1: Nombre del Paciente | F1: Tratamiento | G1: Forma de Pago | H1: Total
B3: --- | C3: --- | D3: --- | E3: --- | F3: --- | G3: --- | H3: 0
E4: Total | H4: =SUM(H3:H3) -> 0

Sheet Facial purificante
A1: Facial purificante | B1: Fecha | C1: No. de Factura | D1: Cantidad | E1: Nombre del Paciente | F1: Tratamiento | G1: Forma de Pago | H1: Total
B3: 45296 | C3: 3954655538 | D3: 1 | E3: Bessy Chan | F3: Facial purificante | G3: Visa L. | H3: 575
B4: 45309 | C4: 2339393005 | D4: 5 | E4: Isabel Castillo | F4: Facial purificante | G4: Visa L. | H4: 2080
B5: 45309 | C5: 2339393005 | D5: 1 | E5: Isabel Castillo | F5: Facial purificante | G5: Visa L. | H5: 420
B6: 45330 | C6: 4281091856 | D6: 1 | E6: Maria Mercedes Sanchez | F6: Facial purificante | G6: Credomatic | H6: 575
B7: 45331 | C7: 3728426352 | D7: 1 | E7: Isabel Dedet | F7: Facial purificante | G7: Credomatic | H7: 575
B8: 45331 | C8: 2962640147 | D8: 1 | E8: Victoria Silva | F8: Facial purificante | G8: Credomatic | H8: 575
B9: 45335 | C9: 3499772398 | D9: 1 | E9: Ana Maria Herbruger | F9: Facial purificante | G9: Credomatic | H9: 450
B10: 45357 | C10: 1423591430 | D10: 1 | E10: Maria Renee Solares | F10: Facial purificante | G10: Visa | H10: 575
B11: 45357 | C11: 2212382807 | D11: 1 | E11: Jade Alejandra Argueta Alvarez | F11: Facial purificante | G11: Credomatic | H11: 575
B12: 45369 | C12: 3319939919 | D12: 1 | E12: Yesenia Larrazabal | F12: Facial purificante y exfoliación de manos | G12: Deposito | H12: 600
B13: 45385 | C13: 958548986 | D13: 1 | E13: Ana Maria Herbruger | F13: Facial purificante | G13: Credomatic | H13: 450
B14: 45390 | C14: 174279488 | D14: 1 | E14: Libni Fileberto Hernandez | F14: Facial purificante | G14: Visa L. | H14: 287.5
... B51: 45646 | C51: 1869103399 | D51: 1 | E51: Stephanie Madrid | F51: Facial purificante | G51: Efectivo | H51: 575
E78: Total | H78: =SUM(H3:H77) -> 33197.5

Sheet Hifu
A1: Hifu | B1: Fecha | C1: No. de Factura | D1: Cantidad | E1: Nombre del Paciente | F1: Tratamiento | G1: Forma de Pago | H1: Total
B3: 45321 | C3: 1585401474 | D3: 1 | E3: Silvia Lorena Paz | F3: Hifu ovalos facial y papada | G3: Visa | H3: 3000
B4: 45335 | C4: 446313629 | D4: 1 | E4: Ana Maria Herbruger | F4: Hifu ovalo facial y papada | G4: Credomatic | H4: 3000
B5: 45390 | C5: 3432858299 | D5: 1 | E5: Andrea Celeste Diaz | F5: Hifu ovalo facial y papada | G5: Visa | H5: 3000
B6: 45436 | C6: 606490181 | D6: 1 | E6: Sonia Yesenia Merida | F6: Hifu ovalo facial y papada | G6: Efectivo | H6: 3000
B7: 45454 | C7: 984301768 | D7: 1 | E7: Ariana Mendoza | F7: Hifu microson papada | G7: Visa | H7: 3000
B8: 45485 | C8: 2204516391 | D8: 1 | E8: Thomas Elfmont | F8: Abono hifu microson ovalo facial y papada (factura con exención de IVA) | G8: Visa | H8: 728.57
B9: 45485 | C9: 2204516391 | D9: 1 | E9: Thomas Elfmont | F9: Cancelación hifu microson ovalo facial y papada (factura con exención de IVA) | G9: Credomatic | H9: 2271.43
B10: 45488 | C10: 1160597328 | D10: 1 | E10: Ruth Noemi Valdez | F10: Hifu microson ovalo facial y papada | G10: Credomatic | H10: 3000
B11: 45516 | C11: 3732227095 | D11: 1 | E11: Carlos Pinto | F11: Hifu microson ovalo facil y papada | G11: Cheque | H11: 3000
B12: 45516 | C12: 3732227095 | D12: 1 | E12: Bertha de Pinto | F12: Hifu microson ovalo facil y papada | G12: Cheque | H12: 3000
B13: 45516 | C13: 3732227095 | D13: 1 | E13: Michelle Solorzano | F13: Hifu microson ovalo facil y papada | G13: Cheque | H13: 3000
B14: 45520 | C14: 3183494623 | D14: 1 | E14: Carmen Urrutia | F14: Hifu microson ovalo facial y papada | G14: Deposito | H14: 3000
E16: Total | H16: =SUM(H3:H15) -> 33000

Sheet Hydrafacial
A1: Hydrafacial | B1: Fecha | C1: No. de Factura | D1: Cantidad | E1: Nombre del Paciente | F1: Tratamiento | G1: Forma de Pago | H1: Total
B3: 45300 | C3: 679428893 | D3: 6 | E3: Janneth Fischer De Zablah | F3: Hydrafacial | G3: Visa | H3: 3000
B4: 45303 | C4: 549211363 | D4: 6 | E4: Diana Linares | F4: Hydrafacial | G4: Credomatic | H4: 3000
B5: 45322 | C5: 4013507674 | D5: 1 | E5: Gabriela Garza | F5: Hydrafacial | G5: Credomatic | H5: 583.8
B6: 45322 | C6: 4013507674 | D6: 1 | E6: Eddy Arroyo | F6: Hydrafacial | G6: Credomatic | H6: 583.8
B7: 45329 | C7: 195643368 | D7: 1 | E7: Patricia Chew | F7: Hydrafacial | G7: Visa | H7: 834
B8: 45356 | C8: 2355252326 | D8: 3 | E8: Marisol Coronado | F8: Hydrafacial | G8: Visa | H8: 2502
B9: 45373 | C9: 1469989733 | D9: 2 | E9: Claudia Contreras De Alfaro | F9: Hydrafacial | G9: Visa | H9: 1332
B10: 45373 | C10: 1469989733 | D10: 1 | E10: Claudia Contreras De Alfaro | F10: Hydrafacial | G10: Visa | H10: 668
B11: 45387 | C11: 1098599118 | D11: 1 | E11: Silvia Patricia Cabrera | F11: Hydrafacial | G11: Credomatic | H11: 834
B12: 45418 | C12: 1144539295 | D12: 1 | E12: Kirin Promalani | F12: Hydracial | G12: Credomatic | H12: 834
B13: 45420 | C13: 356076022 | D13: 1 | E13: Ana Maria Herbruger | F13: Hydracial | G13: Visa L. | H13: 834
B14: 45421 | C14: 4156441337 | D14: 1 | E14: Ximena Orellana | F14: Hydrafacial | G14: Credomatic | H14: 834
... B42: 45638 | C42: 3641001320 | D42: 1 | E42: Marcela Barquin | F42: Hydrafacial | G42: Credomatic | H42: 834
E53: Total | H53: =SUM(H3:H52) -> 45253

Sheet Laboratorios
A1: Laboratorios | B1: Fecha | C1: No. de Factura | D1: Cantidad | E1: Nombre del Paciente | F1: Tratamiento | G1: Forma de Pago | H1: Total
B3: 45315 | C3: 3749136595 | D3: 1 | E3: Luis Alberto Castellanos | F3: Laboratorios | G3: Visa | H3: 750
B4: 45446 | C4: 3639757710 | D4: 1 | E4: Norma De Castellamos | F4: Laboratorios pre-células | G4: Credomatic | H4: 1200
B5: 45505 | C5: 22168784 | D5: 1 | E5: Evelyn Zelaya | F5: Laboratorios pre-células | G5: Deposito | H5: 1200
B6: 45565 | C6: 2551662146 | D6: 1 | E6: Rolando Torres | F6: Laboratorios pre-células | G6: Cheque | H6: 1200
B7: 45572 | C7: 3409134142 | D7: 1 | E7: Alcira Torres | F7: Laboratorios pre-celulas | G7: Cheque | H7: 1200
E18: Total | H18: =SUM(H3:H17) -> 5550

Sheet Masaje linfatico
A1: Masaje linfatico | B1: Fecha | C1: No. de Factura | D1: Cantidad | E1: Nombre del Paciente | F1: Tratamiento | G1: Forma de Pago | H1: Total
B3: 45301 | C3: 3831055404 | D3: 8 | E3: Ines Batres | F3: Masaje linfatico | G3: Visa | H3: 1600
B4: 45313 | C4: 2833729445 | D4: 5 | E4: Megan Jerez (Alisson Batres) | F4: Masaje linfatico | G4: Visa L. | H4: 1000
B5: 45320 | C5: 69486400 | D5: 8 | E5: Marilyn Muñoz | F5: Masaje linfatico | G5: Visa | H5: 1600
B6: 45330 | C6: 1156400484 | D6: 17 | E6: Agnes Castillo | F6: Masaje linfatico | G6: Visa | H6: 3499.9999
B7: 45331 | C7: 2547664007 | D7: 10 | E7: Monica Ivette Cruz | F7: Masaje linfatico | G7: Visa | H7: 2000
B8: 45334 | C8: 4251338516 | D8: 10 | E8: Rebeca Pineda | F8: Masaje linfatico | G8: Deposito | H8: 2000
B9: 45335 | C9: 3762898987 | D9: 6 | E9: Shelee Perez | F9: Masaje linfatico | G9: Visa | H9: 1200
B10: 45351 | C10: 1234848576 | D10: 1 | E10: Gilma Valdez | F10: Masaje linfatico | G10: Efectivo | H10: 200
B11: 45362 | C11: 1071205147 | D11: 1 | E11: Bonna Marroquin | F11: Masaje linfatico | G11: Credomatic | H11: 200
B12: 45385 | C12: 3741336401 | D12: 1 | E12: Maria Lourdes Garcia | F12: Masaje linfatico | G12: Credomatic | H12: 200
B13: 45387 | C13: 439108700 | D13: 5 | E13: Rosalina Donis Muñoz | F13: Masaje linfatico | G13: Visa L. | H13: 1250
B14: 45387 | C14: 3172812392 | D14: 2 | E14: Andrea Celeste Diaz | F14: Masaje linfatico facial | G14: Efectivo | H14: 376
... B38: 45646 | C38: 2242138031 | D38: 1 | E38: Alejandra Quinto | F38: Masaje linfatico | G38: Credomatic | H38: 200
E58: Total | H58: =SUM(H3:H57) -> 37350

Sheet Mesoterapia
A1: Mesoterapia | B1: Fecha | C1: No. de Factura | D1: Cantidad | E1: Nombre del Paciente | F1: Tratamiento | G1: Forma de Pago | H1: Total
B3: 45310 | C3: 1306282846 | D3: 8 | E3: José Antonio Corrales | F3: Mesoterapia abdomen, cintura y espalda | G3: Visa L. | H3: 3120
B4: 45335 | C4: 3208855974 | D4: 10 | E4: Iris Veronica Aroche | F4: Mesoterapia reductora abdomen, cintura, gorditos espalda alta y brazos | G4: Credomatic | H4: 5500
B5: 45357 | C5: 634209830 | D5: 4 | E5: Nicole Melville | F5: Mesoterapia gorditos espalda baja | G5: Visa | H5: 2000
B6: 45364 | C6: 2037729283 | D6: 5 | E6: Julia Marina Valdez | F6: Mesoterapia reductora gorditos espalda alta | G6: Visa | H6: 2330
B7: 45364 | C7: 2037729283 | D7: 1 | E7: Julia Marina Valdez | F7: Mesoterapia reductora gorditos espalda alta | G7: Visa | H7: 470
B8: 45369 | C8: 2710651286 | D8: 10 | E8: Nadia Zimeria Chacama | F8: Mesoterapia abdomen bajo y cintura | G8: Visa | H8: 6186
B9: 45387 | C9: 1663583003 | D9: 1 | E9: Daniela Orellana | F9: Mesoterapia | G9: Credomatic | H9: 500
B10: 45390 | C10: 654198680 | D10: 4 | E10: Maria Jose Ortiz | F10: Mesoterapia flancos y abdomen bajo | G10: Credomatic | H10: 2184
B11: 45393 | C11: 2641249574 | D11: 10 | E11: Silvia Fernanda Chacon | F11: Mesoterapia reductora espalda baja, banana roll y brazos | G11: Credomatic | H11: 6500
B12: 45429 | C12: 3745074608 | D12: 8 | E12: Jose Estuardo Galvez | F12: Mesoterapia abdomen y cintura | G12: Visa L. | H12: 3800
B13: 45456 | C13: 167789590 | D13: 2 | E13: Ethel Velasquez Rivera | F13: Mesoterapia | G13: Credomatic | H13: 960
B14: 45471 | C14: 3946792971 | D14: 1 | E14: Ethel Velasquez Rivera | F14: Mesoterapia reductora brazos | G14: Credomatic | H14: 480
... B32: 45637 | C32: 428560084 | D32: 4 | E32: Bonna Marroquin | F32: Mesoterapia reductora abdomen inferior | G32: Visa | H32: 2000
E33: Total | H33: =SUM(H3:H32) -> 87976

Sheet Morpheus
A1: Morpheus | B1: Fecha | C1: No. de Factura | D1: Cantidad | E1: Nombre del Paciente | F1: Tratamiento | G1: Forma de Pago | H1: Total
B3: 45310 | C3: 2806990785 | D3: 2 | E3: Gabriela Toledo | F3: Morpheus rostro y cuello | G3: Visa | H3: 10000
B4: 45310 | C4: 393824738 | D4: 3 | E4: Astrid Alvarado De Quan | F4: Morpheus rostro y cuello | G4: Credomatic | H4: 15000
B5: 45320 | C5: 4056106375 | D5: 2 | E5: Carla Sena | F5: Morpheus rostro y cuello | G5: Credomatic | H5: 10000
B6: 45322 | C6: 3595650650 | D6: 1 | E6: Julia Sapper | F6: Morpheus rostro y cuello | G6: Deposito | H6: 5000
B7: 45329 | C7: 3749792411 | D7: 2 | E7: Karin Haeckel De Gonzalez | F7: Morpheus rostro y cuello | G7: Visa | H7: 10000
B8: 45329 | C8: 177556139 | D8: 2 | E8: Carol Knecusch Toriello | F8: Morpheus rostro y cuello | G8: Visa | H8: 10000
B9: 45336 | C9: 3726984370 | D9: 1 | E9: Marilyn Muñoz | F9: Morpheus rostro y cuello | G9: Visa | H9: 5460
B10: 45337 | C10: 1341606645 | D10: 2 | E10: Carolina Orellana | F10: Morpheus rostro y cuello | G10: Deposito | H10: 10000
B11: 45337 | C11: 2100971790 | D11: 2 | E11: Jenny Orellana | F11: Morpheus rostro y cuello | G11: Deposito | H11: 10000
B12: 45338 | C12: 1630618064 | D12: 2 | E12: Evelyn Hernandez | F12: Morpheus rostro y cuello | G12: Visa | H12: 10000
B13: 45342 | C13: 559104675 | D13: 4 | E13: Tere De Bolaños | F13: Morpheus corporal | G13: Visa | H13: 20000
B14: 45343 | C14: 195966600 | D14: 1 | E14: Lydia Reyes | F14: Abono a morpheus rostro y cuello | G14: Efectivo | H14: 2000
... B78: 45646 | C78: 4254155511 | D78: 2 | E78: Jose Batres | F78: Morpheus rostro y cuello | G78: Credomatic | H78: 10000
E82: Total | H82: =SUM(H3:H81) -> 714460

Sheet Pico-láser
A1: Pico-láser | B1: Fecha | C1: No. de Factura | D1: Cantidad | E1: Nombre del Paciente | F1: Tratamiento | G1: Forma de Pago | H1: Total
E6: Total | H6: =SUM(H3:H5) -> 0

Sheet Profhilo
A1: Porfhilo | B1: Fecha | C1: No. de Factura | D1: Cantidad | E1: Nombre del Paciente | F1: Tratamiento | G1: Forma de Pago | H1: Total
B3: 45300 | C3: 4025500651 | D3: 2 | E3: Eugenia Paz | F3: Aplicación de profhilo | G3: Visa | H3: 5000
B4: 45301 | C4: 2910864217 | D4: 1 | E4: Claudia Maria Jose Morales | F4: Aplicación de profhilo | G4: Credomatic | H4: 2500
B5: 45309 | C5: 3970256467 | D5: 2 | E5: Elizabeth Molina | F5: Aplicación de profhilo | G5: Deposito | H5: 5000
B6: 45315 | C6: 4071573535 | D6: 2 | E6: Sara Bolaños | F6: Aplicación de profhilo | G6: Deposito | H6: 5000
B7: 45321 | C7: 1516192547 | D7: 2 | E7: Magda Díaz | F7: Aplicación de profhilo | G7: Visa | H7: 5000
B8: 45322 | C8: 2796507074 | D8: 2 | E8: Rosa Maria Miralles | F8: Aplicación de profhilo | G8: Credomatic | H8: 5000
B9: 45322 | C9: 2587902124 | D9: 2 | E9: Maria Jose Alvarez | F9: Aplicación de profhilo | G9: Visa | H9: 5000
B10: 45357 | C10: 3603776325 | D10: 2 | E10: Claudia Eugenia Alburez | F10: Aplicación de profhilo | G10: Visa | H10: 5000
B11: 45390 | C11: 414534931 | D11: 2 | E11: Andrea Meany | F11: Aplicación de profhilo | G11: Credomatic | H11: 5000
B12: 45433 | C12: 2328316348 | D12: 2 | E12: Melanie Guerra | F12: Aplicación de profhilo | G12: Visa L. | H12: 5000
B13: 45504 | C13: 913000973 | D13: 2 | E13: Karen Illescas | F13: Aplicación de profhilo | G13: Credomatic | H13: 5000
B14: 45511 | C14: 22168273 | D14: 2 | E14: Wendy Marisol Gonzalez | F14: Aplicación de profhilo | G14: Visa | H14: 5000
B15: 45513 | C15: 3417000141 | D15: 2 | E15: Erika Aquino | F15: Aplicación de profhilo | G15: Credomatic | H15: 5000
B16: 20/08/20204 | C16: 2219134279 | D16: 2 | E16: Gladys Montenegro Dubon | F16: Aplicación de profhilo | G16: Visa L. | H16: 5000
B17: 45534 | C17: 46024087 | D17: 2 | E17: Isabel Pivaral | F17: Aplicación de profhilo | G17: Visa | H17: 5000
B18: 45546 | C18: 2539734439 | D18: 2 | E18: Paola Bouscayrol De Criado | F18: Aplicación de profhilo | G18: Visa L. | H18: 5000
B19: 45551 | C19: 4110765754 | D19: 2 | E19: Roxana Gabriel Lopez | F19: Aplicación de profhilo | G19: Cheque | H19: 5000
B20: 45553 | C20: 3169665060 | D20: 2 | E20: Silvia Arevalo | F20: Aplicación de profhilo | G20: Deposito | H20: 5000
B21: 45560 | C21: 879313783 | D21: 1 | E21: Arturo Salvatierra | F21: Aplicación de profhilo | G21: Visa | H21: 2500
B22: 45560 | C22: 879313783 | D22: 1 | E22: Mariela De La Cruz | F22: Aplicación de profhilo | G22: Visa | H22: 2500
B23: 45574 | C23: 1143818921 | D23: 2 | E23: Magdalena Diaz | F23: Aplicación de profhilo | G23: Visa | H23: 5000
B24: 45588 | C24: 1898335348 | D24: 2 | E24: Gladys Montenegro Dubon | F24: Aplicación de profhilo | G24: Visa L. | H24: 5000
B25: 45590 | C25: 1029981194 | D25: 2 | E25: Ernesto Guzman | F25: Aplicación de profhilo | G25: Visa | H25: 5000
B26: 45593 | C26: 412175540 | D26: 1 | E26: Arturo Salvartierra | F26: Aplicación de profhilo | G26: Credomatic | H26: 2500
B27: 45593 | C27: 412175540 | D27: 1 | E27: Mariela Cruz | F27: Aplicación de profhilo | G27: Credomatic | H27: 2500
B28: 45602 | C28: 3095153149 | D28: 2 | E28: Eva Masilla | F28: Aplicación de profhilo | G28: Credomatic | H28: 5000
B29: 45643 | C29: 1267943110 | D29: 2 | E29: Ernesto Guzman | F29: Aplicación de profhilo | G29: Credomatic | H29: 5000
E30: Total | H30: =SUM(H3:H29) -> 122500

Sheet PRP
A1: PRP | B1: Fecha | C1: No. de Factura | D1: Cantidad | E1: Nombre del Paciente | F1: Tratamiento | G1: Forma de Pago | H1: Total
B3: 45301 | C3: 4269949891 | D3: 3 | E3: Gabriela Pinto De Pontaza | F3: PRP rostro y cuello | G3: Deposito | H3: 3000
B4: 45306 | C4: 1687177404 | D4: 1 | E4: Gloria Ralda | F4: PRP rostro y cuello | G4: Deposito | H4: 1000
B5: 45306 | C5: 1687177404 | D5: 1 | E5: Gloria Ralda | F5: Abono a PRP | G5: Deposito | H5: 500
B6: 45315 | C6: 1995916393 | D6: 3 | E6: Claudia Maria De León | F6: PRP rostro y cuello | G6: Visa | H6: 3000
B7: 45315 | C7: 585911500 | D7: 1 | E7: Gloria Ralda | F7: Cancelación a PRP | G7: Deposito | H7: 500
B8: 45315 | C8: 585911500 | D8: 1 | E8: Gloria Ralda | F8: PRP rostro y cuello | G8: Deposito | H8: 1000
B9: 45315 | C9: 2555792518 | D9: 2 | E9: Esther Pacheco | F9: PRP rostro y cuello | G9: Deposito | H9: 2400
B10: 45316 | C10: 4066787708 | D10: 3 | E10: Arecely Boguerin | F10: PRP rostro y cuello | G10: Visa L. | H10: 3000
B11: 45320 | C11: 2949271419 | D11: 3 | E11: Ada Briceño | F11: PRP rostro y cuello | G11: Visa L. | H11: 3000
B12: 45321 | C12: 2032485030 | D12: 3 | E12: Mariela Saravia | F12: PRP rostro y cuello | G12: Visa L. | H12: 3000
B13: 45321 | C13: 2320122568 | D13: 3 | E13: Alcira De Torres | F13: PRP rostro y cuello | G13: Efectivo | H13: 3000
B14: 45323 | C14: 165691819 | D14: 1 | E14: Gisela Castillo | F14: PRP rostro | G14: Cheque | H14: 800
... B146: 45645 | C146: 49693094 | D146: 3 | E146: Mayra Lucrecia Morales De Morales | F146: PRP rostro y cuello | G146: Visa L. | H146: 3600
E147: Total | H147: =SUM(H3:H146) -> 304240

Sheet Radiofrecuencia
A1: Radiofrecuencia | B1: Fecha | C1: No. de Factura | D1: Cantidad | E1: Nombre del Paciente | F1: Tratamiento | G1: Forma de Pago | H1: Total
B3: 45301 | C3: 3935652082 | D3: 5 | E3: Gabriela Pinto De Pontaza | F3: Radiofrecuencia abdomen y espalda completa | G3: Visa L. | H3: 2915
B4: 45301 | C4: 3935652082 | D4: 1 | E4: Gabriela Pinto De Pontaza | F4: Radiofrecuencia abdomen y espalda completa | G4: Visa L. | H4: 585
B5: 45301 | C5: 2130526838 | D5: 6 | E5: Norma De Barquin | F5: Radiofrecuencia mentoón, cuello y escote | G5: Deposito | H5: 3000
B6: 45306 | C6: 2104511653 | D6: 4 | E6: Gladys Del Cid De Escobar | F6: Radiofrecuencia abdomen, cintura, espalda alta y gluteos | G6: Visa | H6: 2500
B7: 45313 | C7: 2294960033 | D7: 6 | E7: Edgar Muñoz | F7: Radiofrecuencia rostro y cuello | G7: Visa | H7: 3000
B8: 45315 | C8: 193940475 | D8: 3 | E8: Jennifer Lima | F8: Radiofrecuencia abdomen, cintura, piernas y glúteos | G8: Visa | H8: 2670
B9: 45317 | C9: 4036968491 | D9: 6 | E9: Irene Piñol De Morales | F9: Radiofrecuencia rostro y cuello | G9: Visa | H9: 3000
B10: 45329 | C10: 275990370 | D10: 6 | E10: Dharma Maldonado | F10: Radiofrecuencia corporal | G10: Visa L. | H10: 2670
B11: 45334 | C11: 3163898577 | D11: 8 | E11: Margarita Wever | F11: Radiofrecuencia medias piernas completas y gluteos | G11: Credomatic | H11: 3600
B12: 45342 | C12: 1557810442 | D12: 5 | E12: Claudia Godoy De Aguilar | F12: Radiofrecuencia piernas completas y glúteos | G12: Visa | H12: 4212.9
B13: 45342 | C13: 1557810442 | D13: 1 | E13: Claudia Godoy De Aguilar | F13: Radiofrecuencia piernas completas y glúteos | G13: Visa | H13: 842.6
B14: 45355 | C14: 1483949969 | D14: 4 | E14: Anna Herrera | F14: Radiofrecuencia rostro y cuello | G14: Deposito | H14: 1780
... B49: 45643 | C49: 3553053345 | D49: 6 | E49: Evelyn Hernandez | F49: Radiofrecuencia corporal | G49: Visa L. | H49: 6300
E50: Total | H50: =SUM(H3:H49) -> 157289.5

Sheet Ultrasonido
A1: Ultrasonido post-operatorio | B1: Fecha | C1: No. de Factura | D1: Cantidad | E1: Nombre del Paciente | F1: Tratamiento | G1: Forma de Pago | H1: Total
B3: 45313 | C3: 2787788939 | D3: 10 | E3: Virginia Morales | F3: Ultrasonido post-operatorio | G3: Credomatic | H3: 1800
B4: 45314 | C4: 2387298960 | D4: 5 | E4: Diana Linares | F4: Ultrasonido post-operatorio | G4: Credomatic | H4: 900
B5: 45328 | C5: 4099755301 | D5: 5 | E5: Naima Werren | F5: Ultrasonido post-operatorio | G5: Credomatic | H5: 1800
B6: 45331 | C6: 2547664007 | D6: 10 | E6: Monica Ivette Cruz | F6: Ultrasonido post-operatorio | G6: Visa | H6: 1800
B7: 45334 | C7: 4251338516 | D7: 10 | E7: Rebeca Pineda | F7: Ultrasonido post-operatorio | G7: Deposito | H7: 1800
B8: 45358 | C8: 2771863235 | D8: 5 | E8: Lesli Chilin Morales | F8: Ultrasonido post-operatorio | G8: Visa | H8: 900
B9: 45383 | C9: 3775745118 | D9: 10 | E9: Wendy Paola Giron | F9: Ultrasonido post-operatorio | G9: Visa L. | H9: 1800
B10: 45397 | C10: 3227928430 | D10: 5 | E10: Ines Batres | F10: Ultrasonido post-operatorio | G10: Visa | H10: 900
B11: 45418 | C11: 3108717436 | D11: 10 | E11: Barbara Morales | F11: Ultrasonido post-operatorio | G11: Visa L. | H11: 1800
B12: 45420 | C12: 1550336626 | D12: 10 | E12: Gabriela Alejandra Alejo Morales | F12: Ultrasonido post-operatorio | G12: Visa L. | H12: 1800
B13: 45439 | C13: 3690483684 | D13: 6 | E13: Bonna Marroquin | F13: Ultrasonido post-operatorio | G13: Visa | H13: 1080
B14: 45483 | C14: 3958067078 | D14: 6 | E14: Cinthya Pacheco Garcia | F14: Ultrasonido post-operatorio | G14: Credomatic | H14: 1200
... B17: 45639 | C17: 1679770480 | D17: 8 | E17: Laura Quiroa Samayoa | F17: Ultrasonido post-operatorio | G17: Visa | H17: 1440
E18: Total | H18: =SUM(H3:H17) -> 21720

Sheet Velo de acido hialuronico
A1: Velo de acido hialuronico | B1: Fecha | C1: No. de Factura | D1: Cantidad | E1: Nombre del Paciente | F1: Tratamiento | G1: Forma de Pago | H1: Total
B3: 45643 | C3: 138497865 | D3: 1 | E3: Claudia Maria De León | F3: Velo de acido hialuronico | G3: Credomatic | H3: 650
B4: 45645 | C4: 140536065 | D4: 1 | E4: Gabriela Morales | F4: Velo de acido hialuronico | G4: Credomatic | H4: 650
E5: Total | H5: =SUM(H3:H4) -> 1300

Sheet Velox
A1: Velox | B1: Fecha | C1: No. de Factura | D1: Cantidad | E1: Nombre del Paciente | F1: Tratamiento | G1: Forma de Pago | H1: Total
B3: 45364 | C3: 3967897459 | D3: 8 | E3: Rocio Margarita Molina | F3: Velox entrepierna, chaparreras y banana roll | G3: Visa | H3: 3500
B4: 45414 | C4: 606227387 | D4: 8 | E4: Yanci Palma Ortiz | F4: Velox abdomen, cintura y banana roll | G4: Visa | H4: 3000
B5: 45426 | C5: 1132217046 | D5: 8 | E5: Sergio Rosales | F5: Velox abdomen y cintura | G5: Visa L. | H5: 3040
B6: 45436 | C6: 939343978 | D6: 8 | E6: Ethel Velasquez Rivera | F6: Velox abdomen, cintura y espalda alta | G6: Credomatic | H6: 3000
B7: 45460 | C7: 2626440107 | D7: 8 | E7: Francis Maria Cuellar | F7: Velox chaparreras, banana roll y entrepierna | G7: Visa L. | H7: 2998
B8: 45463 | C8: 1871267445 | D8: 8 | E8: Fabiola Alejandra Flores | F8: Velox chaparrera y banana roll | G8: Visa | H8: 2000
B9: 45471 | C9: 4109845121 | D9: 8 | E9: Gloria Maria Sanchez | F9: Velox abdomen, cintura y piernas | G9: Deposito | H9: 2912
E10: Total | H10: =SUM(H3:H9) -> 20450

Sheet Vitamina C intravenosa
A1: Vitamina C intravenosa | B1: Fecha | C1: No. de Factura | D1: Cantidad | E1: Nombre del Paciente | F1: Tratamiento | G1: Forma de Pago | H1: Total
B3: 45300 | C3: 917458477 | D3: 1 | E3: Wilmer Lopez | F3: Aplicación de vitamina C intravenosa | G3: Credomatic | H3: 535
B4: 45300 | C4: 917458477 | D4: 1 | E4: Joselyn Alvurez | F4: Aplicación de vitamina C intravenosa | G4: Credomatic | H4: 535
B5: 45300 | C5: 4234036202 | D5: 3 | E5: Luis Garrido | F5: Aplicación de vitamina C intravenosa | G5: Visa | H5: 1605
B6: 45301 | C6: 4269949891 | D6: 3 | E6: Gabriela Pinto De Pontaza | F6: Aplicación de vitamina C intravenosa | G6: Deposito | H6: 1605
B7: 45302 | C7: 1706053159 | D7: 1 | E7: Tere De Bolaños | F7: Aplicación de vitamina C intravenosa | G7: Visa | H7: 535
B8: 45306 | C8: 1529234300 | D8: 1 | E8: Mary Contraras | F8: Aplicación de vitamina C intravenosa | G8: Credomatic | H8: 535
B9: 45306 | C9: 650068699 | D9: 1 | E9: Obdulio Gomez | F9: Aplicación de vitamina C intravenosa | G9: Efectivo | H9: 535
B10: 45306 | C10: 650068699 | D10: 1 | E10: Evelia Morales | F10: Aplicación de vitamina C intravenosa | G10: Efectivo | H10: 535
B11: 45310 | C11: 1306282846 | D11: 3 | E11: Ana Herrera | F11: Aplicación de vitamina C intravenosa | G11: Visa L. | H11: 1605
B12: 45310 | C12: 1306282846 | D12: 3 | E12: José Antonio Corrales | F12: Aplicación de vitamina C intravenosa | G12: Visa L. | H12: 1605
B13: 45315 | C13: 1995916393 | D13: 3 | E13: Claudia Maria De León | F13: Aplicación de vitamina C intravenosa | G13: Visa | H13: 1605
B14: 45316 | C14: 1235308280 | D14: 3 | E14: Eugenia Madrid De Paredes | F14: Aplicación de vitamina C intravenosa | G14: Credomatic | H14: 1605
... B89: 45520 | C89: 3627696298 | D89: 1 | E89: Iveth Bojorquez | F89: Aplicación de vitamina C intravenosa | G89: Credomatic | H89: 535
B90: 22/08/20204 | C90: 2005289128 | D90: 1 | E90: Marcela Escobar | F90: Aplicación de vitamina C intravenosa | G90: Credomatic | H90: 535
B91: 45527 | C91: 1019825319 | D91: 1 | E91: Carlos Humberto Rodriguez | F91: Aplicación de vitamina C intravenosa | G91: Credomatic | H91: 535
B92: 45530 | C92: 1428635744 | D92: 3 | E92: Bibian Ramirez | F92: Aplicación de vitamina C intravenosa | G92: Visa | H92: 1605
B93: 45530 | C93: 1428635744 | D93: 3 | E93: Edgar Ordoñez | F93: Aplicación de vitamina C intravenosa | G93: Visa | H93: 1605
B94: 45531 | C94: 899629454 | D94: 1 | E94: Vivian Porres | F94: Aplicación de vitamina C intravenosa | G94: Visa | H94: 535
B95: 45534 | C95: 422594588 | D95: 1 | E95: Silvia Villanueva | F95: Aplicación de vitamina C intravenosa | G95: Visa | H95: 535
B96: 45538 | C96: 2022590115 | D96: 3 | E96: Janeth Zablah de Fischer | F96: Aplicación de vitamina C intravenosa | G96: Credomatic | H96: 1605
B97: 45540 | C97: 371412223 | D97: 1 | E97: Ana Gisela Castillo | F97: Aplicación de vitamina C intravenosa | G97: Cheque | H97: 376
B98: 45546 | C98: 3274065925 | D98: 3 | E98: Pedro Ochandiano | F98: Aplicación de vitamina C intravenosa | G98: Visa L. | H98: 1605
B99: 45551 | C99: 4110765754 | D99: 3 | E99: Roxana Gabriel Lopez | F99: Aplicación de vitamina C intravenosa | G99: Cheque | H99: 1605
B100: 45553 | C100: 1568621810 | D100: 1 | E100: Eugenia Franco | F100: Aplicación de vitamina C intravenosa | G100: Efectivo | H100: 535
B101: 45555 | C101: 2045329713 | D101: 3 | E101: Hector Leal | F101: Aplicación de vitamina C intravenosa | G101: Credomatic | H101: 1605
B102: 45560 | C102: 3495120489 | D102: 1 | E102: Mary Contreras | F102: Aplicación de vitamina C intravenosa | G102: Credomatic | H102: 535
... B145: 45646 | C145: 4254155511 | D145: 1 | E145: Jose Batres | F145: Aplicación de vitamina C intravenosa | G145: Credomatic | H145: 535
E146: Total | H146: =SUM(H3:H145) -> 145406

Sheet Ciclo coolsculpting
A1: Ciclo coolsculpting | B1: Fecha | C1: No. de Factura | D1: Cantidad | E1: Nombre del Paciente | F1: Tratamiento | G1: Forma de Pago | H1: Total
B3: 45328 | C3: 661602431 | D3: 2 | E3: Patricia De Suarez | F3: Ciclos coolsculpting | G3: Deposito | H3: 9000
B4: 45364 | C4: 1202013548 | D4: 2 | E4: Silvia Del Pinal Moran | F4: Ciclos coolsculpting | G4: Credomatic | H4: 9000
B5: 45369 | C5: 538726094 | D5: 4 | E5: Cynthia Castillo de Zelaya | F5: Ciclos coolsculpting | G5: Credomatic | H5: 18000
B6: 45481 | C6: 655376772 | D6: 2 | E6: Luis Valladares | F6: Ciclos coolsculpting | G6: Visa | H6: 9000
E7: Total | H7: =SUM(H3:H6) -> 45000

Sheet Dermapen
A1: Dermapen | B1: Fecha | C1: No. de Factura | D1: Cantidad | E1: Nombre del Paciente | F1: Tratamiento | G1: Forma de Pago | H1: Total
B3: 45329 | C3: 275990370 | D3: 3 | E3: Dharma Maldonado | F3: Dermapen rostro y cuello | G3: Visa L. | H3: 3000
B4: 45468 | C4: 3439152553 | D4: 2 | E4: Iveth Bojorquez | F4: Dermapen rostro y cuello | G4: Visa L. | H4: 3600
B5: 45503 | C5: 3704311757 | D5: 2 | E5: Mariela Saravia | F5: Dermapen rostro y cuello | G5: Visa L. | H5: 3600
E6: Total | H6: =SUM(H3:H5) -> 10200

Sheet Láser CO2
A1: Láser CO2 | B1: Fecha | C1: No. de Factura | D1: Cantidad | E1: Nombre del Paciente | F1: Tratamiento | G1: Forma de Pago | H1: Total
B3: 45372 | C3: 2788051740 | D3: 1 | E3: Hilda Lucrecia Gonzalez de Lopez | F3: Láser CO2 | G3: Visa | H3: 6500
B4: 45400 | C4: 2878947999 | D4: 1 | E4: Jenny Orellana Cruz | F4: Laser CO2 | G4: Visa | H4: 1800
B5: 45490 | C5: 729041878 | D5: 1 | E5: Rosa Magdalena Gomez | F5: Abono láser CO2 | G5: Visa L. | H5: 1000
B6: 45499 | C6: 4041491869 | D6: 1 | E6: Rosa Magdalena Gomez | F6: Canelación láser CO2 | G6: Credomatic | H6: 5000
B7: 45561 | C7: 1372145102 | D7: 1 | E7: Jessica Meza | F7: Láser CO2 | G7: Efectivo | H7: 6000
B8: 45607 | C8: 3895021185 | D8: 1 | E8: Sandra Perez | F8: Láser CO2 | G8: Credomatic | H8: 5000
E9: Total | H9: =SUM(H3:H8) -> 25300

Sheet Masaje relajante
A1: Masaje relajante | B1: Fecha | C1: No. de Factura | D1: Cantidad | E1: Nombre del Paciente | F1: Tratamiento | G1: Forma de Pago | H1: Total
B3: 45295 | C3: 1964328520 | D3: 1 | E3: Luis Garrido | F3: Masaje relajante | G3: Credomatic | H3: 350
B4: 45300 | C4: 4234036202 | D4: 10 | E4: Luis Garrido | F4: Masaje relajante | G4: Visa | H4: 2500
B5: 45348 | C5: 2742046411 | D5: 15 | E5: Luis Garrido | F5: Masaje relajante | G5: Credomatic | H5: 3000
B6: 45405 | C6: 3096793043 | D6: 1 | E6: Ingrid Berganza | F6: Masaje relajante | G6: Credomatic | H6: 350
B7: 45407 | C7: 1725057014 | D7: 1 | E7: Ana Maria Teran | F7: Masaje relajante | G7: Credomatic | H7: 350
B8: 45425 | C8: 305548470 | D8: 1 | E8: Sergio Ortiz | F8: Masaje relajante | G8: Deposito | H8: 350
B9: 45429 | C9: 2074690772 | D9: 1 | E9: Vanessa De Ceballos / Nia Ceballos | F9: Masaje relajante | G9: Credomatic | H9: 350
B10: 45441 | C10: 558383555 | D10: 1 | E10: Adriana Picon | F10: Masaje relajante | G10: Efectivo | H10: 350
B11: 45447 | C11: 181028285 | D11: 1 | E11: Keny Marquez | F11: Masaje relajante | G11: Visa | H11: 300
B12: 45457 | C12: 1757171320 | D12: 1 | E12: Gustavo Oliva | F12: Masaje relajante | G12: Efectivo | H12: 250
B13: 45463 | C13: 2081443783 | D13: 25 | E13: Luis Garrido | F13: Masaje relajante | G13: Visa | H13: 5000
B14: 45468 | C14: 3956228915 | D14: 10 | E14: Zoila Valencia Marroquin | F14: Masaje relajante | G14: Credomatic | H14: 2200
... B24: 45642 | C24: 461917924 | D24: 20 | E24: Luis Garrido | F24: Masaje relajante | G24: Credomatic | H24: 3500
E25: Total | H25: =SUM(H3:H24) -> 24950

Sheet Oligoelementos
A1: Oligoelementos | B1: Fecha | C1: No. de Factura | D1: Cantidad | E1: Nombre del Paciente | F1: Tratamiento | G1: Forma de Pago | H1: Total
B3: 45630 | C3: 1543457484 | D3: 2 | E3: Fabiola Tenas | F3: Aplicación oligoelementos | G3: Efectivo | H3: 1400
E4: Total | H4: =SUM(H3:H3) -> 1400

Sheet Celulas madre
A1: Celulas Madre | B1: Fecha | C1: No. de Factura | D1: Cantidad | E1: Nombre del Paciente | F1: Tratamiento | G1: Forma de Pago | H1: Total
B3: 45315 | C3: 3749136595 | D3: 1 | E3: Luis Alberto Castellanos | F3: Procedimiento celulas madres | G3: Visa | H3: 17750
B4: 45446 | C4: 3639757710 | D4: 1 | E4: Norma De Castellamos | F4: Procedimieno celulas madres | G4: Credomatic | H4: 17750
B5: 45505 | C5: 22168784 | D5: 1 | E5: Evelyn Zelaya | F5: Procedimiento celulas madres | G5: Deposito | H5: 25838
B6: 45565 | C6: 2551662146 | D6: 1 | E6: Rolando Torres | F6: Procedimiento celulas madres | G6: Cheque | H6: 23160
B7: 45572 | C7: 3409134142 | D7: 1 | E7: Alcira Torres | F7: Procedimiento celulas madres | G7: Cheque | H7: 23160
E12: Total | H12: =SUM(H3:H11) -> 107658

Sheet Peeling
A1: Peeling | B1: Fecha | C1: No. de Factura | D1: Cantidad | E1: Nombre del Paciente | F1: Tratamiento | G1: Forma de Pago | H1: Total
B3: 45390 | C3: 1928940883 | D3: 1 | E3: Estela Terreza | F3: Peeling manos | G3: Deposito | H3: 850
B4: 45397 | C4: 690832433 | D4: 1 | E4: Elizabeth Molina | F4: Peeling manos | G4: Visa | H4: 750
B5: 45400 | C5: 3693102747 | D5: 5 | E5: Ana Jeannette Ortiz | F5: Peeling duosomado | G5: Efectivo | H5: 3900
B6: 45436 | C6: 2759872259 | D6: 3 | E6: Karla Sapper | F6: Peeling rostro | G6: Visa | H6: 2550
B7: 45440 | C7: 3116253629 | D7: 5 | E7: Elizabeth Molina | F7: Peeling duosomado | G7: Visa | H7: 3800
B8: 45456 | C8: 150097716 | D8: 5 | E8: Diana Linares | F8: Peeling duosomado | G8: Credomatic | H8: 3800
B9: 45489 | C9: 4108995424 | D9: 1 | E9: Carol Knebusch | F9: Peeling duosomado | G9: Credomatic | H9: 550
B10: 45498 | C10: 3244379101 | D10: 4 | E10: Diana Linares | F10: Peeling luninoso | G10: Credomatic | H10: 1800
B11: 45502 | C11: 3042267056 | D11: 4 | E11: Susy Villas | F11: Peeling luninoso (Sesderma) | G11: Visa L. | H11: 1800
B12: 45503 | C12: 3704311757 | D12: 2 | E12: Mariela Saravia | F12: Peeling luminoso (sesderma) | G12: Visa L. | H12: 900
B13: 45509 | C13: 933773783 | D13: 1 | E13: Magadith Estrada | F13: Peeling manos | G13: Visa | H13: 450
B14: 45547 | C14: 2218086035 | D14: 1 | E14: Maria Jose Solares | F14: Peeling toskani | G14: Visa L. | H14: 650
... B25: 45629 | C25: 3151973820 | D25: 1 | E25: Monica Secaira | F25: Peeling luminoso (sesderma) | G25: Credomatic | H25: 800
E29: Total | H29: =SUM(H3:H28) -> 29795

Sheet Spectra ginecologico
A1: Spectra ginecologico | B1: Fecha | C1: No. de Factura | D1: Cantidad | E1: Nombre del Paciente | F1: Tratamiento | G1: Forma de Pago | H1: Total
B3: 45392 | C3: 2054307925 | D3: 3 | E3: Gabriela Toledo | F3: Spectra ginecologico | G3: Visa | H3: 6000
B4: 45394 | C4: 1712341042 | D4: 3 | E4: Maria Jose Castillo | F4: Spectra ginecologico | G4: Visa L. | H4: 6000
B5: 45412 | C5: 3848161816 | D5: 3 | E5: Monica Penedo | F5: Spectra ginecologico | G5: Visa | H5: 6000
B6: 45495 | C6: 389694147 | D6: 3 | E6: Karla Bocaletti De Enriquez | F6: Spectra ginecologico | G6: Visa L. | H6: 6000
B7: 45531 | C7: 963071948 | D7: 2 | E7: Wendy Marisol Gonzalez | F7: Spectra ginecologico | G7: Credomatic | H7: 3666
B8: 45531 | C8: 963071948 | D8: 1 | E8: Wendy Marisol Gonzalez | F8: Spectra ginecologico | G8: Credomatic | H8: 1834
B9: 45544 | C9: 1594442898 | D9: 1 | E9: Mariana Marquez | F9: Spectra ginecologico | G9: Visa L. | H9: 1933
B10: 45544 | C10: 1594442898 | D10: 1 | E10: Mariana Marquez | F10: Abono spectra ginecologico | G10: Visa L. | H10: 967
B11: 45594 | C11: 2186232327 | D11: 1 | E11: Mariana Marquez | F11: Cancelación spectra ginecologico | G11: Visa | H11: 966
B12: 45594 | C12: 2186232327 | D12: 1 | E12: Mariana Marquez | F12: Abono a spectra ginecologico | G12: Visa | H12: 434
E32: Total | H32: =SUM(H3:H31) -> 33800

Sheet Eliminación de lunares
A1: Eliminación de lunares | B1: Fecha | C1: No. de Factura | D1: Cantidad | E1: Nombre del Paciente | F1: Tratamiento | G1: Forma de Pago | H1: Total
B3: --- | C3: --- | D3: --- | E3: --- | F3: --- | G3: --- | H3: 0
E4: Total | H4: =SUM(H3:H3) -> 0

Sheet Botox
A1: Botox | B1: Fecha | C1: No. de Factura | D1: Cantidad | E1: Nombre del Paciente | F1: Tratamiento | G1: Forma de Pago | H1: Total
B3: 45321 | C3: 3704505037 | D3: 55 | E3: Rita Castillo | F3: Aplicación de botox | G3: Credomatic | H3: 3025
B4: 45321 | C4: 3912912174 | D4: 24 | E4: Eugenia Sandoval De Paz | F4: Aplicación de botox | G4: Credomatic | H4: 1320
B5: 45348 | C5: 3643622117 | D5: 50 | E5: Elizabeth Molina | F5: Aplicación de botox | G5: Deposito | H5: 2750
B6: 45349 | C6: 2784511046 | D6: 54 | E6: Carolina Orellana | F6: Aplicación de botox | G6: Credomatic | H6: 2970
B7: 45370 | C7: 3729477430 | D7: 38 | E7: Evelyn Garrido | F7: Aplicación de botox | G7: Efectivo | H7: 2090
B8: 45370 | C8: 2451982431 | D8: 56 | E8: Lorena Asteguieta Figueroa | F8: Aplicación de botox | G8: Credomatic | H8: 3080
B9: 45370 | C9: 1874742448 | D9: 6 | E9: Sonia De Ponciano | F9: Aplicación de botox | G9: Credomatic | H9: 330
B10: 45370 | C10: 265570270 | D10: 56 | E10: Lissette Giron De Arana (Liz) | F10: Aplicación de botox | G10: Credomatic | H10: 3080
B11: 45370 | C11: 2083343497 | D11: 35 | E11: Lorena Abularach | F11: Aplicación de botox | G11: Efectivo | H11: 1925
B12: 45370 | C12: 315310982 | D12: 56 | E12: Evelyn Orantes De Garcia | F12: Aplicación de botox | G12: Credomatic | H12: 3080
B13: 45370 | C13: 4027335242 | D13: 56 | E13: Caro Vasquez | F13: Aplicación de botox | G13: Credomatic | H13: 3080
B14: 45370 | C14: 3545845509 | D14: 56 | E14: Rosa Maria Miralles | F14: Aplicación de botox | G14: Credomatic | H14: 3080
... B211: 45520 | C211: 1951616483 | D211: 204 | E211: Reyna Yessenia Garcia | F211: Aplicación de botox | G211: Visa | H211: 11220
B212: 22/08/20204 | C212: 3492106083 | D212: 9 | E212: Fabiola Reyes | F212: Aplicación de botox | G212: Credomatic | H212: 495
B213: 45533 | C213: 3043639535 | D213: 55 | E213: Rocio Molina | F213: Aplicación de botox | G213: Credomatic | H213: 3025
B214: 45541 | C214: 884099962 | D214: 7 | E214: Erika Aquino | F214: Aplicación de botox | G214: Credomatic | H214: 385
B215: 45545 | C215: 1401375998 | D215: 50 | E215: Mabby Morales | F215: Aplicación de botox | G215: Visa | H215: 2750
B216: 45545 | C216: 2665369435 | D216: 7 | E216: Jennifer Gonzalez | F216: Aplicación de botox | G216: Visa | H216: 385
B217: 45546 | C217: 1129333725 | D217: 56 | E217: Virginia Castillo | F217: Aplicación de botox | G217: Visa | H217: 3080
B218: 45547 | C218: 596134741 | D218: 20 | E218: Lidia Coronado | F218: Aplicación de botox | G218: Visa | H218: 1100
B219: 45548 | C219: 3899019191 | D219: 39 | E219: Cristina Tejada | F219: Aplicación de botox | G219: Visa L. | H219: 2145
B220: 45551 | C220: 1328694625 | D220: 36 | E220: Maggie Villeda | F220: Aplicación de botox | G220: Credomatic | H220: 1980
B221: 45552 | C221: 4192094551 | D221: 51 | E221: Vinicio Suchini | F221: Aplicación de botox | G221: Visa | H221: 2805
B222: 45572 | C222: 2870169166 | D222: 41 | E222: Doris Pozadas | F222: Aplicación de botox | G222: Visa | H222: 2255
B223: 45595 | C223: 254627593 | D223: 40 | E223: Marta De Rosales | F223: Aplicación de botox | G223: Efectivo | H223: 2200
B224: 45615 | C224: 2021540058 | D224: 59 | E224: Ana Gisela Castillo | F224: Aplicación de botox | G224: Credomatic | H224: 3245
... B348: 45624 | C348: 1438533192 | D348: 30 | E348: Ana Eloisa De Lopez | F348: Aplicación de botox | G348: Deposito | H348: 1650
E349: Total | H349: =SUM(H3:H348) -> 750659.99

Sheet Encimas
A1: Encimas | B1: Fecha | C1: No. de Factura | D1: Cantidad | E1: Nombre del Paciente | F1: Tratamiento | G1: Forma de Pago | H1: Total
B3: --- | C3: --- | D3: --- | E3: --- | F3: --- | G3: --- | H3: 0
E4: Total | H4: =SUM(H3:H3) -> 0

Sheet Grow
A1: Grow | B1: Fecha | C1: No. de Factura | D1: Cantidad | E1: Nombre del Paciente | F1: Tratamiento | G1: Forma de Pago | H1: Total
B3: 45322 | C3: 1256017222 | D3: 1 | E3: Quimica Industrial Guatemalteca, S.A. | F3: Línea telefonica | G3: Cheque | H3: 1461.59
B4: 45322 | C4: 1256017222 | D4: 1 | E4: Quimica Industrial Guatemalteca, S.A. | F4: Servicios prestados recepcionista | G4: Cheque | H4: 3055.5
B5: 45322 | C5: 1256017222 | D5: 1 | E5: Quimica Industrial Guatemalteca, S.A. | F5: Servicios prestados asistente administrativo | G5: Cheque | H5: 3395
B6: 45351 | C6: 3048884158 | D6: 1 | E6: Quimica Industrial Guatemalteca, S.A. | F6: Línea telefonica | G6: Cheque | H6: 1461.59
B7: 45351 | C7: 1256017222 | D7: 1 | E7: Quimica Industrial Guatemalteca, S.A. | F7: Servicios prestados recepcionista | G7: Cheque | H7: 3055.5
B8: 45351 | C8: 1256017222 | D8: 1 | E8: Quimica Industrial Guatemalteca, S.A. | F8: Servicios prestados asistente administrativo | G8: Cheque | H8: 3395
B9: 45351 | C9: 1256017222 | D9: 1 | E9: Quimica Industrial Guatemalteca, S.A. | F9: Otros | G9: Cheque | H9: 1200
B10: 45380 | C10: 4077864874 | D10: 1 | E10: Quimica Industrial Guatemalteca, S.A. | F10: Línea telefonica | G10: Cheque | H10: 1461.59
B11: 45380 | C11: 4077864874 | D11: 1 | E11: Quimica Industrial Guatemalteca, S.A. | F11: Servicios prestados recepcionista | G11: Cheque | H11: 3055.5
B12: 45380 | C12: 4077864874 | D12: 1 | E12: Quimica Industrial Guatemalteca, S.A. | F12: Servicios prestados asistente administrativo | G12: Cheque | H12: 3395
B13: 45412 | C13: 3258271372 | D13: 1 | E13: Quimica Industrial Guatemalteca, S.A. | F13: Línea telefonica | G13: Cheque | H13: 1461.59
B14: 45412 | C14: 3258271372 | D14: 1 | E14: Quimica Industrial Guatemalteca, S.A. | F14: Servicios prestados recepcionista | G14: Cheque | H14: 3055.5
... B39: 45644 | C39: 2634170552 | D39: 1 | E39: Quimica Industrial Guatemalteca, S.A. | F39: Servicios prestados asistente administrativo | G39: Cheque | H39: 3395
E40: Total | H40: =SUM(H3:H39) -> 96145.08

Sheet Abonos a tratamientos
A1: Abono | B1: Fecha | C1: No. de Factura | D1: Cantidad | E1: Nombre del Paciente | F1: Tratamiento | G1: Forma de Pago | H1: Total
B3: 45372 | C3: 3317254792 | D3: 1 | E3: Ana Cristina Rios | F3: Abono a tratamiento | G3: Credomatic | H3: 1000
E4: Total | H4: =SUM(H3:H3) -> 1000

Sheet Cambio de tratamiento
A1: Diferencia por cambio de tratamiento | B1: Fecha | C1: No. de Factura | D1: Cantidad | E1: Nombre del Paciente | F1: Tratamiento | G1: Forma de Pago | H1: Total
B3: 45324 | C3: 318851396 | D3: 1 | E3: Alvaro Ruata | F3: Diferencias por cambio de tratamiento | G3: Credomatic | H3: 1500
E8: Total | H8: =SUM(H3:H7) -> 1500

Sheet Microdermoabrasión
A1: Microdermoabrasión | B1: Fecha | C1: No. de Factura | D1: Cantidad | E1: Nombre del Paciente | F1: Tratamiento | G1: Forma de Pago | H1: Total
B3: 45426 | C3: 1115768733 | D3: 1 | E3: Evelyn Hernandez | F3: Microdermoabrasión | G3: Credomatic | H3: 350
E5: Total | H5: =SUM(H3:H4) -> 350

Sheet Terapia Luminica
A1: Terapia Luminica | B1: Fecha | C1: No. de Factura | D1: Cantidad | E1: Nombre del Paciente | F1: Tratamiento | G1: Forma de Pago | H1: Total
B3: --- | C3: --- | D3: --- | E3: --- | F3: --- | G3: --- | H3: 0
E4: Total | H4: =SUM(H3:H3) -> 0

Sheet Oscilación
A1: Oscilación | B1: Fecha | C1: No. de Factura | D1: Cantidad | E1: Nombre del Paciente | F1: Tratamiento | G1: Forma de Pago | H1: Total
B3: 45299 | C3: 1694188645 | D3: 5 | E3: Sandra Rosario Recinos | F3: Oscilación profunda | G3: Visa | H3: 2500
B4: 45301 | C4: 1218331445 | D4: 4 | E4: Daniela Sanchez | F4: Oscilación profunda | G4: Efectivo $ | H4: 2000
B5: 45301 | C5: 1218331445 | D5: 1 | E5: Daniela Sanchez | F5: Abono a oscilación profunda | G5: Efectivo $ | H5: 280
B6: 45302 | C6: 221332775 | D6: 10 | E6: Claudia Sofia Ceballos | F6: Oscilación profunda | G6: Efectivo | H6: 5000
B7: 45303 | C7: 1072516240 | D7: 1 | E7: Paola Mendoza | F7: Oscilación profunda | G7: Efectivo | H7: 780
B8: 45313 | C8: 2787788939 | D8: 4 | E8: Virginia Morales | F8: Oscilación profunda | G8: Credomatic | H8: 2000
B9: 45314 | C9: 2387298960 | D9: 5 | E9: Diana Linares | F9: Oscilación profunda | G9: Credomatic | H9: 2500
B10: 45320 | C10: 69486400 | D10: 8 | E10: Marilyn Muñoz | F10: Oscilación profunda | G10: Visa | H10: 4000
B11: 45327 | C11: 171723800 | D11: 4 | E11: Andy Reyes | F11: Oscilación profunda | G11: Visa | H11: 2000
B12: 45328 | C12: 1610827727 | D12: 5 | E12: Rocio De Pullin | F12: Oscilación profunda | G12: Credomatic | H12: 2500
B13: 45336 | C13: 815286238 | D13: 7 | E13: Marilyn Muñoz | F13: Oscilación profunda | G13: Visa | H13: 3500
B14: 45342 | C14: 740969785 | D14: 10 | E14: Carla Santizo | F14: Oscilación profunda | G14: Visa | H14: 5000
... B42: 45601 | C42: 222447949 | D42: 5 | E42: Viole Guzman | F42: Oscilación profunda | G42: Visa L. | H42: 2500
E53: Total | H53: =SUM(H3:H52) -> 90610

Sheet Sueros
A1: Sueros | B1: Fecha | C1: No. de Factura | D1: Cantidad | E1: Nombre del Paciente | F1: Tratamiento | G1: Forma de Pago | H1: Total
B3: 45300 | C3: 3027322109 | D3: 1 | E3: Maria Mercedes Moran | F3: Suero glutation | G3: Visa | H3: 750
B4: 45300 | C4: 2154447991 | D4: 3 | E4: Vanessa Smith De Vargas | F4: Suero glutation | G4: Credomatic | H4: 2250
B5: 45300 | C5: 3199420133 | D5: 1 | E5: Maria Mercedes Garcia De Moran | F5: Suero glutation | G5: Visa | H5: 750
B6: 45300 | C6: 4234036202 | D6: 1 | E6: Luis Garrido | F6: Suero glutation | G6: Visa | H6: 750
B7: 45310 | C7: 1306282846 | D7: 1 | E7: José Antonio Corrales | F7: Suero glutation | G7: Visa L. | H7: 750
B8: 45310 | C8: 1306282846 | D8: 1 | E8: Ana Herrera | F8: Suero glutation | G8: Visa L. | H8: 750
B9: 45315 | C9: 1995916393 | D9: 1 | E9: Claudia Maria De León | F9: Suero glutation | G9: Visa | H9: 750
B10: 45316 | C10: 1235308280 | D10: 1 | E10: Eugenia Madrid De Paredes | F10: Suero glutation | G10: Credomatic | H10: 750
B11: 45323 | C11: 706495947 | D11: 1 | E11: Lissette Cifuentes | F11: Suero glutation | G11: Visa L. | H11: 750
B12: 45324 | C12: 2694202194 | D12: 2 | E12: Mercedes Moran | F12: Suero glutation | G12: Credomatic | H12: 1500
B13: 45328 | C13: 3124972219 | D13: 1 | E13: Maria Mercedes De Moran | F13: Suero glutation | G13: Visa | H13: 750
B14: 45328 | C14: 661602431 | D14: 1 | E14: Patricia De Suarez | F14: Suero glutation | G14: Deposito | H14: 750
... B83: 45646 | C83: 4254155511 | D83: 1 | E83: Jose Batres | F83: Suero glutation | G83: Credomatic | H83: 750
E91: Total | H91: =SUM(H3:H90) -> 78070

Sheet Presoterapia
A1: Presoterapia | B1: Fecha | C1: No. de Factura | D1: Cantidad | E1: Nombre del Paciente | F1: Tratamiento | G1: Forma de Pago | H1: Total
B3: 45488 | C3: 1988379910 | D3: 1 | E3: Gloria Maria Sanchez | F3: Presoterapia | G3: Credomatic | H3: 250
E6: Total | H6: =SUM(H3:H5) -> 250

Sheet Nioo
A1: Nioo | B1: Fecha | C1: No. de Factura | D1: Cantidad | E1: Nombre del Paciente | F1: Tratamiento | G1: Forma de Pago | H1: Total
B3: 45314 | C3: 3983101787 | D3: 6 | E3: Silvia Martinez De Garza | F3: Nioo trinity abdomen, cintura y espalda | G3: Visa | H3: 3000
B4: 45328 | C4: 1239304704 | D4: 8 | E4: Zoila Esperanza Valencia | F4: Nioo abdomen, cintura, chaparrera, entrepierna y parte posterior de la pierna | G4: Credomatic | H4: 4368
B5: 45384 | C5: 3862580577 | D5: 8 | E5: Evelyn Castillo De Castañeda | F5: Nioo abdomen, cintura, entrepierna y parte posterior de la pierna | G5: Visa | H5: 4368
B6: 45392 | C6: 1103053273 | D6: 4 | E6: Dalia Elizabeth Diaz | F6: Nioo abdomen y cintura | G6: Visa | H6: 1560
B7: 45393 | C7: 3140305740 | D7: 4 | E7: Dalia Maribel Diaz De Diaz | F7: Nioo abdomen, cintura y espalda | G7: Visa | H7: 1560
E40: Total | H40: =SUM(H3:H39) -> 14856

Sheet Sedación
A1: Sedación | B1: Fecha | C1: No. de Factura | D1: Cantidad | E1: Nombre del Paciente | F1: Tratamiento | G1: Forma de Pago | H1: Total
B3: 45406 | C3: 522404626 | D3: 1 | E3: Evelyn Cerna De Hurtado | F3: Por servicio de sedación | G3: Efectivo | H3: 500
B4: 45426 | C4: 85541046 | D4: 1 | E4: Maria Jose Garcia Gordillo | F4: Servicio por sedación | G4: Credomatic | H4: 400
B5: 45471 | C5: 3951707648 | D5: 1 | E5: Nina Roman | F5: Por servicio de sedación | G5: Deposito | H5: 400
B6: 45504 | C6: 281562593 | D6: 1 | E6: Pricila Duarte | F6: Por servicio de sedación | G6: Credomatic | H6: 410
B7: 45625 | C7: 866402595 | D7: 1 | E7: Sandra Jimenez | F7: Por servicio de sedación | G7: Deposito | H7: 400
B8: 45625 | C8: 65815975 | D8: 1 | E8: Veronica Jimenez | F8: Por servicio de sedación | G8: Deposito | H8: 400
B9: 45629 | C9: 1225149328 | D9: 1 | E9: Miriam Nurith Barrientos De Farrach | F9: Por servicio de sedación | G9: Efectivo | H9: 400
E10: Total | H10: =SUM(H3:H9) -> 2910

Sheet Masaje reflexologia
A1: Sedación | B1: Fecha | C1: No. de Factura | D1: Cantidad | E1: Nombre del Paciente | F1: Tratamiento | G1: Forma de Pago | H1: Total
B3: 45348 | C3: 2742046411 | D3: 1 | E3: Luis Garrido | F3: Masaje de reflexologia | G3: Credomatic | H3: 200
E4: Total | H4: =SUM(H3:H3) -> 200

Sheet Intrasure post-operatorio
A1: Intrasure post-operatorio | B1: Fecha | C1: No. de Factura | D1: Cantidad | E1: Nombre del Paciente | F1: Tratamiento | G1: Forma de Pago | H1: Total
B3: 45350 | C3: 1237076442 | D3: 10 | E3: Claudia Arrecis | F3: Intrasure post-operatorio | G3: Efectivo | H3: 5000
B4: 45355 | C4: 1405176394 | D4: 10 | E4: Naima Werren | F4: Intrasure post-operatorio | G4: Visa | H4: 5000
B5: 45355 | C5: 2570077656 | D5: 10 | E5: Ana Lucia Armas | F5: Intrasure post-operatorio | G5: Visa | H5: 5000
B6: 45373 | C6: 557860364 | D6: 5 | E6: Ethia Dessire Oajaca Hurtado | F6: Intrasure post-operatorio | G6: Credomatic | H6: 2500
B7: 45383 | C7: 1790724770 | D7: 9 | E7: Maria Lourdes Garcia | F7: Intrasure post-operatorio | G7: Credomatic | H7: 4500
B8: 45397 | C8: 3227928430 | D8: 5 | E8: Ines Batres | F8: Intrasure post-operatorio | G8: Visa | H8: 2500
B9: 45420 | C9: 1414023308 | D9: 8 | E9: Claudia Romero | F9: Intrasure post-operatorio | G9: Deposito | H9: 4000
B10: 45440 | C10: 3523888738 | D10: 6 | E10: Williams Lopez Dieguez | F10: Intrasure post-operatorio | G10: Visa | H10: 3000
B11: 45440 | C11: 4104929880 | D11: 5 | E11: Michelle Leonardo | F11: Intrasure post-operatorio | G11: Credomatic | H11: 2500
B12: 45447 | C12: 3884991468 | D12: 4 | E12: Eva Recinos Vasquez | F12: Intrasure post-operatorio | G12: Visa | H12: 2000
B13: 45447 | C13: 3884991468 | D13: 6 | E13: Eva Recinos Vasquez | F13: Intrasure post-operatorio | G13: Efectivo | H13: 3000
B14: 45454 | C14: 75122376 | D14: 5 | E14: Florencia De La Roca Flores | F14: Intrasure post-operatorio | G14: Visa | H14: 2500
... B33: 45556 | C33: 1181240724 | D33: 5 | E33: Paola Calderon | F33: Intrasuere post-operatorio | G33: Visa L. | H33: 2500
B34: 22/08/20204 | C34: 1640252489 | D34: 10 | E34: Ninett Vargas | F34: Intrasuere post-operatorio | G34: Deposito | H34: 5000
B35: 45530 | C35: 3659744214 | D35: 3 | E35: Rolando Archila | F35: Intrasuere post-operatorio | G35: Credomatic | H35: 1500
B36: 45538 | C36: 1964396493 | D36: 10 | E36: Elda Maribel Estrada | F36: Intrasure post-operatorio | G36: Visa | H36: 5000
B37: 45539 | C37: 1533821579 | D37: 5 | E37: Ninett Vargas | F37: Intrasure post-operatorio | G37: Credomatic | H37: 2500
B38: 45541 | C38: 17055932 | D38: 5 | E38: Rebeca Pineda | F38: Intrasure post-operatorio | G38: Deposito | H38: 2500
B39: 45544 | C39: 489900255 | D39: 10 | E39: Mario Andres Acevedo | F39: Intrasure post-operatorio | G39: Credomatic | H39: 5000
B40: 45553 | C40: 3104721567 | D40: 10 | E40: Ana Cristina Rios | F40: Intrasure post-operatorio | G40: Visa | H40: 5000
B41: 45555 | C41: 3821620307 | D41: 5 | E41: Milvian Orellana | F41: Intrasure post-operatorio | G41: Efectivo | H41: 2500
B42: 45555 | C42: 4127540157 | D42: 10 | E42: Gabriela Cuellar | F42: Intrasure post-operatorio | G42: Visa | H42: 5000
B43: 45558 | C43: 2458012255 | D43: 2 | E43: Kimberly Rodas | F43: Intrasure post-operatorio | G43: Visa | H43: 1000
B44: 45566 | C44: 3832365736 | D44: 10 | E44: Lisbeth Viviana Davila | F44: Intrasure post-operatorio | G44: Visa | H44: 5000
B45: 45568 | C45: 3236253181 | D45: 10 | E45: Rony Alvarado | F45: Intrasure post-operatorio | G45: Visa | H45: 5000
B46: 45572 | C46: 1766476073 | D46: 10 | E46: Ernesto Guzman | F46: Intrasure post-operatorio | G46: Visa | H46: 5000
... B65: 45644 | C65: 2844082337 | D65: 1 | E65: Eliana Mazariegos | F65: Intrasure post-operatorio | G65: Visa L. | H65: 600
E66: Total | H66: =SUM(H3:H65) -> 205600

Sheet Mascarilla
A1: Mascarilla | B1: Fecha | C1: No. de Factura | D1: Cantidad | E1: Nombre del Paciente | F1: Tratamiento | G1: Forma de Pago | H1: Total
B3: 45331 | C3: 3728426352 | D3: 1 | E3: Isabel Dedet | F3: Mascarilla de megadosis de vitamina C (germaine) | G3: Credomatic | H3: 650
B4: 45373 | C4: 698630611 | D4: 1 | E4: Irene Piñol De Morales | F4: Aplicación mascarilla | G4: Credomatic | H4: 150
E5: Total | H5: =SUM(H3:H4) -> 800

Sheet Hifu Ultra-forme
A1: Hifu Ultra-forme | B1: Fecha | C1: No. de Factura | D1: Cantidad | E1: Nombre del Paciente | F1: Tratamiento | G1: Forma de Pago | H1: Total
B3: 45349 | C3: 2695384338 | D3: 1 | E3: Melissica Cohen | F3: Hifu ultra-forme papada | G3: Visa | H3: 3840
B4: 45357 | C4: 1854623442 | D4: 1 | E4: Ximena De Bonatti | F4: Hifu facial | G4: Visa | H4: 6800
B5: 45364 | C5: 2314817074 | D5: 1 | E5: Karla De Bonatti | F5: Abono a hifu ultra-formner ovalo facial | G5: Visa | H5: 300
B6: 45364 | C6: 2314817074 | D6: 1 | E6: Karla De Bonatti | F6: Cancelación a hifu ultra-formner ovalo facial | G6: Deposito | H6: 3900
B7: 45364 | C7: 2314817074 | D7: 1 | E7: Karla De Bonatti | F7: Hifu ultra-formner papada | G7: Deposito | H7: 2600
B8: 45371 | C8: 3013034420 | D8: 1 | E8: Yeimi Paola Lopez | F8: Hifu ultra-formner papada | G8: Visa | H8: 2600
B9: 45384 | C9: 3072214406 | D9: 1 | E9: Rony Caballeros | F9: Hifu ultraformer papada | G9: Deposito | H9: 2600
B10: 45384 | C10: 3072214406 | D10: 1 | E10: Rony Caballeros | F10: Hifu ultraformer ojos y frente | G10: Deposito | H10: 2600
B11: 45384 | C11: 3072214406 | D11: 1 | E11: Rony Caballeros | F11: Hifu ultraformercontorno mandibular | G11: Deposito | H11: 2600
B12: 45384 | C12: 3072214406 | D12: 1 | E12: Rony Caballeros | F12: Hifu ultraformer ovalo facial | G12: Deposito | H12: 2600
B13: 45385 | C13: 2392803424 | D13: 1 | E13: Ana Silvia Lopez Quijada | F13: Hifu ultraformer cuello | G13: Deposito | H13: 4000
B14: 45387 | C14: 2569159485 | D14: 1 | E14: Annie Dougherty | F14: Hifu ultraformer ojos y frente | G14: Visa L. | H14: 2600
... B61: 45628 | C61: 1987004504 | D61: 1 | E61: Rony Caballeros | F61: Hifu ultraformer cotorno mandibular | G61: Deposito | H61: 2600
E62: Total | H62: =SUM(H3:H61) -> 226045

Sheet Powershape
A1: Powershape | B1: Fecha | C1: No. de Factura | D1: Cantidad | E1: Nombre del Paciente | F1: Tratamiento | G1: Forma de Pago | H1: Total
B3: 45411 | C3: 3358674097 | D3: 8 | E3: Cyntia Castillo De Zelaya | F3: Powershape moldeo de glúteos y parte posterior de la pierna | G3: Visa | H3: 4000
B4: 45426 | C4: 1007568992 | D4: 8 | E4: Marta De Rosales | F4: Powershape abdomen, cintura y espalda | G4: Visa L. | H4: 4000
B5: 45440 | C5: 1100628841 | D5: 8 | E5: Ethel Velasquez Rivera | F5: Powershape abdomen, espalda, cintura y brazos | G5: Credomatic | H5: 3800
B6: 45441 | C6: 1952337598 | D6: 8 | E6: Claudia Evelyn Alvarez de Jerez | F6: Powershape abdomen, cintura y piernas | G6: Visa | H6: 2000
B7: 45460 | C7: 2626440107 | D7: 8 | E7: Francis Maria Cuellar | F7: Powershape medias piernas completas | G7: Visa L. | H7: 5000
B8: 45461 | C8: 2075607868 | D8: 11 | E8: Ramon Adolfo Canek | F8: Powershape abdomen y cintura | G8: Credomatic | H8: 5951
B9: 45461 | C9: 2075607868 | D9: 1 | E9: Ramon Adolfo Canek | F9: Powershape abdomen y cintura | G9: Credomatic | H9: 549
B10: 45461 | C10: 2075607868 | D10: 11 | E10: Zoila Valencia Marroquin | F10: Powershape abdomen, cintura y piernas | G10: Visa | H10: 5951
B11: 45461 | C11: 2075607868 | D11: 1 | E11: Zoila Valencia Marroquin | F11: Powershape abdomen, cintura y piernas | G11: Visa | H11: 549
B12: 45464 | C12: 4054534147 | D12: 6 | E12: Rocio Molina | F12: Powershape entrepierna, chaparrera, banana roll, parte posterior de la pierna y gluteos | G12: Visa | H12: 3000
B13: 45467 | C13: 187188692 | D13: 8 | E13: Natalia Morales | F13: Powershape abdomen, cintura y piernas (parte posterior) | G13: Visa L. | H13: 4368
B14: 45485 | C14: 637421756 | D14: 8 | E14: Adriana Picon | F14: Powershape medias piernas completas, abdomen y cintura | G14: Visa | H14: 5000
... B19: 45625 | C19: 931810472 | D19: 8 | E19: Monica Gonzalez De Garcia | F19: Powershape abdomen, cintura y espalda | G19: Credomatic | H19: 3000
B20: Total | H20: =SUM(H3:H19) -> 63796

Sheet Exion
A1: Exion | B1: Fecha | C1: No. de Factura | D1: Cantidad | E1: Nombre del Paciente | F1: Tratamiento | G1: Forma de Pago | H1: Total
B3: 45491 | C3: 738151298 | D3: 8 | E3: Guillermo Mendoza | F3: Exion abdomen, cintura, pectoral y espalda | G3: Visa | H3: 8000
B4: 45492 | C4: 8182387171 | D4: 6 | E4: Gabriela Pinto De Pontaza | F4: Exion rostro y cuello | G4: Visa L. | H4: 6000
B5: 45496 | C5: 108740925 | D5: 3 | E5: Evelyn Zelaya Reyes | F5: Exion rostro y cuello | G5: Visa | H5: 15000
B6: 45506 | C6: 1257064907 | D6: 8 | E6: Ileana De Carrera | F6: Exion abdomen, cintura, brazos y medias piernas | G6: Visa | H6: 8000
B7: 45509 | C7: 3464447660 | D7: 3 | E7: Hilda De Zimeri | F7: Exion radiofrecuencia fraccionada rostro y papada | G7: Visa L. | H7: 15000
B8: 45511 | C8: 2346273771 | D8: 8 | E8: Wendy Marisol Gonzalez | F8: Exion abdomen completo, cintura y espalda baja | G8: Visa | H8: 8000
B9: 45513 | C9: 3811593761 | D9: 8 | E9: Angie Vitola | F9: Exion abdomen y cintura | G9: Visa L. | H9: 8000
B10: 45517 | C10: 1248611610 | D10: 8 | E10: Mariana Hernandez | F10: Exion abdomen, cintura, espalda altra y brazos | G10: Visa | H10: 8000
B11: 45518 | C11: 2038710464 | D11: 1 | E11: Monica Valladares | F11: Exion abdomen, cintura, espalda y brazos | G11: Efectivo | H11: 1000
B12: 45530 | C12: 2942322718 | D12: 3 | E12: Elizabeth Molina | F12: Exion radiofrecuencia fraccionada rostro y papada | G12: Visa | H12: 15000
B13: 45539 | C13: 3709092524 | D13: 8 | E13: Francis Cuellar | F13: Exión | G13: Visa L. | H13: 8000
B14: 45540 | C14: 1062880078 | D14: 6 | E14: Agnes Castillo | F14: Exión rostro y cuello | G14: Visa | H14: 6000
... B17: 45581 | C17: 3055767323 | D17: 8 | E17: Maria Conchita Vasquez | F17: Exion abdomen, cintura, brazos, y espalda alta | G17: Visa L. | H17: 8000
E18: Total | H18: =SUM(H3:H17) -> 126000

Sheet Emsculpt NEO
A1: Emsculpt NEO | B1: Fecha | C1: No. de Factura | D1: Cantidad | E1: Nombre del Paciente | F1: Tratamiento | G1: Forma de Pago | H1: Total
B3: 45491 | C3: 738151298 | D3: 5 | E3: Guillermo Mendoza | F3: Emsculpt neo parte frenta de la pierna | G3: Visa | H3: 8330
B4: 45491 | C4: 738151298 | D4: 1 | E4: Guillermo Mendoza | F4: Emsculpt neo parte frenta de la pierna | G4: Visa | H4: 1670
B5: 45491 | C5: 738151298 | D5: 5 | E5: Guillermo Mendoza | F5: Emsculpt neo parte postrior de la pierna | G5: Visa | H5: 8330
B6: 45491 | C6: 738151298 | D6: 1 | E6: Guillermo Mendoza | F6: Emsculpt neo parte postrior de la pierna | G6: Visa | H6: 1670
B7: 45518 | C7: 739459705 | D7: 6 | E7: Maria Jose Alvarez | F7: Emsculpt neo glúteos | G7: Visa | H7: 9999.9996
B8: 45555 | C8: 4173546639 | D8: 5 | E8: Sissel Morales | F8: Emculpt neo | G8: Visa | H8: 8330
B9: 45555 | C9: 4173546639 | D9: 1 | E9: Sissel Morales | F9: Emculpt neo | G9: Visa | H9: 1670
B10: 45560 | C10: 943540615 | D10: 3 | E10: Maria Jose Alvarez | F10: Emsculpt neo piernas | G10: Efectivo | H10: 4999.9998
B11: 45560 | C11: 943540615 | D11: 3 | E11: Maria Jose Alvarez | F11: Emsculpt neo piernas | G11: Visa | H11: 4999.9998
B12: 45572 | C12: 2216249375 | D12: 5 | E12: Karen Orellana | F12: Emsculpt neo | G12: Visa | H12: 8330
B13: 45572 | C13: 2216249375 | D13: 1 | E13: Karen Orellana | F13: Emsculpt neo | G13: Visa | H13: 1670
B14: 45575 | C14: 3017821283 | D14: 3 | E14: Francisco Lavarreda | F14: Emsculpt neo | G14: Deposito | H14: 4999.98
... B24: 45615 | C24: 2211400414 | D24: 1 | E24: Maria Jose Alvarez | F24: Emsculpt neo | G24: Visa L. | H24: 1665
E25: Total | H25: =SUM(H3:H24) -> 115000
