Workbook

Sheet PRESENTACIÓN DE RESULTADOS
A1: Tratamiendo | B1: Enero | C1: Febrero | D1: Marzo | E1: Abril | F1: Mayo | G1: Junio | H1: Julio | I1: Agosto | J1: Septiembre | K1: Octubre | L1: Noviembre | M1: Diciembre | N1: Total
A2: Producto | B2: =SUM(Producto!H3:H19) -> 11814 | C2: =SUM(Producto!H20:H44) -> 15270 | D2: =SUM(Producto!H45:H74) -> 15426.55 | E2: =SUM(Producto!H75:H83) -> 7210 | F2: =SUM(Producto!H84:H107) -> 15220 | G2: =SUM(Producto!H108:H119) -> 7370 | H2: =SUM(Producto!H120:H138) -> 12210 | I2: =SUM(Producto!H139:H149) -> 8800 | J2: =SUM(Producto!H150:H169) -> 14040.46 | K2: =SUM(Producto!H170:H177) -> 6460 | L2: =SUM(Producto!H178:H212) -> 25000 | M2: =SUM(Producto!H213:H231) -> 13494 | N2: =SUM(B2:M2) -> 152315.01 | O2: =+Producto!H232 -> 152315.01 | P2: =+O2-N2 -> 0
A3: Acido hialuronico | B3: 0 | C3: 0 | D3: 0 | E3: 0 | F3: =SUM('Acido hialuronico'!H3) -> 2700 | G3: 0 | H3: 0 | I3: =SUM('Acido hialuronico'!H4:H5) -> 6300 | J3: 0 | K3: =SUM('Acido hialuronico'!H6) -> 2800 | L3: =SUM('Acido hialuronico'!H7:H23) -> 42000 | M3: =SUM('Acido hialuronico'!H24:H25) -> 5800 | N3: =SUM(B3:M3) -> 59600 | O3: =+'Acido hialuronico'!H26 -> 59600 | P3: =+O3-N3 -> 0
A4: Depilación | B4: =SUM(Depilación!H3:H16) -> 6212.5 | C4: =SUM(Depilación!H17:H24) -> 3950 | D4: =SUM(Depilación!H25:H36) -> 5605.25 | E4: =SUM(Depilación!H37:H39) -> 2412.5 | F4: =SUM(Depilación!H40:H48) -> 2311.25 | G4: =SUM(Depilación!H49:H65) -> 8116.5 | H4: =SUM(Depilación!H66:H83) -> 12928.75 | I4: =SUM(Depilación!H84:H93) -> 4006.25 | J4: =SUM(Depilación!H98:H109) -> 5604 | K4: =SUM(Depilación!H110:H125) -> 13721.25 | L4: =SUM(Depilación!H126:H134) -> 5861.25 | M4: =SUM(Depilación!H135:H143) -> 3854 | N4: =SUM(B4:M4) -> 74583.5 | O4: =+Depilación!H144 -> 74583.5 | P4: =+O4-N4 -> 0
A5: Emsculpt | B5: =SUM(Emsculpt!H3) -> 9000 | C5: =SUM(Emsculpt!H4) -> 6750 | D5: =SUM(Emsculpt!H5) -> 6750 | E5: =SUM(Emsculpt!H6:H7) -> 6750 | F5: =SUM(Emsculpt!H8:H9) -> 13500 | G5: 0 | H5: 0 | I5: =SUM(Emsculpt!H10) -> 6750 | J5: =SUM(Emsculpt!H11:H14) -> 20250 | K5: =SUM(Emsculpt!H15) -> 6750 | L5: =SUM(Emsculpt!H16:H20) -> 17750 | M5: =SUM(Emsculpt!H21:H27) -> 25000 | N5: =SUM(B5:M5) -> 119250 | O5: =+Emsculpt!H28 -> 119250 | P5: =+O5-N5 -> 0
A6: Emtone | B6: =SUM(Emtone!H3:H7) -> 18200 | C6: =SUM(Emtone!H8) -> 5000 | D6: =SUM(Emtone!H9:H13) -> 25100 | E6: =SUM(Emtone!H14) -> 5000 | F6: =SUM(Emtone!H15) -> 6500 | G6: =SUM(Emtone!H16:H20) -> 20000 | H6: =SUM(Emtone!H21:H22) -> 10000 | I6: =SUM(Emtone!H23) -> 5000 | J6: =SUM(Emtone!H24:H26) -> 16000 | K6: 0 | L6: =SUM(Emtone!H27:H32) -> 25590.4 | M6: =SUM(Emtone!H33:H35) -> 10000 | N6: =SUM(B6:M6) -> 146390.4 | O6: =+Emtone!H36 -> 146390.4 | P6: =+O6-N6 -> 0
A7: Exilis | B7: =SUM(Exilis!H3:H8) -> 30750 | C7: =SUM(Exilis!H9:H17) -> 32875 | D7: =SUM(Exilis!H18:H25) -> 42250 | E7: =SUM(Exilis!H26:H33) -> 42375 | F7: =SUM(Exilis!H34:H42) -> 58500 | G7: =SUM(Exilis!H43:H53) -> 45175 | H7: =SUM(Exilis!H54:H61) -> 24721 | I7: =SUM(Exilis!H62:H66) -> 18900 | J7: =SUM(Exilis!H67:H74) -> 48500 | K7: =SUM(Exilis!H75:H76) -> 7500 | L7: =SUM(Exilis!H77:H85) -> 44240 | M7: =SUM(Exilis!H86:H91) -> 22746 | N7: =SUM(B7:M7) -> 418532 | O7: =+Exilis!H92 -> 418532 | P7: =+O7-N7 -> 0
A8: Exfoliación | B8: 0 | C8: 0 | D8: 0 | E8: 0 | F8: 0 | G8: 0 | H8: 0 | I8: 0 | J8: 0 | K8: 0 | L8: 0 | M8: 0 | N8: =SUM(B8:M8) -> 0 | O8: =+Exfoliación!H4 -> 0 | P8: =+O8-N8 -> 0
A9: Facial purificante | B9: =SUM('Facial purificante'!H3:H9) -> 6057.5 | C9: =SUM('Facial purificante'!H10:H12) -> 1600 | D9: =SUM('Facial purificante'!H13:H18) -> 3200 | E9: =SUM('Facial purificante'!H19:H21) -> 2625 | F9: =SUM('Facial purificante'!H22:H35) -> 9850 | G9: =SUM('Facial purificante'!H36:H42) -> 3850 | H9: =SUM('Facial purificante'!H43:H44) -> 1782.5 | I9: =SUM('Facial purificante'!H45:H47) -> 2750 | J9: =SUM('Facial purificante'!H48:H56) -> 6900 | K9: =SUM('Facial purificante'!H57:H62) -> 3450 | L9: =SUM('Facial purificante'!H63:H72) -> 5922.5 | M9: =SUM('Facial purificante'!H73:H77) -> 5666.9999 | N9: =SUM(B9:M9) -> 53654.5 | O9: =+'Facial purificante'!H78 -> 53654.5 | P9: =+O9-N9 -> 0
A10: Hifu | B10: 0 | C10: =SUM(Hifu!H3:H5) -> 10930 | D10: 0 | E10: 0 | F10: =SUM(Hifu!H6) -> 3500 | G10: 0 | H10: =SUM(Hifu!H7:H10) -> 15200 | I10: =SUM(Hifu!H11:H12) -> 6583 | J10: 0 | K10: 0 | L10: =SUM(Hifu!H13) -> 2800 | M10: =SUM(Hifu!H14:H16) -> 13168 | N10: =SUM(B10:M10) -> 52181 | O10: =+Hifu!H17 -> 52181 | P10: =+O10-N10 -> 0
A11: Hydrafacial | B11: =SUM(Hydrafacial!H3:H4) -> 1167.6 | C11: =SUM(Hydrafacial!H5:H6) -> 3169 | D11: =SUM(Hydrafacial!H7:H8) -> 1668 | E11: 0 | F11: =SUM(Hydrafacial!H9:H10) -> 1595 | G11: =SUM(Hydrafacial!H11:H12) -> 3636.24 | H11: =SUM(Hydrafacial!H13:H17) -> 5985.4 | I11: =SUM(Hydrafacial!H18:H19) -> 2501.4 | J11: =SUM(Hydrafacial!H20:H21) -> 2502 | K11: =SUM(Hydrafacial!H22:H26) -> 6122 | L11: =SUM(Hydrafacial!H27:H29) -> 3669.6 | M11: =SUM(Hydrafacial!H30:H35) -> 6672 | N11: =SUM(B11:M11) -> 38688.24 | O11: =+Hydrafacial!H36 -> 38688.24 | P11: =+O11-N11 -> 0
A12: Laboratorios | B12: =SUM(Laboratorios!H3:H5) -> 2810 | C12: =SUM(Laboratorios!H6) -> 47 | D12: =SUM(Laboratorios!H7) -> 750 | E12: =SUM(Laboratorios!H8) -> 750 | F12: 0 | G12: 0 | H12: =SUM(Laboratorios!H9:H11) -> 2796.95 | I12: =SUM(Laboratorios!H12:H16) -> 5186.46 | J12: 0 | K12: =SUM(Laboratorios!H17) -> 750 | L12: 0 | M12: 0 | N12: =SUM(B12:M12) -> 13090.41 | O12: =+Laboratorios!H18 -> 13090.41 | P12: =+O12-N12 -> 0
A13: Masaje linfatico | B13: =SUM('Masaje linfatico'!H3:H9) -> 6097 | C13: =SUM('Masaje linfatico'!H10:H12) -> 777 | D13: =SUM('Masaje linfatico'!H13:H19) -> 6636 | E13: =SUM('Masaje linfatico'!H20:H21) -> 2950 | F13: =SUM('Masaje linfatico'!H22:H28) -> 6518 | G13: =SUM('Masaje linfatico'!H29:H32) -> 5859 | H13: =SUM('Masaje linfatico'!H33:H36) -> 5659 | I13: =SUM('Masaje linfatico'!H37:H42) -> 6577 | J13: =SUM('Masaje linfatico'!H43:H47) -> 5459 | K13: =SUM('Masaje linfatico'!H48:H50) -> 3459 | L13: =SUM('Masaje linfatico'!H51:H54) -> 6059 | M13: =SUM('Masaje linfatico'!H55:H57) -> 4700 | N13: =SUM(B13:M13) -> 60750 | O13: =+'Masaje linfatico'!H58 -> 60750 | P13: =+O13-N13 -> 0
A14: Mesoterapia | B14: =SUM(Mesoterapia!H3) -> 4800 | C14: =SUM(Mesoterapia!H4) -> 2400 | D14: =SUM(Mesoterapia!H5:H9) -> 9490 | E14: =SUM(Mesoterapia!H10:H12) -> 9900 | F14: =SUM(Mesoterapia!H13) -> 3400 | G14: 0 | H14: =SUM(Mesoterapia!H14:H15) -> 4420 | I14: =SUM(Mesoterapia!H16) -> 5000 | J14: =SUM(Mesoterapia!H17:H20) -> 16100 | K14: 0 | L14: =SUM(Mesoterapia!H21:H22) -> 7397.6 | M14: =SUM(Mesoterapia!H23) -> 2500 | N14: =SUM(B14:M14) -> 65407.6 | O14: =+Mesoterapia!H24 -> 65407.6 | P14: =+O14-N14 -> 0
A15: Morpheus | B15: =SUM(Morpheus!H3:H18) -> 101200 | C15: =SUM(Morpheus!H19:H23) -> 50000 | D15: =SUM(Morpheus!H24:H41) -> 210000 | E15: =SUM(Morpheus!H42:H52) -> 125000 | F15: =SUM(Morpheus!H53:H66) -> 156500 | G15: =SUM(Morpheus!H67:H76) -> 85000 | H15: =SUM(Morpheus!H77:H82) -> 70000 | I15: =SUM(Morpheus!H83:H97) -> 145000 | J15: =SUM(Morpheus!H98:H101) -> 40000 | K15: =SUM(Morpheus!H102:H108) -> 80000 | L15: =SUM(Morpheus!H109:H115) -> 70000 | M15: =SUM(Morpheus!H116:H120) -> 50000 | N15: =SUM(B15:M15) -> 1182700 | O15: =+Morpheus!H121 -> 1182700 | P15: =+O15-N15 -> 0
A16: Pico-láser | B16: 0 | C16: =SUM('Pico-láser'!H3:H5) -> 5300 | D16: 0 | E16: 0 | F16: 0 | G16: 0 | H16: 0 | I16: 0 | J16: 0 | K16: 0 | L16: 0 | M16: 0 | N16: =SUM(B16:M16) -> 5300 | O16: =+'Pico-láser'!H6 -> 5300 | P16: =+O16-N16 -> 0
A17: Powershape | B17: =SUM(Powershape!H3) -> 1596 | C17: 0 | D17: 0 | E17: 0 | F17: 0 | G17: 0 | H17: 0 | I17: 0 | J17: 0 | K17: 0 | L17: 0 | M17: 0 | N17: =SUM(B17:M17) -> 1596 | O17: =+Powershape!H4 -> 1596 | P17: =+O17-N17 -> 0
A18: Profhilo | B18: 0 | C18: 0 | D18: 0 | E18: 0 | F18: 0 | G18: 0 | H18: =SUM(Profhilo!H3) -> 3000 | I18: 0 | J18: 0 | L18: =SUM(Profhilo!H4:H5) -> 10000 | M18: =SUM(Profhilo!H6:H11) -> 13750 | N18: =SUM(B18:M18) -> 26750 | O18: =+Profhilo!H12 -> 26750 | P18: =+O18-N18 -> 0
A19: PRP | B19: =SUM(PRP!H3:H5) -> 7040 | C19: =SUM(PRP!H6:H22) -> 34970 | D19: =SUM(PRP!H23:H27) -> 11200 | E19: =SUM(PRP!H28:H36) -> 8020 | F19: =SUM(PRP!H37:H59) -> 44442 | G19: =SUM(PRP!H60:H74) -> 30978.4 | H19: =SUM(PRP!H75:H92) -> 52400 | I19: =SUM(PRP!H93:H103) -> 30900 | J19: =SUM(PRP!H104:H144) -> 60200 | K19: =SUM(PRP!H145:H154) -> 21020 | L19: =SUM(PRP!H155:H161) -> 15400 | M19: =SUM(PRP!H162:H170) -> 23360 | N19: =SUM(B19:M19) -> 339930.4 | O19: =+PRP!H171 -> 339930.4 | P19: =+O19-N19 -> 0
A20: Radiofrecuencia | B20: =SUM(Radiofrecuencia!H3:H8) -> 16680 | C20: =SUM(Radiofrecuencia!H9) -> 1670 | D20: =SUM(Radiofrecuencia!H10:H13) -> 10560 | E20: =SUM(Radiofrecuencia!H14) -> 1780 | F20: =SUM(Radiofrecuencia!H15) -> 3560 | G20: =SUM(Radiofrecuencia!H16:H24) -> 24640 | H20: =SUM(Radiofrecuencia!H25:H33) -> 24676 | I20: =SUM(Radiofrecuencia!H34:H38) -> 7200 | J20: =SUM(Radiofrecuencia!H39:H46) -> 21002 | K20: =SUM(Radiofrecuencia!H47:H48) -> 8880 | L20: =SUM(Radiofrecuencia!H49:H51) -> 12015 | M20: =SUM(Radiofrecuencia!H52:H59) -> 21350 | N20: =SUM(B20:M20) -> 154013 | O20: =+Radiofrecuencia!H60 -> 154013 | P20: =+O20-N20 -> 0
A21: Ultrasonido | B21: 0 | C21: =SUM(Ultrasonido!H3) -> 220 | D21: =SUM(Ultrasonido!H4:H5) -> 1230 | E21: =SUM(Ultrasonido!H6:H11) -> 4020 | F21: =SUM(Ultrasonido!H12:H17) -> 5680 | G21: =SUM(Ultrasonido!H18:H23) -> 9450 | H21: =SUM(Ultrasonido!H24:H26) -> 3780 | I21: =SUM(Ultrasonido!H27:H28) -> 2880 | J21: =SUM(Ultrasonido!H29:H34) -> 6590 | K21: =SUM(Ultrasonido!H35) -> 180 | L21: =SUM(Ultrasonido!H36) -> 360 | M21: =SUM(Ultrasonido!H37) -> 1620 | N21: =SUM(B21:M21) -> 36010 | O21: =+Ultrasonido!H38 -> 36010 | P21: =+O21-N21 -> 0
A22: Velo de acido hialuronico | B22: =SUM('Velo de acido hialuronico'!H3:H6) -> 2550 | C22: =SUM('Velo de acido hialuronico'!H7) -> 650 | D22: 0 | E22: 0 | F22: 0 | G22: 0 | H22: 0 | I22: 0 | J22: =SUM('Velo de acido hialuronico'!H8:H11) -> 5960 | K22: 0 | L22: =SUM('Velo de acido hialuronico'!H12) -> 650 | M22: 0 | N22: =SUM(B22:M22) -> 9810 | O22: =+'Velo de acido hialuronico'!H13 -> 9810 | P22: =+O22-N22 -> 0
A23: Velox | B23: =SUM(Velox!H3) -> 2856 | C23: 0 | D23: =SUM(Velox!H4) -> 2128 | E23: =SUM(Velox!H5) -> 2500 | F23: =SUM(Velox!H6) -> 2240 | G23: =SUM(Velox!H7:H8) -> 6256 | H23: =SUM(Velox!H9:H10) -> 6528 | I23: =SUM(Velox!H11:H13) -> 6280 | J23: 0 | K23: =SUM(Velox!H14:H15) -> 5320 | L23: =SUM(Velox!H16:H17) -> 1700 | M23: =SUM(Velox!H18) -> 4000 | N23: =SUM(B23:M23) -> 39808 | O23: =+Velox!H19 -> 39808 | P23: =+O23-N23 -> 0
A24: Verju | B24: =SUM(Verju!H3:H5) -> 10100 | C24: =SUM(Verju!H6) -> 708.33 | D24: 0 | E24: 0 | F24: 0 | G24: 0 | H24: 0 | I24: 0 | J24: 0 | K24: 0 | L24: 0 | M24: 0 | N24: =SUM(B24:M24) -> 10808.33 | O24: =+Verju!H7 -> 10808.33 | P24: =+O24-N24 -> 0
A25: Vitamina C intravenosa | B25: =SUM('Vitamina C intravenosa'!H3:H26) -> 16969.5 | C25: =SUM('Vitamina C intravenosa'!H27:H47) -> 18503 | D25: =SUM('Vitamina C intravenosa'!H48:H60) -> 15940 | E25: =SUM('Vitamina C intravenosa'!H61:H71) -> 8560 | F25: =SUM('Vitamina C intravenosa'!H72:H87) -> 19795 | G25: =SUM('Vitamina C intravenosa'!H88:H101) -> 17412.6 | H25: =SUM('Vitamina C intravenosa'!H102:H109) -> 10700 | I25: =SUM('Vitamina C intravenosa'!H110:H120) -> 7998 | J25: =SUM('Vitamina C intravenosa'!H121:H141) -> 24451 | K25: =SUM('Vitamina C intravenosa'!H142:H156) -> 18026 | L25: =SUM('Vitamina C intravenosa'!H157:H174) -> 23916 | M25: =SUM('Vitamina C intravenosa'!H175:H183) -> 13751 | N25: =SUM(B25:M25) -> 196022.1 | O25: =+'Vitamina C intravenosa'!H184 -> 196022.1 | P25: =+O25-N25 -> 0
A26: Ciclo coolsculpting | B26: 0 | C26: 0 | D26: 0 | E26: =SUM('Ciclo coolsculpting'!H3) -> 18000 | F26: 0 | G26: 0 | H26: 0 | I26: =SUM('Ciclo coolsculpting'!H4) -> 9000 | J26: 0 | K26: 0 | L26: 0 | M26: 0 | N26: =SUM(B26:M26) -> 27000 | O26: =+'Ciclo coolsculpting'!H5 -> 27000 | P26: =+O26-N26 -> 0
A27: Cliovana | B27: 0 | C27: 0 | D27: 0 | E27: 0 | F27: 0 | G27: 0 | H27: 0 | I27: 0 | J27: 0 | K27: 0 | L27: 0 | M27: 0 | N27: =SUM(B27:M27) -> 0 | O27: =+Cliovana!H4 -> 0 | P27: =+O27-N27 -> 0
A28: Dermapen | B28: =SUM(Dermapen!H3) -> 3000 | C28: =SUM(Dermapen!H4:H8) -> 8160 | D28: 0 | E28: =SUM(Dermapen!H9) -> 3300 | F28: =SUM(Dermapen!H10:H11) -> 4300 | G28: =SUM(Dermapen!H12:H15) -> 4900 | H28: =SUM(Dermapen!H16) -> 1000 | I28: 0 | J28: 0 | K28: =SUM(Dermapen!H17) -> 1280 | L28: =SUM(Dermapen!H18) -> 3300 | M28: =SUM(Dermapen!H19) -> 3240 | N28: =SUM(B28:M28) -> 32480 | O28: =+Dermapen!H20 -> 32480 | P28: =+O28-N28 -> 0
A29: Láser CO2 | B29: =SUM('Láser CO2'!H3) -> 3900 | C29: 0 | D29: =SUM('Láser CO2'!H4) -> 5000 | E29: 0 | F29: =SUM('Láser CO2'!H5:H6) -> 10680 | G29: 0 | H29: 0 | I29: 0 | J29: 0 | K29: 0 | L29: =SUM('Láser CO2'!H7:H8) -> 9500 | M29: 0 | N29: =SUM(B29:M29) -> 29080 | O29: =+'Láser CO2'!H9 -> 29080 | P29: =+O29-N29 -> 0
A30: Masaje relajante | B30: =SUM('Masaje relajante'!H3:H4) -> 550 | C30: =SUM('Masaje relajante'!H5) -> 280 | D30: 0 | E30: 0 | F30: =SUM('Masaje relajante'!H6) -> 2000 | G30: =SUM('Masaje relajante'!H7:H8) -> 1050 | H30: =SUM('Masaje relajante'!H9) -> 250 | I30: =SUM('Masaje relajante'!H10) -> 250 | J30: =SUM('Masaje relajante'!H11:H12) -> 2400 | K30: 0 | L30: 0 | M30: =SUM('Masaje relajante'!H13:H14) -> 3250 | N30: =SUM(B30:M30) -> 10030 | O30: =+'Masaje relajante'!H15 -> 10030 | P30: =+O30-N30 -> 0
A31: Oligoelementos | B31: 0 | C31: 0 | D31: 0 | E31: 0 | F31: 0 | G31: 0 | H31: 0 | I31: 0 | J31: 0 | K31: 0 | L31: 0 | M31: 0 | N31: =SUM(B31:M31) -> 0 | O31: =+Oligoelementos!H4 -> 0 | P31: =+O31-N31 -> 0
A32: Grow | B32: =SUM(Grow!H3:H8) -> 20202.09 | C32: =SUM(Grow!H9:H14) -> 20002.09 | D32: =SUM(Grow!H15:H19) -> 19552.09 | E32: =SUM(Grow!H20:H24) -> 19552.09 | F32: =SUM(Grow!H25:H30) -> 19752.09 | G32: =SUM(Grow!H31:H35) -> 19552.09 | H32: =SUM(Grow!H36:H40) -> 13732.09 | I32: =SUM(Grow!H41:H44) -> 8662.09 | J32: =SUM(Grow!H45:H47) -> 7572.59 | K32: 0 | L32: =SUM(Grow!H48:H53) -> 15824.18 | M32: =SUM(Grow!H54:H57) -> 9662.09 | N32: =SUM(B32:M32) -> 174065.58 | O32: =+Grow!H58 -> 174065.58 | P32: =+O32-N32 -> 0
A33: Abonos | B33: 0 | C33: 0 | D33: =SUM('Abonos a tratamientos'!H3) -> 95 | E33: 0 | F33: 0 | G33: 0 | H33: 0 | I33: 0 | J33: 0 | K33: 0 | L33: 0 | M33: 0 | N33: =SUM(B33:M33) -> 95 | O33: =+'Abonos a tratamientos'!H4 -> 95 | P33: =+O33-N33 -> 0
A34: Celulas madre | B34: =SUM('Celulas madre'!H3:H4) -> 50600 | C34: 0 | D34: =SUM('Celulas madre'!H5) -> 22750 | E34: =SUM('Celulas madre'!H6) -> 24250 | F34: 0 | G34: 0 | H34: =SUM('Celulas madre'!H7:H8) -> 45400 | I34: =SUM('Celulas madre'!H9) -> 19150 | J34: 0 | K34: =SUM('Celulas madre'!H10:H11) -> 52350 | L34: 0 | M34: 0 | N34: =SUM(B34:M34) -> 214500 | O34: =+'Celulas madre'!H12 -> 214500 | P34: =+O34-N34 -> 0
A35: Lipo-recover | B35: 0 | C35: 0 | D35: 0 | E35: 0 | F35: 0 | G35: 0 | H35: 0 | I35: 0 | J35: 0 | K35: 0 | L35: 0 | M35: 0 | N35: =SUM(B35:M35) -> 0 | O35: =+'Lipo-recover'!H4 -> 0 | P35: =+O35-N35 -> 0
A36: Peeling | B36: 0 | C36: 0 | D36: 0 | E36: 0 | F36: 0 | G36: 0 | H36: 0 | I36: 0 | J36: 0 | K36: 0 | L36: 0 | M36: 0 | N36: =SUM(B36:M36) -> 0 | O36: =+Peeling!H4 -> 0 | P36: =+O36-N36 -> 0
A37: Spectra ginecologico | B37: =SUM('Spectra ginecologico'!H3:H6) -> 10000 | C37: =SUM('Spectra ginecologico'!H7:H11) -> 15810 | D37: 0 | E37: =SUM('Spectra ginecologico'!H12:H14) -> 13999.998 | F37: 0 | G37: =SUM('Spectra ginecologico'!H15:H20) -> 19105 | H37: =SUM('Spectra ginecologico'!H21) -> 6000 | I37: =SUM('Spectra ginecologico'!H22:H23) -> 2905 | J37: =SUM('Spectra ginecologico'!H24:H25) -> 4300 | K37: =SUM('Spectra ginecologico'!H26) -> 6000 | L37: =SUM('Spectra ginecologico'!H27:H31) -> 17610 | M37: 0 | N37: =SUM(B37:M37) -> 95729.998 | O37: =+'Spectra ginecologico'!H32 -> 95729.998 | P37: =+O37-N37 -> 0
A38: Vanquish | B38: 0 | C38: 0 | D38: 0 | E38: 0 | F38: 0 | G38: 0 | H38: 0 | I38: 0 | J38: 0 | K38: 0 | L38: 0 | M38: 0 | N38: =SUM(B38:M38) -> 0 | O38: =+Vanquish!H4 -> 0 | P38: =+O38-N38 -> 0
A39: Elimación de lunares | B39: 0 | C39: 0 | D39: 0 | E39: 0 | F39: 0 | G39: 0 | H39: 0 | I39: 0 | J39: 0 | K39: 0 | L39: 0 | M39: 0 | N39: =SUM(B39:M39) -> 0 | O39: =+'Eliminación de lunares'!H4:H4 -> 0 | P39: =+O39-N39 -> 0
A40: Botox | B40: 0 | C40: 0 | D40: =SUM(Botox!H3:H118) -> 242478.49 | E40: 0 | F40: 0 | G40: 0 | H40: =SUM(Botox!H119:H248) -> 285873.49 | I40: 0 | J40: 0 | K40: 0 | L40: =SUM(Botox!H249:H354) -> 236280.2 | M40: =SUM(Botox!H355:H358) -> 9240 | N40: =SUM(B40:M40) -> 773872.18 | O40: =+Botox!H359 -> 773872.18 | P40: =+O40-N40 -> 0
A41: Xwave | C41: 0 | D41: 0 | E41: 0 | F41: 0 | G41: 0 | H41: 0 | I41: 0 | J41: 0 | K41: 0 | L41: 0 | M41: 0 | N41: =SUM(B41:M41) -> 0 | O41: =+Xwave!H4 -> 0 | P41: =+O41-N41 -> 0
A42: Encimas | B42: 0 | C42: 0 | D42: 0 | E42: 0 | F42: 0 | G42: 0 | H42: 0 | I42: 0 | J42: 0 | K42: 0 | L42: 0 | M42: 0 | N42: =SUM(B42:M42) -> 0 | O42: =+Encimas!H4 -> 0 | P42: =+O42-N42 -> 0
A43: Cambio de tratamiento | B43: 0 | C43: =SUM('Cambio de tratamiento'!H3) -> 313.6 | D43: =SUM('Cambio de tratamiento'!H4) -> 200 | E43: 0 | F43: 0 | G43: =SUM('Cambio de tratamiento'!H5) -> 215 | H43: =SUM('Cambio de tratamiento'!H6) -> 3354.58 | I43: =SUM('Cambio de tratamiento'!H7) -> 245 | J43: 0 | K43: 0 | L43: 0 | M43: 0 | N43: =SUM(B43:M43) -> 4328.18 | O43: =+'Cambio de tratamiento'!H8 -> 4328.18 | P43: =+O43-N43 -> 0
A44: Microdermoabrasión | B44: 0 | C44: 0 | D44: =SUM(Microdermoabrasión!H3) -> 600 | E44: 0 | F44: 0 | G44: =SUM(Microdermoabrasión!H4) -> 600 | H44: 0 | I44: 0 | J44: 0 | K44: 0 | L44: 0 | M44: 0 | N44: =SUM(B44:M44) -> 1200 | O44: =+Microdermoabrasión!H5 -> 1200 | P44: =+O44-N44 -> 0
A45: Terapia Luminica | B45: 0 | C45: 0 | D45: 0 | F45: 0 | G45: 0 | H45: 0 | I45: 0 | J45: 0 | K45: 0 | L45: 0 | M45: 0 | N45: =SUM(B45:M45) -> 0 | O45: =+'Terapia Luminica'!H4 -> 0 | P45: =+O45-N45 -> 0
A46: Oscilacion | B46: =SUM(Oscilación!H3:H14) -> 41500 | C46: =SUM(Oscilación!H15:H20) -> 25000 | D46: =SUM(Oscilación!H21:H28) -> 30500 | E46: =SUM(Oscilación!H29:H35) -> 17750 | F46: =SUM(Oscilación!H36:H38) -> 8000 | G46: =SUM(Oscilación!H39:H46) -> 23250 | H46: =SUM(Oscilación!H47:H54) -> 27000 | I46: =SUM(Oscilación!H55:H61) -> 25360 | J46: =SUM(Oscilación!H62:H70) -> 23000 | K46: =SUM(Oscilación!H71:H76) -> 23500 | L46: =SUM(Oscilación!H77:H79) -> 6500 | M46: =SUM(Oscilación!H80:H85) -> 11500 | N46: =SUM(B46:M46) -> 262860 | O46: =+Oscilación!H86 -> 262860 | P46: =+O46-N46 -> 0
A47: Sueros | B47: =SUM(Sueros!H3:H7) -> 3750 | C47: =SUM(Sueros!H8:H13) -> 4500 | D47: =SUM(Sueros!H14:H18) -> 4500 | E47: =SUM(Sueros!H19:H22) -> 3000 | F47: =SUM(Sueros!H23:H32) -> 7500 | G47: =SUM(Sueros!H33:H40) -> 6123.6 | H47: =SUM(Sueros!H41:H43) -> 2250 | I47: =SUM(Sueros!H44:H46) -> 2200 | J47: =SUM(Sueros!H47:H56) -> 10715 | K47: =SUM(Sueros!H57:H61) -> 5250 | L47: =SUM(Sueros!H62:H68) -> 5250 | M47: =SUM(Sueros!H69) -> 2100 | N47: =SUM(B47:M47) -> 57138.6 | O47: =+Sueros!H70 -> 57138.6 | P47: =+O47-N47 -> 0
A48: Presoterapia | B48: =SUM(Presoterapia!H3:H4) -> 4000 | C48: 0 | D48: =SUM(Presoterapia!H5) -> 2300 | E48: 0 | F48: 0 | G48: 0 | H48: 0 | I48: 0 | J48: 0 | K48: 0 | L48: 0 | M48: 0 | N48: =SUM(B48:M48) -> 6300 | O48: =+Presoterapia!H6 -> 6300 | P48: =+N48-O48 -> 0
A49: Nioo | B49: 0 | C49: =SUM(Nioo!H3) -> 4000 | D49: =SUM(Nioo!H4:H9) -> 18400 | E49: =SUM(Nioo!H10) -> 3000 | F49: =SUM(Nioo!H11:H15) -> 10640 | G49: =SUM(Nioo!H16:H24) -> 38000 | H49: =SUM(Nioo!H25:H26) -> 7000 | I49: =SUM(Nioo!H27:H28) -> 2500 | J49: =SUM(Nioo!H29:H32) -> 14280 | K49: =SUM(Nioo!H33:H34) -> 8000 | L49: =SUM(Nioo!H35:H37) -> 5200 | M49: =SUM(Nioo!H38:H39) -> 5500 | N49: =SUM(B49:M49) -> 116520 | O49: =+Nioo!H40 -> 116520 | P49: =+N49-O49 -> 0
A50: Sedación | B50: 0 | C50: 0 | D50: 0 | E50: 0 | F50: 0 | G50: 0 | H50: =SUM(Sedación!H3) -> 350 | N50: =SUM(B50:M50) -> 350 | O50: =+Sedación!H4 -> 350 | P50: =+N50-O50 -> 0
N51: =SUM(B51:M51) -> 0 | O51: =+Microdermoabrasión!H6 -> 0 | P51: =+O51-N51 -> 0
A52: Total | B52: =SUM(B2:B51) -> 393402.19 | C52: =SUM(C2:C51) -> 272855.02 | D52: =SUM(D2:D51) -> 714309.38 | E52: =SUM(E2:E51) -> 332704.59 | F52: =SUM(F2:F51) -> 418683.34 | G52: =SUM(G2:G51) -> 380539.43 | H52: =SUM(H2:H51) -> 658997.76 | I52: =SUM(I2:I51) -> 348884.2 | ... N52: =SUM(N2:N51) -> 5062740 | P52: =+O52-N52 -> -5062740
B53: =+'[1]enero 23'!$B$170 -> 393402.19 | C53: =+'[1]febrero 23'!$B$156 -> 272855.02 | D53: =+'[2]marzo 23'!$B$270 -> 714309.39 | E53: =+'[2]abril 23'!$B$115 -> 332704.59 | F53: =+'[2]mayo 23'!$B$162 -> 418683.34 | G53: =+'[2]junio 23'!$B$168 -> 380539.43 | H53: =+'[2]julio 23'!$B$262 -> 658997.77 | I53: =+'[2]agosto 23'!$B$142 -> 348884.4 | J53: =+'[2]septiembre 23'!$B$161 -> 355826.05 | K53: =+'[2]octubre 23'!$B$117 -> 280818.25 | L53: =+'[2]noviembre 23'!$B$250 -> 619795.53 | M53: =+'[2]diciembre 23'!$B$129 -> 285924.09
B54: =+B52-B53 -> -0.0003999999 | C54: =+C52-C53 -> -0.00020000001 | D54: =+D52-D53 -> -0.00815 | E54: =+E52-E53 -> -0.0019999999 | F54: =+F52-F53 -> 0 | G54: =+G52-G53 -> -0.00019999995 | H54: =+H52-H53 -> -0.0075940001 | I54: =+I52-I53 -> -0.2 | ... M54: =+M52-M53 -> -0.0001

Sheet Producto
A1: Producto | B1: Fecha | C1: No. de Factura | D1: Cantidad | E1: Nombre del Paciente | F1: Tratamiento | G1: Forma de Pago | H1: Total
B3: 44936 | C3: 2717010146 | D3: 1 | E3: Patricia Sandoval | F3: Complete collagen (protocol) | G3: Efectivo | H3: 850
B4: 44937 | C4: 1511474418 | D4: 1 | E4: Mimi de Quan | F4: Frasco de protocol colageno con acido hialuronico | G4: Credomatic | H4: 550
B5: 44938 | C5: 2010334081 | D5: 1 | E5: Karla Pinto Portillo | F5: Suero regenerativo (SKINGENUITY) | G5: Efectivo $ | H5: 1010
B6: 44938 | C6: 2010334081 | D6: 1 | E6: Karla Pinto Portillo | F6: Suero reparado (SKINGENUITY) | G6: Efectivo $ | H6: 1294
B7: 44938 | C7: 174280333 | D7: 1 | E7: Norma de Barquin | F7: Protector solar spray (HELIOCARE) | G7: Efectivo | H7: 380
B8: 44938 | C8: 174280333 | D8: 1 | E8: Norma de Barquin | F8: Protector solar compacto (HELIOCARE) | G8: Efectivo | H8: 450
B9: 44943 | C9: 521751306 | D9: 1 | E9: Sara Mayorga | F9: RHA Serum | G9: Visa L. | H9: 1280
B10: 44943 | C10: recibo | D10: 1 | E10: Massiel Hernandez | F10: Protector solar spray (HELIOCARE) | G10: Efectivo | H10: 150
B11: 44943 | C11: recibo | D11: 1 | E11: Massiel Hernandez | F11: Protector solar gel (HELIOCARE) | G11: Efectivo | H11: 80
B12: 44944 | C12: 3839773296 | D12: 1 | E12: Vanessa Smith de Vargas | F12: Protector solar compacto (HELIOCARE) | G12: Credomatic | H12: 450
B13: 44951 | C13: 1237468518 | D13: 1 | E13: Zuleima Cruz Salguero | F13: RHA Serum | G13: Visa | H13: 1280
B14: 44952 | C14: 4032643175 | D14: 1 | E14: Cristina Sanchez | F14: Serun AOX C&E | G14: Visa | H14: 850
B15: 44952 | C15: recibo | D15: 2 | E15: Dra Julia Monroy | F15: Protector solar gel (HELIOCARE) | G15: Efectivo | H15: 160
B16: 44953 | C16: 2905163280 | D16: 3 | E16: Wanda Serovic | F16: Frasco de protocol colageno con acido hialuronico | G16: Credomatic | H16: 1650
B17: 44953 | C17: 2905163280 | D17: 1 | E17: Wanda Serovic | F17: Proto-col collagen Shot | G17: Credomatic | H17: 650
B18: 44953 | C18: 1582714813 | D18: 1 | E18: Wanda Serovic | F18: Protector solar spray (HELIOCARE) | G18: Credomatic | H18: 380
B19: 44956 | C19: 3581166546 | D19: 1 | E19: Silvia Patricia Oxon | F19: Protector solar gel (HELIOCARE) | G19: Credomatic | H19: 350
B20: 44960 | C20: 2773371547 | D20: 1 | E20: Alma Gricel Tobar | F20: Frasco de protocol colageno con acido hialuronico | G20: Visa | H20: 550
B21: 44960 | C21: 2773371547 | D21: 1 | E21: Alma Gricel Tobar | F21: Serum AOX C&E | G21: Visa | H21: 850
B22: 44964 | C22: 907168346 | D22: 1 | E22: Mimi de Quan | F22: Frasco de protocol colageno con acido hialuronico | G22: Credomatic | H22: 550
B23: 44964 | C23: 2333755906 | D23: 1 | E23: Mimi de Quan | F23: Serum AOX C&E | G23: Credomatic | H23: 850
B24: 44964 | C24: recibo | D24: 1 | E24: Johana Barillas | F24: Protector solar spray (HELIOCARE) | G24: Efectivo | H24: 149
B25: 44964 | C25: recibo | D25: 1 | E25: Massiel Hernandez | F25: complete collagen (protocol) | G25: Efectivo | H25: 289
B26: 44965 | C26: 2990883213 | D26: 1 | E26: Miguel Angel Martinez Solis | F26: Jabon biretix | G26: Efectivo | H26: 450
B27: 44965 | C27: 2990883213 | D27: 1 | E27: Miguel Angel Martinez Solis | F27: Abono a protector solar gel (HELIOCARE) | G27: Efectivo | H27: 140
B28: 44965 | C28: 2990883213 | D28: 1 | E28: Miguel Angel Martinez Solis | F28: Cancelación a protector solar gel (HELIOCARE) | G28: Visa | H28: 210
B29: 44965 | C29: 2990883213 | D29: 1 | E29: Miguel Angel Martinez Solis | F29: Tensage Cram (Endocare) | G29: Visa | H29: 630
B30: 44965 | C30: 1778601715 | D30: 1 | E30: Claudia Valenzuela | F30: Suero regenerativo (SKINGENUITY) | G30: Visa L. | H30: 1010
B31: 44965 | C31: 1778601715 | D31: 1 | E31: Claudia Valenzuela | F31: Suero reparador (SKINGENUITY) | G31: Visa L. | H31: 1294
B32: 44965 | C32: 1778601715 | D32: 1 | E32: Claudia Valenzuela | F32: Tensage Cram (Endocare) | G32: Visa L. | H32: 630
B33: 44965 | C33: 3225373309 | D33: 1 | E33: Diana Linares | F33: Xxtralash | G33: Credomatic | H33: 850
B34: 44967 | C34: 4090774266 | D34: 1 | E34: Anggie Gelvets | F34: Faja post-quirurgica IC 3001 | G34: Efectivo | H34: 1000
B35: 44970 | C35: 133842754 | D35: 1 | E35: Alex Weller | F35: Tensage Cram (Endocare) | G35: Visa | H35: 630
B36: 44971 | C36: 669467521 | D36: 1 | E36: Miguel Angel Martinez Solis | F36: Frasco de protocol colageno con acido hialuronico | G36: Efectivo | H36: 550
B37: 44973 | C37: recibo | D37: 1 | E37: Anderson Tay | F37: Jabon facial sinaklein (Venustras) | G37: Efectivo | H37: 38
B38: 44974 | C38: 1808812747 | D38: 1 | E38: Ileana de Carrera | F38: Protector solar compacto (HELIOCARE) | G38: Credomatic | H38: 450
B39: 44974 | C39: 1808812747 | D39: 1 | E39: Ileana de Carrera | F39: Frasco de capsulas heliocare Ultra-D | G39: Credomatic | H39: 450
B40: 44977 | C40: 3658958771 | D40: 1 | E40: Mirna Sarceño | F40: Protector solar gel (heliocare) | G40: Visa | H40: 350
B41: 44977 | C41: 64045497 | D41: 1 | E41: Abel Escartin | F41: Faja post-quirurgica para hombre codio 10596CAM (factura con exención de IVA) | G41: Visa | H41: 900
B42: 44977 | C42: 64045497 | D42: 1 | E42: Lissa Maldonado Arias | F42: Faja post-quirurgica codigo IC-3000 (factura con exención de IVA) | G42: Visa | H42: 750
B43: 44978 | C43: 2076197314 | D43: 1 | E43: Christina Los | F43: Complete collagen (protocol) | G43: Credomatic | H43: 850
B44: 44978 | C44: 130769485 | D44: 1 | E44: Ingrid Rivera | F44: Xxtralash | G44: Visa | H44: 850
B45: 44987 | C45: 3427617206 | D45: 1 | E45: Alma Tobar | F45: Jabon para acne (VENUSTAS) | G45: Credomatic | H45: 300
B46: 44987 | C46: 3427617206 | D46: 1 | E46: Alma Tobar | F46: Crema venustas | G46: Credomatic | H46: 250
B47: 44987 | C47: 3427617206 | D47: 1 | E47: Alma Tobar | F47: Tensage cream (Endocare) | G47: Credomatic | H47: 630
B48: 44988 | C48: 1105806114 | D48: 1 | E48: Ileana De Carrera | F48: Crema contorno de ojos (BIOTOPIX) | G48: Credomatic | H48: 450
B49: 44988 | C49: 3842982853 | D49: 1 | E49: Hadazah Orozco | F49: Jabon para acne (VENUSTAS) | G49: Credomatic | H49: 300
B50: 44992 | C50: 2070366694 | D50: 1 | E50: Andrea Archila | F50: Serum AOX C&E | G50: Visa L. | H50: 850
B51: 44992 | C51: recibo | D51: 1 | E51: Gloria Constancia | F51: Jabon facial belviso | G51: Efectivo | H51: 55.25
B52: 44992 | C52: recibo | D52: 1 | E52: Gloria Constancia | F52: Jabon facial sinaklien | G52: Efectivo | H52: 74.8
B53: 44992 | C53: recibo | D53: 1 | E53: Gloria Constancia | F53: Dapzon rice | G53: Efectivo | H53: 76.5
B54: 44994 | C54: 3849277388 | D54: 1 | E54: Eunice Herrera Escobar | F54: Frasco de protocol colageno con acido hialuronico | G54: Visa | H54: 550
B55: 44998 | C55: 2590327999 | D55: 1 | E55: Telma Maldonado | F55: Complete collagen (protocol) | G55: Credomatic | H55: 850
B56: 44998 | C56: 2590327999 | D56: 1 | E56: Telma Maldonado | F56: Protector solar spray (HELIOCARE) | G56: Credomatic | H56: 380
B57: 44998 | C57: 2590327999 | D57: 1 | E57: Telma Maldonado | F57: Crema venustas | G57: Credomatic | H57: 250
B58: 45006 | C58: 2565161821 | D58: 1 | E58: Beatriz Tambasco | F58: Jabon para piel seca y sensible (VENUSTAS) | G58: Visa | H58: 250
B59: 45007 | C59: 105006485 | D59: 1 | E59: Marcela Barquin | F59: Abono a complete collagen (protocol) | G59: Credomatic | H59: 750
B60: 45007 | C60: 105006485 | D60: 1 | E60: Marcela Barquin | F60: Cancelación a complete collagen (protocol) | G60: Efectivo | H60: 100
B61: 45007 | C61: 105006485 | D61: 1 | E61: Marcela Barquin | F61: Proto-col collagen shot | G61: Efectivo | H61: 650
B62: 45007 | C62: 105006485 | D62: 1 | E62: Marcela Barquin | F62: Crema venustas | G62: Efectivo | H62: 250
B63: 45007 | C63: 2474984209 | D63: 1 | E63: Heidi Mariela Garcia | F63: Frasco de protocol colageno con acido hialuronico | G63: Efectivo | H63: 550
B64: 45008 | C64: 2716027603 | D64: 1 | E64: Maria Jose Ortiz | F64: Proto-col collagen shot | G64: Visa | H64: 650
B65: 45008 | C65: 2716027603 | D65: 1 | E65: Maria Jose Ortiz | F65: Frasco de protocol colageno con acido hialuronico | G65: Visa | H65: 550
... B231: 45275 | C231: 1031294821 | D231: 1 | E231: Sonia Oviedo | F231: 3D Lip (Teoxane) | G231: Efectivo | H231: 580
E232: Total | H232: =SUM(H3:H231) -> 152315.01

Sheet Acido hialuronico
A1: Acido hialuronico | B1: Fecha | C1: No. de Factura | D1: Cantidad | E1: Nombre del Paciente | F1: Tratamiento | G1: Forma de Pago | H1: Total
B3: 45076 | C3: 2420588771 | D3: 1 | E3: Mayra Mazariegos de Mendez | F3: Aplicación acido hialuronico en labios | G3: Deposito | H3: 2700
B4: 45146 | C4: 539969771 | D4: 1 | E4: Virginia Castillo | F4: Aplicación de acido hiluronico | G4: Visa | H4: 2800
B5: 45146 | C5: 539969771 | D5: 1 | E5: Virginia Castillo | F5: Aplicación de acido hiluronico | G5: Visa | H5: 3500
B6: 45223 | C6: 3094757961 | D6: 1 | E6: Mariana Orellana | F6: Aplicación acido hialuronico | G6: Deposito | H6: 2800
B7: 45244 | C7: 953174132 | D7: 1 | E7: Marilyn Barascout | F7: Aplicación acido hialuronico | G7: Credomatic | H7: 2000
B8: 45250 | C8: 882855121 | D8: 1 | E8: Ana Elizabeth Molina | F8: Aplicación acido hialuronico labios | G8: Deposito | H8: 2000
B9: 45250 | C9: 2203995018 | D9: 1 | E9: Mabby Morales | F9: Aplicación acido hialuronico nariz | G9: Visa | H9: 2800
B10: 45251 | C10: 1582253869 | D10: 1 | E10: Gabriela Valverde | F10: Aplicación acido hialuronico labios | G10: Visa | H10: 2000
B11: 45251 | C11: 3206301846 | D11: 1 | E11: Ana Marina Martinez | F11: Aplicación acido hialuronico | G11: Cheque | H11: 1000
B12: 45251 | C12: 1824017879 | D12: 1 | E12: Ana Marina Martinez | F12: Aplicación acido hialuronico | G12: Cheque | H12: 1000
B13: 45252 | C13: 3799663895 | D13: 1 | E13: Gabriela Toledo Torres | F13: Aplicación acido hialuronico labios | G13: Credomatic | H13: 2000
B14: 45252 | C14: 3799663895 | D14: 1 | E14: Gabriela Toledo Torres | F14: Aplicación acido hialuronico nariz | G14: Credomatic | H14: 2700
... B25: 45280 | C25: 2469150969 | D25: 1 | E25: Carla Sena | F25: Aplicación acido hialuronico nariz | G25: Credomatic | H25: 3000
E26: Total | H26: =SUM(H3:H25) -> 59600

Sheet Depilación
A1: Depilación | B1: Fecha | C1: No. de Factura | D1: Cantidad | E1: Nombre del Paciente | F1: Tratamiento | G1: Forma de Pago | H1: Total
B3: 44930 | C3: 2650292592 | D3: 4 | E3: Keren Noriega | F3: Depilación rostro completo | G3: Visa L. | H3: 925
B4: 44935 | C4: 2105886131 | D4: 4 | E4: Gabriela Alfaro | F4: Depilación axila | G4: Credomatic | H4: 700
B5: 44935 | C5: 2105886131 | D5: 4 | E5: Gabriela Alfaro | F5: Depilación bigote | G5: Credomatic | H5: 500
B6: 44938 | C6: 2590655824 | D6: 4 | E6: Lissete Sanchez | F6: Depilación axila | G6: Visa | H6: 700
B7: 44938 | C7: 2590655824 | D7: 4 | E7: Lissete Sanchez | F7: Depilación bikini | G7: Visa | H7: 925
B8: 44939 | C8: 322626027 | D8: 4 | E8: Claudia Arrecis | F8: Depilación bikini | G8: Efectivo | H8: 925
B9: 44939 | C9: 322626027 | D9: 4 | E9: Claudia Arrecis | F9: Depilación axila | G9: Efectivo | H9: 700
B10: 44943 | C10: recibo | D10: 1 | E10: Marleni Castillo | F10: Depilación bikini | G10: Efectivo | H10: 50
B11: 44944 | C11: 1712474995 | D11: 1 | E11: Nicte Cifuentes | F11: Depilación bikini | G11: Credomatic | H11: 231.25
B12: 44944 | C12: 2637121956 | D12: 1 | E12: Mishel de Reitzel | F12: Depilación axila | G12: Credomatic | H12: 175
B13: 44946 | C13: recibo | D13: 1 | E13: Melany Perez | F13: Depilación bikini | G13: Efectivo | H13: 50
B14: 44946 | C14: recibo | D14: 1 | E14: Melany Perez | F14: Depilación bigote | G14: Efectivo | H14: 50
B15: 44946 | C15: recibo | D15: 1 | E15: Melany Perez | F15: Depilación axila | G15: Efectivo | H15: 50
B16: 44951 | C16: 2698856826 | D16: 1 | E16: Mishel de Reitzel | F16: Depilación bikini | G16: Credomatic | H16: 231.25
B17: 44960 | C17: 2463973448 | D17: 4 | E17: Claudia Castillo | F17: Depilación rostro completo | G17: Credomatic | H17: 1200
B18: 44965 | C18: 1255358974 | D18: 4 | E18: Claudia Campos | F18: Depilación rostro completo | G18: Visa L. | H18: 925
B19: 44977 | C19: 32523008433 | D19: 4 | E19: Evelyn Cerna | F19: Depilación bikini | G19: Visa | H19: 925
B20: 44977 | C20: 32523008433 | D20: 4 | E20: Evelyn Cerna | F20: Depilación axila | G20: Visa | H20: 700
B21: 44985 | C21: recibo | D21: 1 | E21: Marleni Castillo | F21: Depilación bikini | G21: Efectivo | H21: 50
B22: 44985 | C22: recibo | D22: 1 | E22: Melany Perez | F22: Depilación bikini | G22: Efectivo | H22: 50
B23: 44985 | C23: recibo | D23: 1 | E23: Melany Perez | F23: Depilación axila | G23: Efectivo | H23: 50
B24: 44985 | C24: recibo | D24: 1 | E24: Melany Perez | F24: Depilación bigote | G24: Efectivo | H24: 50
B25: 44986 | C25: 676678220 | D25: 1 | E25: Mishel De Reitzel | F25: Depilación axila | G25: Visa | H25: 175
B26: 44986 | C26: 483411296 | D26: 2 | E26: Carla De Zelaya | F26: Depilación medias piernas | G26: Credomatic | H26: 900
B27: 44992 | C27: 935936691 | D27: 4 | E27: Anhara Silvia Chacon De Sandoval | F27: Depilación bigote, menton, antebrazo, abdomen y dedos de manos y pies | G27: Visa L. | H27: 960
B28: 44993 | C28: 3919724872 | D28: 1 | E28: Mishel De Reitzel | F28: Depilación bikini | G28: Credomatic | H28: 231.25
B29: 45000 | C29: 2113880679 | D29: 2 | E29: Norma De Barquin | F29: Depilación barbilla | G29: Credomatic | H29: 760
B30: 45007 | C30: 226118147 | D30: 4 | E30: Danury Samayoa | F30: Depilación rostro completo | G30: Visa | H30: 900
B31: 45008 | C31: 670256428 | D31: 1 | E31: Marilu Pierri | F31: Depilación bikini | G31: Credomatic | H31: 264.5
B32: 45008 | C32: 670256428 | D32: 1 | E32: Marilu Pierri | F32: Depilación axila | G32: Credomatic | H32: 264.5
B33: 45013 | C33: 806895864 | D33: 4 | E33: Bianca Conte | F33: Depilación rostro completo | G33: Visa | H33: 1000
B34: 45016 | C34: recibo | D34: 1 | E34: Melany Perez | F34: Depilación axila | G34: Efectivo | H34: 50
B35: 45016 | C35: recibo | D35: 1 | E35: Melany Perez | F35: Depilación bigote | G35: Efectivo | H35: 50
B36: 45016 | C36: recibo | D36: 1 | E36: Melany Perez | F36: Depilación bikini | G36: Efectivo | H36: 50
B37: 45033 | C37: 822560300 | D37: 4 | E37: Johana Tamyo | F37: Depilación dedos de pies | G37: Credomatic | H37: 700
B38: 45033 | C38: 822560300 | D38: 2 | E38: Johana Tamyo | F38: Depilación bikini | G38: Credomatic | H38: 462.5
B39: 45042 | C39: 1737247359 | D39: 4 | E39: Evelyn Cerna | F39: Depilación piernas | G39: Credomatic | H39: 1250
B40: 45048 | C40: 319441993 | D40: 2 | E40: Claudia Leon De Castillo | F40: Depilació bikini | G40: Visa L. | H40: 432
B41: 45048 | C41: 319441993 | D41: 1 | E41: Claudia Leon De Castillo | F41: Depilació bikini | G41: Visa L. | H41: 218
B42: 45049 | C42: 3489680614 | D42: 1 | E42: Mishel De Reitzel | F42: Depilació bikini | G42: Credomatic | H42: 231.25
B43: 45049 | C43: 3489680614 | D43: 1 | E43: Mishel De Reitzel | F43: Depilación axila | G43: Credomatic | H43: 175
B44: 45051 | C44: recibo | D44: 1 | E44: Melany Perez | F44: Depilación bikini | G44: Efectivo | H44: 50
B45: 45051 | C45: recibo | D45: 1 | E45: Melany Perez | F45: Depilación bigote | G45: Efectivo | H45: 50
B46: 45051 | C46: recibo | D46: 1 | E46: Melany Perez | F46: Depilación axila | G46: Efectivo | H46: 50
B47: 45054 | C47: 1747340940 | D47: 4 | E47: Lissete Sanchez | F47: Depilación brazos | G47: Visa | H47: 925
B48: 45057 | C48: 383402356 | D48: 1 | E48: Maria Isabel Castillo | F48: Depilación rostro completo | G48: Visa L. | H48: 180
B49: 45078 | C49: 57298259 | D49: 4 | E49: Ana Luz Morales | F49: Depilación bikini | G49: Visa | H49: 925
B50: 45079 | C50: 3773713778 | D50: 1 | E50: Marilu Pierri | F50: Depilación bikini | G50: Credomatic | H50: 264.5
B51: 45079 | C51: 3773713778 | D51: 1 | E51: Marilu Pierri | F51: Depilación axila | G51: Credomatic | H51: 264.5
B52: 45079 | C52: recibo | D52: 1 | E52: Melany Perez | F52: Depilación axila | G52: Efectivo | H52: 50
B53: 45079 | C53: recibo | D53: 1 | E53: Melany Perez | F53: Depilación bigote | G53: Efectivo | H53: 50
B54: 45079 | C54: recibo | D54: 1 | E54: Melany Perez | F54: Depilación bikini | G54: Efectivo | H54: 50
B55: 45091 | C55: 986728906 | D55: 1 | E55: Mishel De Reitzel | F55: Depilación bikini | G55: Credomatic | H55: 231.25
B56: 45091 | C56: 986728906 | D56: 1 | E56: Mishel De Reitzel | F56: Depilación axila | G56: Credomatic | H56: 175
B57: 45091 | C57: 3030207969 | D57: 2 | E57: Mariana Marquez | F57: Depilación piernas | G57: Visa | H57: 625
B58: 45091 | C58: 3030207969 | D58: 2 | E58: Mariana Marquez | F58: Depilación bikini | G58: Visa | H58: 462.5
B59: 45091 | C59: 3030207969 | D59: 2 | E59: Mariana Marquez | F59: Depilación brazos | G59: Visa | H59: 550
B60: 45092 | C60: 1484473755 | D60: 3 | E60: Nidia Och | F60: Depilación bikini | G60: Visa L. | H60: 693.75
B61: 45093 | C61: 1940147782 | D61: 4 | E61: Fabiola Azurdia | F61: Depilación axila | G61: Visa L. | H61: 700
B62: 45093 | C62: 1940147782 | D62: 7 | E62: Fabiola Azurdia | F62: Depilación piernas | G62: Visa L. | H62: 1638
B63: 45093 | C63: 1940147782 | D63: 1 | E63: Fabiola Azurdia | F63: Depilación piernas | G63: Visa L. | H63: 237
B64: 45105 | C64: 1554073056 | D64: 2 | E64: Carla De Zelaya | F64: Depilación axila | G64: Credomatic | H64: 350
B65: 45106 | C65: 967591809 | D65: 4 | E65: Ximena Echeverria | F65: Depilación medio rostro | G65: Visa | H65: 850
B66: 45111 | C66: 134762245 | D66: 3 | E66: Maria Jose Solares | F66: Depilación bikini | G66: Visa L. | H66: 693.75
B67: 45114 | C67: recibo | D67: 1 | E67: Melany Perez | F67: Depilación bikini | G67: Efectivo | H67: 50
B68: 45114 | C68: recibo | D68: 1 | E68: Melany Perez | F68: Depilación axila | G68: Efectivo | H68: 50
B69: 45114 | C69: recibo | D69: 1 | E69: Melany Perez | F69: Depilación bigote | G69: Efectivo | H69: 50
B70: 45117 | C70: 2305114772 | D70: 4 | E70: Allan Diaz | F70: Depilación medio rostro | G70: Visa | H70: 850
B71: 45117 | C71: 2305114772 | D71: 4 | E71: Rotceh Garcia | F71: Depilación medias piernas | G71: Visa | H71: 1000
B72: 45119 | C72: 3642902293 | D72: 4 | E72: Valeria Florido | F72: Depilación piernas | G72: Credomatic | H72: 1250
B73: 45119 | C73: 3642902293 | D73: 4 | E73: Valeria Florido | F73: Depilación bikini | G73: Credomatic | H73: 925
B74: 45119 | C74: 3642902293 | D74: 4 | E74: Valeria Florido | F74: Depilación glúteos | G74: Credomatic | H74: 700
B75: 45126 | C75: 3241168669 | D75: 4 | E75: Karla Bocaletti De Enriquez | F75: Depilación intergluteos | G75: Visa | H75: 550
B76: 45126 | C76: 3241168669 | D76: 4 | E76: Karla Bocaletti De Enriquez | F76: Depilación axila | G76: Visa | H76: 700
B77: 45126 | C77: 3241168669 | D77: 4 | E77: Karla Bocaletti De Enriquez | F77: Depilación medias piernas | G77: Visa | H77: 975
B78: 45128 | C78: 4130555284 | D78: 4 | E78: Ivanna Flores Rivera | F78: Depilación rostro completo | G78: Visa L. | H78: 780
B79: 45128 | C79: 4130555284 | D79: 4 | E79: Ivanna Flores Rivera | F79: Depilación piernas | G79: Visa L. | H79: 1250
B80: 45128 | C80: 4130555284 | D80: 4 | E80: Ivanna Flores Rivera | F80: Depilación axila | G80: Visa L. | H80: 700
B81: 45128 | C81: 4130555284 | D81: 4 | E81: Ivanna Flores Rivera | F81: Depilación brazos | G81: Visa L. | H81: 1000
... B84: 45147 | C84: 4044178983 | D84: 1 | E84: Mishel De Reitzel | F84: Depilación axila | G84: Credomatic | H84: 175
B85: 45156 | C85: recibo | D85: 1 | E85: Melany Perez | F85: Depilación bikini | G85: Efectivo | H85: 50
B86: 45156 | C86: recibo | D86: 1 | E86: Melany Perez | F86: Depilación axila | G86: Efectivo | H86: 50
B87: 45156 | C87: recibo | D87: 1 | E87: Melany Perez | F87: Depilación bigote | G87: Efectivo | H87: 50
B88: 45159 | C88: 1710833804 | D88: 4 | E88: Andrea Archila | F88: Depilación axila | G88: Visa L. | H88: 700
B89: 45159 | C89: 1710833804 | D89: 4 | E89: Andrea Archila | F89: Depilación aureola | G89: Visa L. | H89: 500
B90: 45161 | C90: 763053002 | D90: 1 | E90: Mishel De Reitzel | F90: Depilación bikini | G90: Credomatic | H90: 231.25
B91: 45168 | C91: 3956296714 | D91: 4 | E91: Maria Esperaza Barrutia | F91: Depilación de bigote | G91: Visa | H91: 600
B92: 45169 | C92: 3386526172 | D92: 4 | E92: Ximena Ventura | F92: Depilación espalda | G92: Visa | H92: 950
B93: 45169 | C93: 3386526172 | D93: 4 | E93: Ximena Ventura | F93: Depilación axila | G93: Visa | H93: 700
B98: 45176 | C98: 591152173 | D98: 4 | E98: Lessette Sanchez | F98: Depilación bikini | G98: Visa | H98: 925
B99: 45182 | C99: 3396158071 | D99: 1 | E99: Michelle de Reitzel | F99: Depilacion axila | G99: Credomatic | H99: 175
B100: 45190 | C100: 4263986259 | D100: 2 | E100: Ana Mercedes Flores | F100: Depilación axila | G100: Visa | H100: 350
B101: 45190 | C101: 4263986259 | D101: 2 | E101: Ana Mercedes Flores | F101: Depilación piernas | G101: Visa | H101: 625
B102: 45190 | C102: 4263986259 | D102: 2 | E102: Ana Mercedes Flores | F102: Depilación bikini | G102: Visa | H102: 462.5
B103: 45195 | C103: 2847885920 | D103: 2 | E103: Luisa Fernanda Lemus | F103: Depilación axila | G103: Visa L. | H103: 350
... B136: 45264 | C136: 2337555487 | D136: 4 | E136: Monica De Garcia | F136: Depilación mentón | G136: Visa L. | H136: 800
B137: 45268 | C137: recibo | D137: 1 | E137: Melany Perez | F137: Depilación axila | G137: Efectivo | H137: 50
B138: 45268 | C138: recibo | D138: 1 | E138: Melany Perez | F138: Depilación bikini | G138: Efectivo | H138: 50
B139: 45268 | C139: recibo | D139: 1 | E139: Melany Perez | F139: Depilación bigote | G139: Efectivo | H139: 50
...

Sheet Emsculpt
A1: Emsculpt | B1: Fecha | C1: No. de Factura | D1: Cantidad | E1: Nombre del Paciente | F1: Tratamiento | G1: Forma de Pago | H1: Total
B3: 44931 | C3: 8077385 | D3: 4 | E3: Nicolle Melville | F3: Emsculpt abdomen | G3: Visa | H3: 9000
B4: 44974 | C4: 3501213210 | D4: 3 | E4: Maria Olga De Cohen | F4: Emsculpt abdomen | G4: Visa | H4: 6750
B5: 45001 | C5: 1605652076 | D5: 3 | E5: Maria Jose Ruano | F5: Emsculpt glúteos | G5: Visa L. | H5: 6750
B6: 45042 | C6: 148586966 | D6: 2 | E6: Natalie Recinos Sarceño | F6: Abono a emsculpt abdomen | G6: Credomatic | H6: 5958
B7: 45042 | C7: 148586966 | D7: 1 | E7: Natalie Recinos Sarceño | F7: Cancelación a emsculpt abdomen | G7: Efectivo $ | H7: 792
B8: 45051 | C8: 2861254121 | D8: 3 | E8: Alvaro Francisco Ruata | F8: Emsculpt abdomen | G8: Credomatic | H8: 6750
B9: 45062 | C9: 2313700579 | D9: 3 | E9: Maria Jose Alvarez | F9: Emsculpt gluteos | G9: Visa | H9: 6750
B10: 45148 | C10: 1342522360 | D10: 3 | E10: Jocob Cifuentes Veliz | F10: Emsculpt abdomen | G10: Visa | H10: 6750
B11: 45174 | C11: 3648736166 | D11: 3 | E11: Miguel Martinez | F11: Emsculpt abdomen | G11: Visa | H11: 6750
B12: 45194 | C12: 1860976643 | D12: 3 | E12: Jose Manuel Castellanos | F12: Emsculpt abdomen | G12: Visa L. | H12: 6750
B13: 45194 | C13: 2102086755 | D13: 2 | E13: Sara Bolaños | F13: Abono a tratamiento Emsculpt abdomen | G13: Deposito | H13: 6500
B14: 45194 | C14: 2102086755 | D14: 1 | E14: Sara Bolaños | F14: Cancelación a tratamiento Emsculpt abdomen | G14: Visa L. | H14: 250
... B27: 45279 | C27: 3414117226 | D27: 1 | E27: Maria Jose Alvarez | F27: Emsculpt glúteos | G27: Visa | H27: 1750
E28: Total | H28: =SUM(H3:H27) -> 119250

Sheet Emtone
A1: Emtone | B1: Fecha | C1: No. de Factura | D1: Cantidad | E1: Nombre del Paciente | F1: Tratamiento | G1: Forma de Pago | H1: Total
B3: 44930 | C3: 3021422995 | D3: 5 | E3: Perla Karina Alfaro Ortiz | F3: Emtone chaparrera, entrepierna, banana roll y parte posterior de la pierna | G3: Visa | H3: 4955
B4: 44930 | C4: 3021422995 | D4: 1 | E4: Perla Karina Alfaro Ortiz | F4: Emtone chaparrera, entrepierna, banana roll y parte posterior de la pierna | G4: Visa | H4: 995
B5: 44942 | C5: 363789713 | D5: 4 | E5: Nicte Alfaro | F5: Emtone abdomen, cintura y brazos | G5: Visa | H5: 2250
B6: 44944 | C6: 74597906 | D6: 8 | E6: Myriam Mijanos Ramirez | F6: Emtone medias piernans completas | G6: Visa | H6: 5000
B7: 44953 | C7: 1879916783 | D7: 8 | E7: Norma Pineda | F7: Emtone medias piernas completas | G7: Visa | H7: 5000
B8: 44977 | C8: 414729941 | D8: 8 | E8: Giselle Sanzogni | F8: Emtone medias piernas completas | G8: Credomatic | H8: 5000
B9: 44993 | C9: 3498920069 | D9: 8 | E9: Marta Maria Perez | F9: Emtone chaparrera, entrepiernas y parte posterior de la pierna | G9: Visa | H9: 5000
B10: 44995 | C10: 2773897014 | D10: 8 | E10: Nancy Paola Gudiel | F10: Emtone medias piernas completas | G10: Visa | H10: 5000
B11: 45000 | C11: 1661946787 | D11: 8 | E11: Maria Jose Herrera | F11: Emtone medias piernas y glúteos | G11: Credomatic | H11: 5100
B12: 45000 | C12: 1430015315 | D12: 8 | E12: Nicte Alfaro | F12: Emtone corporal | G12: Visa | H12: 5000
B13: 45007 | C13: 226118147 | D13: 8 | E13: Danury Samayoa | F13: Emtone chaparrera, entrepierna y parte posterior de la pierna y glúteos | G13: Visa | H13: 5000
B14: 45040 | C14: 1392791543 | D14: 8 | E14: Myriam Mijangos | F14: Emtone abdomen y cintura | G14: Visa | H14: 5000
... B35: 45279 | C35: 4218899378 | D35: 8 | E35: Edna Beatriz Suchite | F35: Emtone corporal | G35: Visa L. | H35: 5000
E36: Total | H36: =SUM(H3:H35) -> 146390.4

Sheet Exilis
A1: Exilis | B1: Fecha | C1: No. de Factura | D1: Cantidad | E1: Nombre del Paciente | F1: Tratamiento | G1: Forma de Pago | H1: Total
B3: 44930 | C3: 1419134061 | D3: 8 | E3: Rita Miranda Ovalle | F3: Exilis abdomen, cintura y espalda alta | G3: Visa | H3: 6500
B4: 44937 | C4: 2805746571 | D4: 8 | E4: Maggie Villela | F4: Exilis abdomen, cintura y espalda | G4: Visa L. | H4: 6500
B5: 44938 | C5: 2674674021 | D5: 1 | E5: Lissete Sanchez | F5: Abono a exilis piernas completas y abdomen | G5: Credomatic | H5: 5000
B6: 44942 | C6: 363789713 | D6: 8 | E6: Nicte Alfaro | F6: Exilis abdomen, cintura, espalda alta y brazos | G6: Visa | H6: 6250
B7: 44957 | C7: 379734400 | D7: 7 | E7: Dora Janeth De La Cruz De Monterroso | F7: Exilis abdomen, cintura y espalda alta | G7: Visa L. | H7: 5999.9996
B8: 44957 | C8: 379734400 | D8: 1 | E8: Dora Janeth De La Cruz De Monterroso | F8: Exilis abdomen, cintura y espalda alta | G8: Visa | H8: 500
B9: 44965 | C9: 2990883213 | D9: 1 | E9: Miguel Angel Martinez Solis | F9: Abono a exilis rostro y cuello | G9: Visa | H9: 3300
B10: 44965 | C10: 197673098 | D10: 8 | E10: Miguel Angel Martinez Solis | F10: Exilis abdomen, cintura y espalda baja | G10: Deposito | H10: 6500
B11: 44965 | C11: 197673098 | D11: 1 | E11: Miguel Angel Martinez Solis | F11: Cancelación a exilis rostro y cuello | G11: Deposito | H11: 1000
B12: 44970 | C12: 133842754 | D12: 8 | E12: Alex Weller | F12: Exilis abdomen, cintura y espalda baja | G12: Visa | H12: 6500
B13: 44970 | C13: 133842754 | D13: 6 | E13: Alex Weller | F13: Exilis rostro y cuello | G13: Visa | H13: 3900
B14: 44978 | C14: 3439806162 | D14: 8 | E14: Maria Jose Ruano | F14: Exilis abdomen, cintura y espalda | G14: Visa L. | H14: 6250
... B91: 45280 | C91: 3358608807 | D91: 1 | E91: Katherine Jordan | F91: Cancelción a exilis abdomen y cintura | G91: Visa L. | H91: 5000
E92: Total | H92: =SUM(H3:H91) -> 418532

Sheet Exfoliación
A1: Exfoliación | B1: Fecha | C1: No. de Factura | D1: Cantidad | E1: Nombre del Paciente | F1: Tratamiento | G1: Forma de Pago | H1: Total
B3: --- | C3: --- | D3: --- | E3: --- | F3: --- | G3: --- | H3: 0
E4: Total | H4: =SUM(H3:H3) -> 0

Sheet Facial purificante
A1: Facial purificante | B1: Fecha | C1: No. de Factura | D1: Cantidad | E1: Nombre del Paciente | F1: Tratamiento | G1: Forma de Pago | H1: Total
B3: 44931 | C3: 4230107039 | D3: 3 | E3: Dulce Marleny Vielman | F3: Facial purificante | G3: Visa | H3: 1725
B4: 44932 | C4: 735333448 | D4: 1 | E4: Patricia Gonzalez Starrs | F4: Facial purificante | G4: Visa | H4: 575
B5: 44935 | C5: 3232188127 | D5: 1 | E5: Diego Castillo | F5: Facial purificante | G5: Credomatic | H5: 575
B6: 44935 | C6: 3232188127 | D6: 1 | E6: Isabel Castillo | F6: Facial purificante | G6: Credomatic | H6: 402.5
B7: 44945 | C7: 2642757293 | D7: 2 | E7: Maziel Arango | F7: Facial purificante | G7: Efectivo | H7: 1150
B8: 44946 | C8: 770460610 | D8: 2 | E8: Juan Carlos Eguizabal | F8: Facial purificante | G8: Efectivo | H8: 1150
B9: 44956 | C9: 3581166546 | D9: 1 | E9: Silvia Patricia Oxon | F9: Facial purificante | G9: Credomatic | H9: 480
B10: 44959 | C10: 512640849 | D10: 1 | E10: Marjorie Manzo | F10: Facial purificante | G10: Credomatic | H10: 575
B11: 44964 | C11: 417089747 | D11: 1 | E11: Maria Renée Solares | F11: Facial purificante | G11: Credomatic | H11: 575
B12: 44972 | C12: 3909766254 | D12: 1 | E12: Ana Elizabeth Molina | F12: Facial purificante | G12: Visa | H12: 450
B13: 44986 | C13: 2863615258 | D13: 1 | E13: Ada Tejeda | F13: Facial purificante | G13: Deposito | H13: 450
B14: 44986 | C14: 792480024 | D14: 1 | E14: Ana Herbruger | F14: Facial purificante | G14: Credomatic | H14: 450
... B77: 45275 | C77: 1260866636 | D77: 2 | E77: Monica Lorena Martinez | F77: Facial purificante | G77: Visa L. | H77: 1150
E78: Total | H78: =SUM(H3:H77) -> 53654.5

Sheet Hifu
A1: Hifu | B1: Fecha | C1: No. de Factura | D1: Cantidad | E1: Nombre del Paciente | F1: Tratamiento | G1: Forma de Pago | H1: Total
B3: 44960 | C3: 814694929 | D3: 1 | E3: Alma Gricel Tobar | F3: Hifu ovalo facial y papada | G3: Deposito | H3: 4830
B4: 44972 | C4: 134558227 | D4: 1 | E4: Lydia Reyes | F4: Hifu ovalo facial y papada | G4: Visa | H4: 2600
B5: 44978 | C5: 827080822 | D5: 1 | E5: Ana Gislena Banus | F5: Hifu ovalo facial y papada | G5: Credomatic | H5: 3500
B6: 45075 | C6: 1881883923 | D6: 1 | E6: Jessie Tefel | F6: Hifu ovalo facial y papada | G6: Visa | H6: 3500
B7: 45113 | C7: 3871690244 | D7: 1 | E7: Ruth Sazo | F7: Hifu ovalo facial y papada | G7: Visa | H7: 3000
B8: 45118 | C8: 2111391586 | D8: 1 | E8: Ana Maria Teran | F8: Hifu ovalo facial y papada | G8: Visa | H8: 3000
B9: 45125 | C9: 3176480898 | D9: 1 | E9: Claudia Castillo | F9: Hifu ovalo facial y papada | G9: Visa L. | H9: 3200
B10: 45125 | C10: 1658585 | D10: 2 | E10: Esther Pacheco | F10: Hifu ovalo facial y papada | G10: Visa L. | H10: 6000
B11: 45146 | C11: 539969771 | D11: 1 | E11: Virginia Castillo | F11: Hifu ovalo facial y papada | G11: Visa | H11: 3200
B12: 45147 | C12: 366178616 | D12: 1 | E12: Maria Fernanda Remon | F12: Hifu ovalo facial y papada | G12: Visa | H12: 3383
B13: 45237 | C13: 3280356856 | D13: 1 | E13: Maria Teresa Arriola | F13: Hifu ovalo facial y papada | G13: Visa | H13: 2800
B14: 45268 | C14: 1388595424 | D14: 1 | E14: Gabriela Toledo | F14: Hifu ovalo facial y papada | G14: Credomatic | H14: 3500
... B16: 45271 | C16: 1752452591 | D16: 2 | E16: Melvin Quijivix | F16: Hifu ovalo facial y papada | G16: Deposito | H16: 4834
E17: Total | H17: =SUM(H3:H16) -> 52181

Sheet Hydrafacial
A1: Hydrafacial | B1: Fecha | C1: No. de Factura | D1: Cantidad | E1: Nombre del Paciente | F1: Tratamiento | G1: Forma de Pago | H1: Total
B3: 44932 | C3: 1691175570 | D3: 1 | E3: Lia Sanchez | F3: Hydrafacial | G3: Visa | H3: 583.8
B4: 44953 | C4: 2139636298 | D4: 1 | E4: Marisol Coronado | F4: Hydrafacial | G4: Credomatic | H4: 583.8
B5: 44972 | C5: 2819113225 | D5: 4 | E5: Wendy Marisol Gonzalez | F5: Hydrafacial | G5: Credomatic | H5: 2335
B6: 44973 | C6: 1258243715 | D6: 1 | E6: Elisa De Gil | F6: Hydrafacial | G6: Cheque | H6: 834
B7: 45000 | C7: 3855565521 | D7: 1 | E7: Johana Tamayo | F7: Hydrafacial | G7: Credomatic | H7: 834
B8: 45015 | C8: 2439464289 | D8: 1 | E8: Marcela Barquin | F8: Hydrafacial | G8: Credomatic | H8: 834
B9: 45048 | C9: 3585820799 | D9: 2 | E9: Rony Caballero | F9: Hydrafacial | G9: Efectivo | H9: 1160
B10: 45048 | C10: 3585820799 | D10: 1 | E10: Rony Caballero | F10: Hydrafacial | G10: Efectivo | H10: 435
B11: 45079 | C11: 3294710955 | D11: 1 | E11: Elisa Gil De Dedet | F11: Hydrafacial | G11: Cheque | H11: 834
B12: 45104 | C12: 988760668 | D12: 3 | E12: Andrea Rottmann | F12: Hydrafacial | G12: Credomatic | H12: 2802.24
B13: 45111 | C13: 521881109 | D13: 1 | E13: Jessica Chour | F13: Hydrafacial | G13: Visa | H13: 600
B14: 45121 | C14: 1501382008 | D14: 3 | E14: Gabriela Morales | F14: Hydrafacial | G14: Credomatic | H14: 1800
... B35: 45278 | C35: 182013905 | D35: 2 | E35: Katherine Jordan | F35: Hydrafacial | G35: Visa L. | H35: 1668
E36: Total | H36: =SUM(H3:H35) -> 38688.24

Sheet Laboratorios
A1: Laboratorios | B1: Fecha | C1: No. de Factura | D1: Cantidad | E1: Nombre del Paciente | F1: Tratamiento | G1: Forma de Pago | H1: Total
B3: 44942 | C3: 3683404304 | D3: 1 | E3: Ninive Vargas | F3: Laboratorios | G3: Credomatic | H3: 910
B4: 44946 | C4: 4259727711 | D4: 1 | E4: Victor Sagastume | F4: Laboratorios | G4: Visa | H4: 950
B5: 44946 | C5: 2951302643 | D5: 1 | E5: Sandra Fain | F5: Laboratorios | G5: Efectivo | H5: 950
B6: 44985 | C6: recibo | D6: 1 | E6: Gricel Chun | F6: Laboratorios | G6: Efectivo | H6: 47
B7: 44992 | C7: 2930526121 | D7: 1 | E7: Luis Castellanos | F7: Laboratorios | G7: Cheque | H7: 750
B8: 45043 | C8: 2201175240 | D8: 1 | E8: Evelyn Hernandez | F8: Laboratorios | G8: Visa | H8: 750
B9: 45121 | C9: 3320005399 | D9: 1 | E9: Mabby Morales | F9: Laboratorios | G9: Visa | H9: 750
B10: 45121 | C10: 3320005399 | D10: 1 | E10: Luis Leonel Morales | F10: Laboratorios | G10: Visa | H10: 850
B11: 45121 | C11: 3320005399 | D11: 1 | E11: Luis Leonel Morales | F11: Laboratorios | G11: Visa | H11: 1196.95
B12: 45139 | C12: 261639467 | D12: 1 | E12: Norma De Barquin | F12: Laboratorios | G12: Credomatic | H12: 1363.46
B13: 45142 | C13: 467091746 | D13: 1 | E13: Carlos Rodolfo De La Vega | F13: Laboratorios | G13: Efectivo | H13: 1135
B14: 45148 | C14: recibo | D14: 1 | E14: Dra Carolina Martinez | F14: Laboratorios | G14: Efectivo | H14: 788
B15: 45149 | C15: 3546759955 | D15: 1 | E15: Erica Mancilla | F15: Laboratorios | G15: Visa | H15: 850
B16: 45154 | C16: 2380808937 | D16: 1 | E16: Jacqueline Rottman | F16: Laboratorios pellets femenino | G16: Credomatic | H16: 1050
B17: 45218 | C17: 644236177 | D17: 1 | E17: Huerta Reina | F17: Laboratorios | G17: Visa | H17: 750
E18: Total | H18: =SUM(H3:H17) -> 13090.41

Sheet Masaje linfatico
A1: Masaje linfatico | B1: Fecha | C1: No. de Factura | D1: Cantidad | E1: Nombre del Paciente | F1: Tratamiento | G1: Forma de Pago | H1: Total
B3: 44935 | C3: 3402256232 | D3: 7 | E3: Sherlee Perez | F3: Masaje linfatico | G3: Visa | H3: 1400
B4: 44938 | C4: 244845665 | D4: 1 | E4: Mishel de Reitzel | F4: Masaje linfatico | G4: Credomatic | H4: 259
B5: 44943 | C5: 179322914 | D5: 8 | E5: Karla Jordan | F5: Masaje linfatico | G5: Visa | H5: 1600
B6: 44944 | C6: 2637121956 | D6: 1 | E6: Mishel de Reitzel | F6: Masaje linfatico | G6: Credomatic | H6: 259
B7: 44951 | C7: 2698856826 | D7: 1 | E7: Mishel de Reitzel | F7: Masaje linfatico | G7: Credomatic | H7: 259
B8: 44952 | C8: 4032643175 | D8: 8 | E8: Cristina Sanchez | F8: Masaje linfatico | G8: Visa | H8: 1600
B9: 44952 | C9: 1875525855 | D9: 6 | E9: Susy Villas | F9: Masaje linfatico facial | G9: Credomatic | H9: 720
B10: 44958 | C10: 1820609236 | D10: 1 | E10: Mishel De Reitzel | F10: Masaje linfatico | G10: Credomatic | H10: 259
B11: 44970 | C11: 3013034004 | D11: 1 | E11: Mishel De Reitzel | F11: Masaje linfatico | G11: Credomatic | H11: 259
B12: 44978 | C12: 2237089643 | D12: 1 | E12: Mishel De Reitzel | F12: Masaje linfatico | G12: Credomatic | H12: 259
B13: 44986 | C13: 676678220 | D13: 1 | E13: Mishel De Reitzel | F13: Masaje linfatico | G13: Visa | H13: 259
B14: 44993 | C14: 3919724872 | D14: 1 | E14: Mishel De Reitzel | F14: Masaje linfatico | G14: Credomatic | H14: 259
... B57: 45280 | C57: 3696904271 | D57: 1 | E57: Gabriela Pinto De Pontaza | F57: Masaje linfatico | G57: Credomatic | H57: 200
E58: Total | H58: =SUM(H3:H57) -> 60750

Sheet Mesoterapia
A1: Mesoterapia | B1: Fecha | C1: No. de Factura | D1: Cantidad | E1: Nombre del Paciente | F1: Tratamiento | G1: Forma de Pago | H1: Total
B3: 44942 | C3: 363789713 | D3: 10 | E3: Nicte Alfaro | F3: Mesoterapia abdomen, cintura, espalda alta y brazos | G3: Visa | H3: 4800
B4: 44963 | C4: 3139913013 | D4: 5 | E4: Rosario Palma Recinos | F4: Mesoterapia reductora abdomen y cintura | G4: Credomatic | H4: 2400
B5: 44993 | C5: 390285133 | D5: 10 | E5: Eunice Herrera Escobar | F5: Mesoterapia vitamina C glúteos | G5: Credomatic | H5: 3840
B6: 45000 | C6: 1430015315 | D6: 7 | E6: Nicte Alfaro | F6: Mesoterapia corporal | G6: Visa | H6: 3276
B7: 45000 | C7: 1430015315 | D7: 1 | E7: Nicte Alfaro | F7: Mesoterapia corporal | G7: Visa | H7: 474
B8: 45007 | C8: 226118147 | D8: 5 | E8: Danury Samayoa | F8: Mesoterapia banana roll solo lado derecho | G8: Visa | H8: 1580
B9: 45007 | C9: 226118147 | D9: 1 | E9: Danury Samayoa | F9: Mesoterapia banana roll solo lado derecho | G9: Visa | H9: 320
B10: 45034 | C10: 3294577217 | D10: 5 | E10: Sara Abularach | F10: Mesoterapia abdomen, cintura y gorditos de espalda alta | G10: Visa L. | H10: 2500
B11: 45035 | C11: 4027205059 | D11: 10 | E11: Maria Jose Garcia | F11: Mesoterapia | G11: Credomatic | H11: 4600
B12: 45040 | C12: 1392791543 | D12: 8 | E12: Myriam Mijangos | F12: Mesoterapia reductora abdomen y cintura | G12: Visa | H12: 2800
B13: 45076 | C13: 347491152 | D13: 5 | E13: Maria Elvia Navichoc | F13: Mesoterpia | G13: Cheque | H13: 3400
B14: 45111 | C14: 134762245 | D14: 5 | E14: Maria Jose Solares | F14: Mesoterapia reductora | G14: Visa L. | H14: 2210
... B23: 45268 | C23: 1388595424 | D23: 5 | E23: Gabriela Toledo | F23: Mesoterapia | G23: Credomatic | H23: 2500
E24: Total | H24: =SUM(H3:H23) -> 65407.6

Sheet Morpheus
A1: Morpheus | B1: Fecha | C1: No. de Factura | D1: Cantidad | E1: Nombre del Paciente | F1: Tratamiento | G1: Forma de Pago | H1: Total
B3: 44931 | C3: 1878802740 | D3: 3 | E3: Mabby Morales | F3: Morpheus rostro y cuello | G3: Visa L. | H3: 15000
B4: 44949 | C4: 3707128998 | D4: 1 | E4: Irene Martensen De Granados | F4: Abono a morpheus rostro y cuello | G4: Credomatic | H4: 3000
B5: 44949 | C5: 3707128998 | D5: 1 | E5: Irene Martensen De Granados | F5: Cancelación a morpheus rostro y cuello | G5: Visa | H5: 7000
B6: 44951 | C6: 3612299139 | D6: 1 | E6: Maria Cristina Martinez | F6: Morpheus rostro y cuello | G6: Visa L. | H6: 5000
B7: 44951 | C7: 2363966048 | D7: 1 | E7: Lorena de Gomez | F7: Abono a morpheus rostro y cuello | G7: Visa | H7: 6000
B8: 44951 | C8: 1261391501 | D8: 1 | E8: Lorena de Gomez | F8: Abono a morpheus rostro y cuello | G8: Visa | H8: 2000
B9: 44951 | C9: 3393276124 | D9: 1 | E9: Lorena de Gomez | F9: Abono a morpheus rostro y cuello | G9: Visa | H9: 2000
B10: 44951 | C10: 4048045569 | D10: 1 | E10: Lorena de Gomez | F10: Cancelación a morpheus rostro y cuello | G10: Visa | H10: 1200
B11: 44951 | C11: 1475561296 | D11: 2 | E11: Elizabeth Nicte Paz | F11: Morpheus rostro y cuello | G11: Visa | H11: 10000
B12: 44951 | C12: 1562135199 | D12: 2 | E12: Elizabeth Nicte Paz (mamá) | F12: Morpheus rostro y cuello | G12: Visa | H12: 10000
B13: 44953 | C13: 2905163280 | D13: 2 | E13: Wanda Serovic | F13: Morpheus rostro y cuello | G13: Credomatic | H13: 10000
B14: 44956 | C14: 680020621 | D14: 2 | E14: Karla Sarti De Bonatti | F14: Morpheus rostro y cuello | G14: Credomatic | H14: 10000
... B120: 45279 | C120: 1916421311 | D120: 2 | E120: Gabriela Pinto De Pontaza | F120: Morpheus rostro y cuello | G120: Visa | H120: 10000
E121: Total | H121: =SUM(H3:H120) -> 1182700

Sheet Pico-láser
A1: Pico-láser | B1: Fecha | C1: No. de Factura | D1: Cantidad | E1: Nombre del Paciente | F1: Tratamiento | G1: Forma de Pago | H1: Total
B3: 44974 | C3: 135104321 | D3: 2 | E3: Lisbeth Lopez | F3: Pico-láser | G3: Credomatic | H3: 1950
B4: 44978 | C4: 496257727 | D4: 3 | E4: Silvia Carolina Godoy | F4: Pico-láser | G4: Credomatic | H4: 2550
B5: 44978 | C5: 2865907652 | D5: 1 | E5: Lisbeth Estrada | F5: Pico-láser | G5: Efectivo | H5: 800
E6: Total | H6: =SUM(H3:H5) -> 5300

Sheet Powershape
A1: Powershape | B1: Fecha | C1: No. de Factura | D1: Cantidad | E1: Nombre del Paciente | F1: Tratamiento | G1: Forma de Pago | H1: Total
B3: 44930 | C3: 3021422995 | D3: 6 | E3: Perla Karina Alfaro Ortiz | F3: Powershape chaparrera, parte posterior de la pierna y moldeo de glúteos | G3: Visa | H3: 1596
E4: Total | H4: =SUM(H3:H3) -> 1596

Sheet Profhilo
A1: Porfhilo | B1: Fecha | C1: No. de Factura | D1: Cantidad | E1: Nombre del Paciente | F1: Tratamiento | G1: Forma de Pago | H1: Total
B3: 45135 | C3: 942162860 | D3: 1 | E3: Poala Monteagudo | F3: Aplicación de profhilo | G3: Credomatic | H3: 3000
B4: 45253 | C4: 2194294972 | D4: 2 | E4: Astrid Alvarado | F4: Aplicación de profhilo | G4: Credomatic | H4: 5000
B5: 45259 | C5: 1157187004 | D5: 2 | E5: Sandra Beatriz Alvarado | F5: Aplicación de profhilo | G5: Visa | H5: 5000
B6: 45266 | C6: 2525646246 | D6: 1 | E6: Karina Martinez | F6: Aplicación de profhilo | G6: Credomatic | H6: 2500
B7: 45272 | C7: 2205044553 | D7: 1 | E7: Sonia Oviedo | F7: Abono a tratamiento profhilo | G7: Visa | H7: 375
B8: 45272 | C8: 1297172486 | D8: 1 | E8: Sonia Oviedo | F8: Cancelación a tratamiento profhilo | G8: Visa | H8: 2125
B9: 45272 | C9: recibo | D9: 1 | E9: Gladys Del Cid De Escobar | F9: Aplicación de profhilo | G9: Efectivo | H9: 1250
B10: 45273 | C10: 4105324177 | D10: 1 | E10: Claudia Maria Jose Morales Donis | F10: Aplicación de profhilo | G10: Credomatic | H10: 2500
B11: 45274 | C11: 1990544598 | D11: 1 | E11: Yesenia Larrazabal | F11: Aplicación de profhilo | G11: Visa | H11: 5000
E12: Total | H12: =SUM(H3:H11) -> 26750

Sheet PRP
A1: PRP | B1: Fecha | C1: No. de Factura | D1: Cantidad | E1: Nombre del Paciente | F1: Tratamiento | G1: Forma de Pago | H1: Total
B3: 44930 | C3: 3620160573 | D3: 3 | E3: Annie Dougherty | F3: PRP rostro y cuello | G3: Visa L. | H3: 2880
B4: 44949 | C4: 828653815 | D4: 3 | E4: María Saravia | F4: PRP rostro y cuello | G4: Visa L. | H4: 3360
B5: 44952 | C5: 1869037945 | D5: 1 | E5: Gisela Castillo | F5: PRP rostro | G5: Cheque | H5: 800
B6: 44958 | C6: 2348895448 | D6: 1 | E6: Ruth Sazo | F6: PRP rostro y cuello | G6: Credomatic | H6: 1600
B7: 44958 | C7: 2348895448 | D7: 1 | E7: Ruth Sazo | F7: PRP escote | G7: Credomatic | H7: 1400
B8: 44958 | C8: 2348895448 | D8: 1 | E8: Ruth Sazo | F8: PRP rodillas | G8: Credomatic | H8: 1500
B9: 44958 | C9: 2348895448 | D9: 1 | E9: Ruth Sazo | F9: PRP manos | G9: Credomatic | H9: 1350
B10: 44958 | C10: 2348895448 | D10: 1 | E10: Ruth Sazo | F10: PRP antebrazo | G10: Credomatic | H10: 1600
B11: 44959 | C11: 484722330 | D11: 1 | E11: Vanessa Smith de Vargas | F11: PRP rostro y cuello | G11: Visa L. | H11: 1600
B12: 44965 | C12: 2990883213 | D12: 3 | E12: Miguel Angel Martinez Solis | F12: PRP rostro y cuello | G12: Visa | H12: 3360
B13: 44967 | C13: 1075922045 | D13: 3 | E13: Andrea Meany | F13: PRP Capilar | G13: Credomatic | H13: 1800
B14: 44970 | C14: 133842754 | D14: 3 | E14: Alex Weller | F14: PRP rostro y cuello | G14: Visa | H14: 3360
... B170: 45278 | C170: 1634549823 | D170: 3 | E170: Ana Maria Teran | F170: PRP rostro y cuello | G170: Visa L. | H170: 3000
E171: Total | H171: =SUM(H3:H170) -> 339930.4

Sheet Radiofrecuencia
A1: Radiofrecuencia | B1: Fecha | C1: No. de Factura | D1: Cantidad | E1: Nombre del Paciente | F1: Tratamiento | G1: Forma de Pago | H1: Total
B3: 44936 | C3: 1634550648 | D3: 1 | E3: Anneliese Wintzer | F3: Radiofrecuencia rostro y cuello | G3: Credomatic | H3: 450
B4: 44939 | C4: 322626027 | D4: 6 | E4: Claudia Arrecis | F4: Radiofrecuencia rostro y cuello | G4: Efectivo | H4: 2670
B5: 44939 | C5: 322626027 | D5: 5 | E5: Claudia Arrecis | F5: Radiofrecuencia abdomen, cintura, brazos y piernas | G5: Efectivo | H5: 6665
B6: 44939 | C6: 322626027 | D6: 1 | E6: Claudia Arrecis | F6: Radiofrecuencia abdomen, cintura, brazos y piernas | G6: Efectivo | H6: 1335
B7: 44946 | C7: 4289874178 | D7: 5 | E7: Maria Josee Solares | F7: Radiofecuencia rostro y cuello | G7: Visa L. | H7: 2000
B8: 44952 | C8: 4032643175 | D8: 8 | E8: Cristina Sanchez | F8: Radiofrecuencia rostro y cuello | G8: Visa | H8: 3560
B9: 44978 | C9: 533087440 | D9: 1 | E9: Norma Florian | F9: Cancelación a radiofrecuencia abdomen, cintura, espalda alta y gluteos | G9: Visa | H9: 1670
B10: 44992 | C10: 1207914449 | D10: 5 | E10: Raquel Calderon | F10: Radiofrecuencia abdomen, cintura y espalda | G10: Credomatic | H10: 3330
B11: 44992 | C11: 1207914449 | D11: 1 | E11: Raquel Calderon | F11: Radiofrecuencia abdomen, cintura y espalda | G11: Credomatic | H11: 670
B12: 44998 | C12: 2993833710 | D12: 6 | E12: Monica Merida De León | F12: Radiofrecuencia rostro y cuello | G12: Visa L. | H12: 3000
B13: 44999 | C13: 2015381660 | D13: 8 | E13: Dora De La Cruz | F13: Radiofrecuencia abdomen, cintura y espalda alta | G13: Visa L. | H13: 3560
B14: 45028 | C14: 2731032897 | D14: 4 | E14: Ana Luisa Ramos | F14: Radiofrecuencia abdomen, cintura y espalda baja | G14: Visa | H14: 1780
... B59: 45278 | C59: 182013905 | D59: 6 | E59: Betzalia Maribel Arriaga | F59: Radiofrecuencia rostro y cuello | G59: Visa L. | H59: 2670
E60: Total | H60: =SUM(H3:H59) -> 154013

Sheet Ultrasonido
A1: Ultrasonido post-operatorio | B1: Fecha | C1: No. de Factura | D1: Cantidad | E1: Nombre del Paciente | F1: Tratamiento | G1: Forma de Pago | H1: Total
B3: 44981 | C3: 1538738192 | D3: 1 | E3: Luis Francisco Garcia Axulen | F3: Ultrasonido post-operatorio | G3: Deposito | H3: 220
B4: 44987 | C4: 1563968764 | D4: 1 | E4: Luis Francisco Garcia | F4: Abono a ultrasonido post-operatorio | G4: Deposito | H4: 1000
B5: 45002 | C5: 2335131016 | D5: 1 | E5: Blanca Lemus | F5: Ultrasonido post-operatorio | G5: Efectivo | H5: 230
B6: 45030 | C6: 90590367 | D6: 2 | E6: Katherine Portillo | F6: Ultrasonido post-operatorio | G6: Credomatic | H6: 360
B7: 45037 | C7: 2626896055 | D7: 2 | E7: Katherine Portillo | F7: Ultrasonido post-operatorio | G7: Credomatic | H7: 360
B8: 45040 | C8: 1416577598 | D8: 10 | E8: Ana Vriginia Coosemans | F8: Ultrasonido post-operatorio | G8: Deposito | H8: 1200
B9: 45040 | C9: 4087041600 | D9: 5 | E9: Rony Caballero | F9: Ultrasonido post-operatorio | G9: Efectivo | H9: 900
B10: 45042 | C10: 2064532099 | D10: 5 | E10: Rafael Fiallos | F10: Ultrasonido post-operatorio | G10: Efectivo | H10: 600
B11: 45042 | C11: 2064532099 | D11: 5 | E11: Norma Pineda | F11: Ultrasonido post-operatorio | G11: Efectivo | H11: 600
B12: 45048 | C12: 2562475862 | D12: 5 | E12: Sulma Elizabeth Hernandez | F12: Ultrasonidos post-operatorio | G12: Credomatic | H12: 1000
B13: 45048 | C13: 226640767 | D13: 1 | E13: Katherine Portillo | F13: Ultrasonidos post-operatorio | G13: Visa L. | H13: 180
B14: 45055 | C14: 1037452307 | D14: 10 | E14: Bonna Marroquin | F14: Ultrasonidos post-operatorio | G14: Credomatic | H14: 1500
... B37: 45265 | C37: 2714255864 | D37: 9 | E37: Sara Mayorga | F37: Ultradonido post-operatorio | G37: Efectivo | H37: 1620
E38: Total | H38: =SUM(H3:H37) -> 36010

Sheet Velo de acido hialuronico
A1: Velo de acido hialuronico | B1: Fecha | C1: No. de Factura | D1: Cantidad | E1: Nombre del Paciente | F1: Tratamiento | G1: Forma de Pago | H1: Total
B3: 44935 | C3: 3232188127 | D3: 1 | E3: Elizabeth Molina | F3: Velo de acido hialuronico | G3: Credomatic | H3: 600
B4: 44936 | C4: 1634550648 | D4: 1 | E4: Anneliese Wintzer | F4: Velo de acido hialuronico | G4: Credomatic | H4: 650
B5: 44939 | C5: 1251688846 | D5: 1 | E5: Vanessa de Mancilla | F5: Velo de acido hialuronico | G5: Credomatic | H5: 650
B6: 44956 | C6: 3581166546 | D6: 1 | E6: Silvia Patricia Oxon | F6: Velo de acido hialuronico | G6: Credomatic | H6: 650
B7: 44973 | C7: 1258243715 | D7: 1 | E7: Elisa De Gil | F7: Velo de acido hialuronico | G7: Cheque | H7: 650
B8: 45180 | C8: 2241154763 | D8: 1 | E8: Mabby Morales | F8: Velo de acido hialuronico | G8: Credomatic | H8: 650
B9: 45188 | C9: 3045738417 | D9: 3 | E9: Carlos Colindres | F9: Velo de acido hialuronico | G9: Visa L. | H9: 1770
B10: 45188 | C10: 1965903057 | D10: 3 | E10: Heidy Colindres | F10: Velo de acido hialuronico | G10: Visa L. | H10: 1770
B11: 45194 | C11: 2464498696 | D11: 3 | E11: Maria de Leon | F11: Velo de acido hialuronico | G11: Visa | H11: 1770
B12: 45233 | C12: 1711164460 | D12: 1 | E12: Clara Conde | F12: Velo de acido hialuronico | G12: Credomatic | H12: 650
E13: Total | H13: =SUM(H3:H12) -> 9810

Sheet Velox
A1: Velox | B1: Fecha | C1: No. de Factura | D1: Cantidad | E1: Nombre del Paciente | F1: Tratamiento | G1: Forma de Pago | H1: Total
B3: 44931 | C3: 8077385 | D3: 6 | E3: Nicolle Melville | F3: Velox espalda baja, entrepierna, banana roll y chaparrera | G3: Visa | H3: 2856
B4: 45007 | C4: 226118147 | D4: 8 | E4: Danury Samayoa | F4: Velox chaparreras, entrepierna, y banana roll | G4: Visa | H4: 2128
B5: 45041 | C5: 779174422 | D5: 8 | E5: Jose Antonio Arzu | F5: Velox abdomen, cintura y espalda baja | G5: Credomatic | H5: 2500
B6: 45072 | C6: 2444970953 | D6: 8 | E6: Luis Araya | F6: Velox abdomen, cintura, pectoral, espalda | G6: Visa | H6: 2240
B7: 45084 | C7: 2573160404 | D7: 8 | E7: Maria Esperanza Barrutia | F7: Velox abdomen, cintura, chaparrera y banana roll | G7: Credomatic | H7: 2056
B8: 45099 | C8: 3564389051 | D8: 8 | E8: Angelica Maria Giron | F8: Velox abdomen completo, cintura y espalda baja | G8: Credomatic | H8: 4200
B9: 45126 | C9: 3241168669 | D9: 8 | E9: Karla Bocaletti De Enriquez | F9: Velox abdomen, cintura y brazos | G9: Visa | H9: 2688
B10: 45134 | C10: 3419488724 | D10: 8 | E10: Claudia Contreras De Alfaro | F10: Velox chaparrera y entrepierna | G10: Visa | H10: 3840
B11: 45146 | C11: 4165747199 | D11: 6 | E11: Karina Martinez | F11: Velox reductor abdomen y cintura | G11: Visa L. | H11: 2280
B12: 45155 | C12: 3861465003 | D12: 2 | E12: Isabel Figueroa Buezo | F12: Velox abdomen, cintura y gorditos espalda alta | G12: Credomatic | H12: 1000
B13: 45162 | C13: 438585984 | D13: 8 | E13: Karleen Giron | F13: Velox abdomen, banana roll, entrepierna y chaparreras | G13: Deposito | H13: 3000
B14: 45205 | C14: 2987934997 | D14: 8 | E14: Olga Lucia Tercero | F14: Velox abdomen, cintura, chaparrera y banana roll | G14: Deposito | H14: 2320
... B18: 45278 | C18: 461981108 | D18: 8 | E18: Kirin Gangaramani | F18: Velox abdomen, cintura y chaparrera | G18: Visa | H18: 4000
E19: Total | H19: =SUM(H3:H18) -> 39808

Sheet Verju
A1: Verju | B1: Fecha | C1: No. de Factura | D1: Cantidad | E1: Nombre del Paciente | F1: Tratamiento | G1: Forma de Pago | H1: Total
B3: 44937 | C3: 2805746571 | D3: 11 | E3: Maggie Villela | F3: Verju abdomen y cintura | G3: Visa L. | H3: 4576
B4: 44937 | C4: 2805746571 | D4: 1 | E4: Maggie Villela | F4: Verju abdomen y cintura | G4: Visa L. | H4: 424
B5: 44949 | C5: 906906239 | D5: 12 | E5: Rosario Palma Recinos | F5: Verju abdomen y cintura | G5: Visa | H5: 5100
B6: 44960 | C6: 2499104273 | D6: 1 | E6: Ana Lucia Cuestas | F6: Verju abdomen y cintura | G6: Visa L. | H6: 708.33
E7: Total | H7: =SUM(H3:H6) -> 10808.33

Sheet Vitamina C intravenosa
A1: Vitamina C intravenosa | B1: Fecha | C1: No. de Factura | D1: Cantidad | E1: Nombre del Paciente | F1: Tratamiento | G1: Forma de Pago | H1: Total
B3: 44932 | C3: 2848999730 | D3: 1 | E3: Iveth Bojorquez | F3: Aplicación vitamina C intravenosa | G3: Visa | H3: 500
B4: 44935 | C4: 481709657 | D4: 2 | E4: Sonia Chiroy de Rodriguez | F4: Aplicación vitamina C intravenosa | G4: Efectivo | H4: 1000
B5: 44935 | C5: 481709657 | D5: 1 | E5: Josselyn Rodriguez | F5: Aplicación vitamina C intravenosa | G5: Efectivo | H5: 500
B6: 44935 | C6: 1604799877 | D6: 3 | E6: Carlos Humberto Rodriguez | F6: Aplicación vitamina C intravenosa | G6: Deposito | H6: 1500
B7: 44937 | C7: 1511474418 | D7: 1 | E7: Mimi de Quan | F7: Aplicación vitamina C intravenosa | G7: Credomatic | H7: 500
B8: 44938 | C8: 2010334081 | D8: 3 | E8: Karla Pinto Portillo | F8: Aplicación vitamina C intravenosa | G8: Efectivo $ | H8: 1500
B9: 44942 | C9: 3683404304 | D9: 2 | E9: Ninive Vargas | F9: Aplicación vitamina C intravenosa | G9: Credomatic | H9: 1000
B10: 44943 | C10: recibo | D10: 1 | E10: Gricel Chun | F10: Aplicación vitamina C intravenosa | G10: Efectivo | H10: 93.5
B11: 44944 | C11: 467615785 | D11: 1 | E11: Evelyn Hernandez | F11: Aplicación vitamina C intravenosa | G11: Credomatic | H11: 500
B12: 44944 | C12: 1344424017 | D12: 2 | E12: Evelyn Hernandez | F12: Aplicación vitamina C intravenosa | G12: Credomatic | H12: 1000
B13: 44946 | C13: 1937655612 | D13: 1 | E13: Myra Leana Cortez | F13: Aplicación vitamina C intravenosa | G13: Visa | H13: 500
B14: 44946 | C14: 1937655612 | D14: 1 | E14: Katiana Liberona | F14: Aplicación vitamina C intravenosa | G14: Efectivo | H14: 500
B15: 44946 | C15: 4289874178 | D15: 3 | E15: Maria Josee Solares | F15: Aplicación vitamina C intravenosa | G15: Visa L. | H15: 1500
B16: 44949 | C16: 1176912602 | D16: 1 | E16: Viviano Gomez | F16: Aplicación vitamina C intravenosa | G16: Efectivo | H16: 500
B17: 44949 | C17: 1176912602 | D17: 1 | E17: Viviano Gomez (acompañante) | F17: Aplicación vitamina C intravenosa | G17: Efectivo | H17: 500
B18: 44949 | C18: 872106676 | D18: 1 | E18: Blanca Lara | F18: Aplicación vitamina C intravenosa | G18: Visa | H18: 500
B19: 44949 | C19: 872106676 | D19: 1 | E19: Margarita Lara | F19: Aplicación vitamina C intravenosa | G19: Visa | H19: 500
B20: 44949 | C20: 3872804531 | D20: 1 | E20: Karla Sarti De Bonatti | F20: Aplicación vitamina C intravenosa | G20: Credomatic | H20: 500
B21: 44949 | C21: 3086305346 | D21: 1 | E21: Paola Monteagudo | F21: Aplicación vitamina C intravenosa | G21: Efectivo | H21: 500
B22: 44951 | C22: 93996868 | D22: 1 | E22: Luisa Fernanda Monge | F22: Aplicación vitamina C intravenosa | G22: Visa | H22: 500
... B116: 45147 | C116: 1254115869 | D116: 1 | E116: Rocio Cancinos | F116: Aplicación vitamina C intravenosa | G116: Visa | H116: 535
B117: 45148 | C117: recibo | D117: 1 | E117: Dra Carolina Martinez | F117: Aplicación vitamina C intravenosa | G117: Efectivo | H117: 132
B118: 45154 | C118: 902909760 | D118: 3 | E118: Regina Merida | F118: Aplicación vitamina C intravenosa | G118: Credomatic | H118: 1605
B119: 45168 | C119: 2473017651 | D119: 1 | E119: Anabella Toriello | F119: Aplicación de vitamina C intravenosa | G119: Visa | H119: 535
B120: 45169 | C120: 2165850932 | D120: 1 | E120: Karla Bonatti | F120: Aplicación de vitamina C intravenosa | G120: Credomatic | H120: 535
B121: 45170 | C121: 3679077196 | D121: 1 | E121: Sonia Chiroy | F121: Aplicación de vitamina C intravenosa | G121: Visa | H121: 535
B122: 45170 | C122: 2067680633 | D122: 1 | E122: Xilone Galo | F122: Aplicación de vitamina C intravenosa | G122: Visa | H122: 535
B123: 45176 | C123: 3762897800 | D123: 1 | E123: Ana Gisela Castillo | F123: Aplicación de vitamina C intravenosa | G123: Credomatic | H123: 376
B124: 45180 | C124: 2241154763 | D124: 6 | E124: Mabby Morales | F124: Aplicación vitamina C intravenosa | G124: Credomatic | H124: 3210
B125: 45181 | C125: 2581217481 | D125: 3 | E125: Yanira Chacon | F125: Aplicación de vitamina C intravenosa | G125: Visa | H125: 1605
B126: 45181 | C126: 1240350765 | D126: 3 | E126: Patricia Chew | F126: Aplicación de vitamina C intravenosa | G126: Credomatic | H126: 1605
B127: 45182 | C127: 52972872 | D127: 1 | E127: Ana Maria | F127: Aplicación de vitamina C intravenosa | G127: Visa | H127: 535
B128: 45187 | C128: 1349534689 | D128: 3 | E128: Veronica de Sagastume | F128: Aplicación de vitamina C intravenosa | G128: Visa L. | H128: 1605
B129: 45187 | C129: 88556938 | D129: 3 | E129: Victor Sagastume | F129: Aplicación de vitamina C intravenosa | G129: Visa L. | H129: 1605
... B183: 45278 | C183: 1634549823 | D183: 6 | E183: Ana Maria Teran | F183: Aplicación de vitamina C intravenosa | G183: Visa L. | H183: 3210
E184: Total | H184: =SUM(H3:H183) -> 196022.1

Sheet Ciclo coolsculpting
A1: Ciclo coolsculpting | B1: Fecha | C1: No. de Factura | D1: Cantidad | E1: Nombre del Paciente | F1: Tratamiento | G1: Forma de Pago | H1: Total
B3: 45035 | C3: 4027205059 | D3: 4 | E3: Maria Jose Garcia | F3: Ciclos coolsculpting | G3: Credomatic | H3: 18000
B4: 45159 | C4: 2087602020 | D4: 2 | E4: Jose Ignacio Bolaños Arriola | F4: Ciclos coolsculpting | G4: Visa | H4: 9000
E5: Total | H5: =SUM(H3:H4) -> 27000

Sheet Cliovana
A1: Cliovana | B1: Fecha | C1: No. de Factura | D1: Cantidad | E1: Nombre del Paciente | F1: Tratamiento | G1: Forma de Pago | H1: Total
B3: --- | C3: --- | D3: --- | E3: --- | F3: --- | G3: --- | H3: 0
E4: Total | H4: =SUM(H3:H3) -> 0

Sheet Dermapen
A1: Dermapen | B1: Fecha | C1: No. de Factura | D1: Cantidad | E1: Nombre del Paciente | F1: Tratamiento | G1: Forma de Pago | H1: Total
B3: 44946 | C3: 4289874178 | D3: 3 | E3: Maria Josee Solares | F3: Dermapen rostro y cuello | G3: Visa L. | H3: 3000
B4: 44966 | C4: 4242624287 | D4: 1 | E4: Jessica Meza | F4: Dermapen rostro y cuello | G4: Visa | H4: 1260
B5: 44970 | C5: 561397809 | D5: 2 | E5: Diana Linares | F5: Dermapen rostro y cuello | G5: Visa L. | H5: 2400
B6: 44981 | C6: 2333689185 | D6: 3 | E6: Ana Luisa Montes | F6: Dermapen rostro y cuello | G6: Visa L. | H6: 3000
B7: 44984 | C7: 2840809246 | D7: 1 | E7: Julia Sapper | F7: Dermapen rostro y cuello | G7: Efectivo | H7: 1000
B8: 44984 | C8: 2840809246 | D8: 1 | E8: Julia Sapper | F8: Abono a tratamiento dermapen rostro y cuello | G8: Efectivo | H8: 500
B9: 45027 | C9: 1784760685 | D9: 3 | E9: Ana Rosa Ovalle | F9: Dermapen rostro y cuello | G9: Efectivo | H9: 3300
B10: 45068 | C10: 1923237767 | D10: 1 | E10: Maria Elvia Navichoc | F10: Dermapen rostro y cuello | G10: Cheque | H10: 1000
B11: 45077 | C11: 2171095910 | D11: 3 | E11: Pricila Duarte | F11: Dermapen rostro y cuello | G11: Cheque | H11: 3300
B12: 45090 | C12: 1990610141 | D12: 1 | E12: Silvia Patricia Cabrera De Rivera | F12: Dermapen rostro y cuello | G12: Visa | H12: 1200
B13: 45092 | C13: 1375552100 | D13: 1 | E13: Julia Sapper | F13: Cancelación a dermape rostro y cuello | G13: Efectivo | H13: 500
B14: 45092 | C14: 1375552100 | D14: 1 | E14: Julia Sapper | F14: Dermapen rostro y cuello | G14: Efectivo | H14: 1000
... B19: 45266 | C19: 1935887194 | D19: 3 | E19: Beatriz Tambasco | F19: Dermapen rostro y cuello | G19: Visa | H19: 3240
E20: Total | H20: =SUM(H3:H19) -> 32480

Sheet Láser CO2
A1: Láser CO2 | B1: Fecha | C1: No. de Factura | D1: Cantidad | E1: Nombre del Paciente | F1: Tratamiento | G1: Forma de Pago | H1: Total
B3: 44935 | C3: 3306967000 | D3: 1 | E3: Maria Regina Palma | F3: Lasér CO2 | G3: Deposito | H3: 3900
B4: 45008 | C4: 1720797090 | D4: 1 | E4: Gabriela Toledo | F4: Laser CO2 | G4: Deposito | H4: 5000
B5: 45050 | C5: 4007611036 | D5: 1 | E5: Maria Jose Enriquez | F5: Lasér CO2 | G5: Credomatic | H5: 4680
B6: 45076 | C6: 2473609958 | D6: 1 | E6: Olga Kabanova | F6: Lasér CO2 | G6: Visa | H6: 6000
B7: 45243 | C7: 4065282753 | D7: 1 | E7: Monica de Garcia | F7: Laser CO2 | G7: Credomatic | H7: 5600
B8: 45253 | C8: 4223944002 | D8: 1 | E8: Jose Rosas | F8: Laser CO2 | G8: Visa L. | H8: 3900
E9: Total | H9: =SUM(H3:H8) -> 29080

Sheet Masaje relajante
A1: Masaje relajante | B1: Fecha | C1: No. de Factura | D1: Cantidad | E1: Nombre del Paciente | F1: Tratamiento | G1: Forma de Pago | H1: Total
B3: 44937 | C3: 2721729139 | D3: 1 | E3: Lucia Garza | F3: Masaje relajante | G3: Credomatic | H3: 300
B4: 44946 | C4: 1508524242 | D4: 1 | E4: Patricia Chew | F4: Masaje relajante | G4: Visa | H4: 250
B5: 44965 | C5: 975718793 | D5: 1 | E5: Alejandro Solano | F5: Masaje relajante | G5: Efectivo | H5: 280
B6: 45061 | C6: 1533296782 | D6: 10 | E6: Olga De Sosa | F6: Masaje relajante | G6: Cheque | H6: 2000
B7: 45083 | C7: 77611340 | D7: 1 | E7: Jessie Arroyave | F7: Masaje relajante | G7: Credomatic | H7: 350
B8: 45091 | C8: 2570471180 | D8: 2 | E8: Evelyn Cerna | F8: Masaje relajante | G8: Credomatic | H8: 700
B9: 45113 | C9: 160452171 | D9: 1 | E9: Dan Truner | F9: Masaje relajante | G9: Credomatic | H9: 250
B10: 45155 | C10: 2680376855 | D10: 1 | E10: Alicia Sagastume | F10: Masaje relajante | G10: Deposito | H10: 250
B11: 45196 | C11: 2906803208 | D11: 6 | E11: Johana de Leon | F11: Masaje relajante | G11: Visa | H11: 1200
B12: 45196 | C12: 2906803208 | D12: 6 | E12: Johana de Leon | F12: Masaje relajante | G12: Visa | H12: 1200
B13: 45274 | C13: 1222724962 | D13: 1 | E13: Luisa Barillas | F13: Masaje relajante | G13: Credomatic | H13: 250
B14: 45278 | C14: 182013905 | D14: 10 | E14: Katherine Jordan | F14: Masaje relajante | G14: Visa L. | H14: 3000
E15: Total | H15: =SUM(H3:H14) -> 10030

Sheet Oligoelementos
A1: Oligoelementos | B1: Fecha | C1: No. de Factura | D1: Cantidad | E1: Nombre del Paciente | F1: Tratamiento | G1: Forma de Pago | H1: Total
B3: --- | C3: --- | D3: --- | E3: --- | F3: --- | G3: --- | H3: 0
E4: Total | H4: =SUM(H3:H3) -> 0

Sheet Celulas madre
A1: Celulas Madre | B1: Fecha | C1: No. de Factura | D1: Cantidad | E1: Nombre del Paciente | F1: Tratamiento | G1: Forma de Pago | H1: Total
B3: 44946 | C3: 4259727711 | D3: 1 | E3: Victor Sagastume | F3: Procedimiento celulas madres | G3: Visa | H3: 26550
B4: 44946 | C4: 2951302643 | D4: 1 | E4: Sandra Fain | F4: Procedimiento celulas madres | G4: Efectivo | H4: 24050
B5: 44992 | C5: 2930526121 | D5: 1 | E5: Luis Castellanos | F5: Procedimiento celulas madres | G5: Cheque | H5: 22750
B6: 45043 | C6: 2201175240 | D6: 1 | E6: Evelyn Hernandez | F6: Procedimiento celulas madres | G6: Visa | H6: 24250
B7: 45121 | C7: 3320005399 | D7: 1 | E7: Luis Leonel Morales | F7: Procedimiento celulas madres | G7: Visa | H7: 22700
B8: 45121 | C8: 3320005399 | D8: 1 | E8: Mabby Morales | F8: Procedimiento celulas madres | G8: Visa | H8: 22700
B9: 45149 | C9: 4044309255 | D9: 1 | E9: Erica Mancilla | F9: Procedimiento celulas madres | G9: Visa | H9: 19150
B10: 45215 | C10: 1232161653 | D10: 2 | E10: Wendy Lopez | F10: Procedimiento de celulas madre | G10: Deposito | H10: 28000
B11: 45218 | C11: 644236177 | D11: 1 | E11: Huerta Reina | F11: Procedimiento de celulas madre | G11: Visa | H11: 24350
E12: Total | H12: =SUM(H3:H11) -> 214500

Sheet Lipo-recover
A1: Lipo-recover | B1: Fecha | C1: No. de Factura | D1: Cantidad | E1: Nombre del Paciente | F1: Tratamiento | G1: Forma de Pago | H1: Total
B3: --- | C3: --- | D3: --- | E3: --- | F3: --- | G3: --- | H3: 0
E4: Total | H4: =SUM(H3:H3) -> 0

Sheet Peeling
A1: Peeling | B1: Fecha | C1: No. de Factura | D1: Cantidad | E1: Nombre del Paciente | F1: Tratamiento | G1: Forma de Pago | H1: Total
B3: --- | C3: --- | D3: --- | E3: --- | F3: --- | G3: --- | H3: 0
E4: Total | H4: =SUM(H3:H3) -> 0

Sheet Spectra ginecologico
A1: Spectra ginecologico | B1: Fecha | C1: No. de Factura | D1: Cantidad | E1: Nombre del Paciente | F1: Tratamiento | G1: Forma de Pago | H1: Total
B3: 44942 | C3: 1908886624 | D3: 2 | E3: María Saravia | F3: Spectra ginecologico | G3: Visa | H3: 3332
B4: 44942 | C4: 1908886624 | D4: 1 | E4: María Saravia | F4: Spectra ginecologico | G4: Visa | H4: 1668
B5: 44944 | C5: 3178711647 | D5: 2 | E5: Adriana Marroquin | F5: Spectra ginecologico | G5: Credomatic | H5: 3200
B6: 44944 | C6: 3178711647 | D6: 1 | E6: Adriana Marroquin | F6: Spectra ginecologico | G6: Credomatic | H6: 1800
B7: 44965 | C7: 4145630009 | D7: 3 | E7: Marlin Johana De León | F7: Spectra ginecologico | G7: Credomatic | H7: 5809.9998
B8: 44980 | C8: 2168343551 | D8: 2 | E8: Fabiola De Argueta | F8: Spectra ginecologico | G8: Deposito | H8: 3332
B9: 44980 | C9: 2168343551 | D9: 1 | E9: Fabiola De Argueta | F9: Spectra ginecologico | G9: Deposito | H9: 1668
B10: 44984 | C10: 1615809294 | D10: 2 | E10: Nancy Quan | F10: Spectra ginecologico | G10: Visa | H10: 3332
B11: 44984 | C11: 1615809294 | D11: 1 | E11: Nancy Quan | F11: Spectra ginecologico | G11: Visa | H11: 1668
B12: 45027 | C12: 1784760685 | D12: 3 | E12: Ana Rosa Ovalle | F12: Spectra ginecologico | G12: Efectivo | H12: 4500
B13: 45027 | C13: 2873902609 | D13: 3 | E13: Estela Terraza | F13: Spectra ginecologico | G13: Efectivo | H13: 4500
B14: 45040 | C14: 1392791543 | D14: 3 | E14: Myriam Mijangos | F14: Spectra ginecologico | G14: Visa | H14: 4999.998
... B31: 45258 | C31: 379866564 | D31: 1 | E31: Evelyn Hernandez | F31: Spectra ginecologico | G31: Visa | H31: 1938
E32: Total | H32: =SUM(H3:H31) -> 95729.998

Sheet Vanquish
A1: Vanquish | B1: Fecha | C1: No. de Factura | D1: Cantidad | E1: Nombre del Paciente | F1: Tratamiento | G1: Forma de Pago | H1: Total
B3: --- | C3: --- | D3: --- | E3: --- | F3: --- | G3: --- | H3: 0
E4: Total | H4: =SUM(H3:H3) -> 0

Sheet Xwave
A1: Xwave | B1: Fecha | C1: No. de Factura | D1: Cantidad | E1: Nombre del Paciente | F1: Tratamiento | G1: Forma de Pago | H1: Total
B3: --- | C3: --- | D3: --- | E3: --- | F3: --- | G3: --- | H3: 0
E4: Total | H4: =SUM(H3:H3) -> 0

Sheet Eliminación de lunares
A1: Eliminación de lunares | B1: Fecha | C1: No. de Factura | D1: Cantidad | E1: Nombre del Paciente | F1: Tratamiento | G1: Forma de Pago | H1: Total
B3: --- | C3: --- | D3: --- | E3: --- | F3: --- | G3: --- | H3: 0
E4: Total | H4: =SUM(H3:H3) -> 0

Sheet Botox
A1: Botox | B1: Fecha | C1: No. de Factura | D1: Cantidad | E1: Nombre del Paciente | F1: Tratamiento | G1: Forma de Pago | H1: Total
B3: 45006 | C3: 3401730285 | D3: 45 | E3: Claudia Bregel | F3: Aplicación de botox | G3: Deposito | H3: 2475
B4: 45006 | C4: 1831879759 | D4: 18 | E4: Mayra Valdez | F4: Aplicación de botox | G4: Credomatic | H4: 990
B5: 45006 | C5: 2465287170 | D5: 50 | E5: Mary Cordon | F5: Aplicación de botox | G5: Visa | H5: 2750
B6: 45006 | C6: 3919203878 | D6: 38 | E6: Evelyn García | F6: Aplicación de botox | G6: Credomatic | H6: 2090
B7: 45006 | C7: 176507018 | D7: 54 | E7: Susy De Rodriguez | F7: Aplicación de botox | G7: Cheque | H7: 2970
B8: 45006 | C8: 1220821609 | D8: 18 | E8: Susy De Biguria | F8: Aplicación de botox | G8: Credomatic | H8: 990
B9: 45006 | C9: 3383575794 | D9: 54 | E9: Carmen Monroy | F9: Aplicación de botox | G9: Credomatic | H9: 2970
B10: 45006 | C10: 1067140493 | D10: 56 | E10: Ana Lorena Meyer | F10: Aplicación de botox | G10: Credomatic | H10: 3080
B11: 45006 | C11: 3854124774 | D11: 36 | E11: Silvia Echeverria | F11: Aplicación de botox | G11: Credomatic | H11: 1980
B12: 45006 | C12: 2725201564 | D12: 28 | E12: Regina Merida | F12: Aplicación de botox | G12: Credomatic | H12: 1540
B13: 45006 | C13: 1280787906 | D13: 50 | E13: Nicte Paz | F13: Aplicación de botox | G13: Credomatic | H13: 2750
B14: 45006 | C14: 3124447388 | D14: 54 | E14: Irma Rivera | F14: Aplicación de botox | G14: Credomatic | H14: 2970
... B245: 45134 | C245: 138822397 | D245: 56 | E245: Ana Carolina Roca | F245: Aplicación de botox | G245: Credomatic | H245: 3080
B246: 45134 | C246: recibo | D246: 38 | E246: Patricia Espigares | F246: Aplicación de botox | G246: Efectivo | H246: 2090
B247: 45134 | C247: recibo | D247: 30 | E247: Deidree Stephanie Kneeland | F247: Abono aplicación de botox | G247: Efectivo | H247: 1599.9999
B248: 45134 | C248: recibo | D248: 26 | E248: Deidree Stephanie Kneeland | F248: Cancelaciòn aplicación de botox | G248: Efectivo $ | H248: 1479.998
B249: 45244 | C249: 953174132 | D249: 52 | E249: Marilyn Barascout | F249: Aplicación de botox | G249: Credomatic | H249: 2860
B250: 45258 | C250: 2887008895 | D250: 38 | E250: Delia Chour | F250: Aplicación de botox | G250: Credomatic | H250: 2090
B251: 45258 | C251: 725306405 | D251: 44 | E251: Lorena Abularach | F251: Aplicación de botox | G251: Efectivo | H251: 2420
B252: 45258 | C252: 1569213552 | D252: 52 | E252: Evelyn de Garcia | F252: Aplicación de botox | G252: Credomatic | H252: 2860
B253: 45258 | C253: 3487647978 | D253: 58 | E253: Alba de Gonzalez | F253: Aplicación de botox | G253: Cheque | H253: 3190
B254: 45258 | C254: 3716172493 | D254: 20 | E254: Clarissa de Gonzalez | F254: Aplicación de botox | G254: Credomatic | H254: 1100
B255: 45258 | C255: 3925623432 | D255: 58 | E255: Ana Luisa Martinez | F255: Aplicación de botox | G255: Credomatic | H255: 3190
B256: 45258 | C256: 3340455666 | D256: 50 | E256: Heide Reinoso | F256: Aplicación de botox | G256: Credomatic | H256: 2750
B257: 45258 | C257: 3528411831 | D257: 40 | E257: Andrea Meany | F257: Aplicación de botox | G257: Credomatic | H257: 2200
B258: 45258 | C258: 2781496799 | D258: 50 | E258: Virginia Hernandez | F258: Aplicación de botox | G258: Credomatic | H258: 2750
B259: 45258 | C259: 3556199209 | D259: 37 | E259: Samara Toledo | F259: Aplicación de botox | G259: Efectivo $ | H259: 1983.2
B260: 45258 | C260: 3556199209 | D260: 1 | E260: Samara Toledo | F260: Aplicación de botox | G260: Credomatic | H260: 107
... B358: 45278 | C358: 2469939754 | D358: 60 | E358: Joaquin Cerna | F358: Aplicación de botox | G358: Visa | H358: 3300
E359: Total | H359: =SUM(H3:H358) -> 773872.18

Sheet Encimas
A1: Encimas | B1: Fecha | C1: No. de Factura | D1: Cantidad | E1: Nombre del Paciente | F1: Tratamiento | G1: Forma de Pago | H1: Total
B3: --- | C3: --- | D3: --- | E3: --- | F3: --- | G3: --- | H3: 0
E4: Total | H4: =SUM(H3:H3) -> 0

Sheet Grow
A1: Grow | B1: Fecha | C1: No. de Factura | D1: Cantidad | E1: Nombre del Paciente | F1: Tratamiento | G1: Forma de Pago | H1: Total
B3: 44957 | C3: 4165159416 | D3: 1 | E3: Quimica Industrial Guatemalteca, S.A. | F3: Línea telefonica | G3: Cheque | H3: 1461.59
B4: 44957 | C4: 4165159416 | D4: 1 | E4: Quimica Industrial Guatemalteca, S.A. | F4: Servicios prestados de enfermeria | G4: Cheque | H4: 5820
B5: 44957 | C5: 4165159416 | D5: 1 | E5: Quimica Industrial Guatemalteca, S.A. | F5: Servicios prestados de recepcionista | G5: Cheque | H5: 3055.5
B6: 44957 | C6: 4165159416 | D6: 1 | E6: Quimica Industrial Guatemalteca, S.A. | F6: Servicios prestados de asistente administrativo | G6: Cheque | H6: 3395
B7: 44957 | C7: 4165159416 | D7: 1 | E7: Quimica Industrial Guatemalteca, S.A. | F7: Servicio prestado facturado | G7: Cheque | H7: 5820
B8: 44957 | C8: 4165159416 | D8: 1 | E8: Quimica Industrial Guatemalteca, S.A. | F8: Otros | G8: Cheque | H8: 650
B9: 44985 | C9: 2101364026 | D9: 1 | E9: Quimica Industrial Guatemalteca, S.A. | F9: Línea telefonica | G9: Cheque | H9: 1461.59
B10: 44985 | C10: 2101364026 | D10: 1 | E10: Quimica Industrial Guatemalteca, S.A. | F10: Servicios prestados de enfermeria | G10: Cheque | H10: 5820
B11: 44985 | C11: 2101364026 | D11: 1 | E11: Quimica Industrial Guatemalteca, S.A. | F11: Servicios prestados de recepcionista | G11: Cheque | H11: 3055.5
B12: 44985 | C12: 2101364026 | D12: 1 | E12: Quimica Industrial Guatemalteca, S.A. | F12: Servicios prestados de asistente administrativo | G12: Cheque | H12: 3395
B13: 44985 | C13: 2101364026 | D13: 1 | E13: Quimica Industrial Guatemalteca, S.A. | F13: Servicio prestado facturado | G13: Cheque | H13: 5820
B14: 44985 | C14: 2101364026 | D14: 1 | E14: Quimica Industrial Guatemalteca, S.A. | F14: Papeleria y utilies | G14: Cheque | H14: 450
... B57: 45280 | C57: 1936477407 | D57: 1 | E57: Quimica Industrial Guatemalteca, S.A. | F57: Otros | G57: Cheque | H57: 1750
E58: Total | H58: =SUM(H3:H57) -> 174065.58

Sheet Abonos a tratamientos
A1: Abono | B1: Fecha | C1: No. de Factura | D1: Cantidad | E1: Nombre del Paciente | F1: Tratamiento | G1: Forma de Pago | H1: Total
B3: 45007 | C3: 2341880464 | D3: 1 | E3: Rafael Fiallos | F3: Abono a tratamiento | G3: Efectivo $ | H3: 95
E4: Total | H4: =SUM(H3:H3) -> 95

Sheet Cambio de tratamiento
A1: Diferencia por cambio de tratamiento | B1: Fecha | C1: No. de Factura | D1: Cantidad | E1: Nombre del Paciente | F1: Tratamiento | G1: Forma de Pago | H1: Total
B3: 44973 | C3: 1258243715 | D3: 1 | E3: Elisa De Gil | F3: Diferencia por cambio de tratamiento | G3: Cheque | H3: 313.6
B4: 45012 | C4: 348786542 | D4: 1 | E4: Adriana Caceres | F4: Diferencia por cambio de tratamiento | G4: Credomatic | H4: 200
B5: 45093 | C5: 1352551502 | D5: 1 | E5: Heidi Rodriguez | F5: Diferencia por cambio por tratamiento | G5: Visa | H5: 215
B6: 45133 | C6: 1774862786 | D6: 1 | E6: Karla Zelaya | F6: Diferencia por cambio de tratamiento | G6: Visa | H6: 3354.58
B7: 45159 | C7: 1710833804 | D7: 1 | E7: Andrea Archila | F7: Diferencia por cambio de tratamiento | G7: Visa L. | H7: 245
E8: Total | H8: =SUM(H3:H7) -> 4328.18

Sheet Microdermoabrasión
A1: Microdermoabrasión | B1: Fecha | C1: No. de Factura | D1: Cantidad | E1: Nombre del Paciente | F1: Tratamiento | G1: Forma de Pago | H1: Total
B3: 44993 | C3: 884624540 | D3: 1 | E3: Sandra De Leon Torres | F3: Microdermoabrasión | G3: Credomatic | H3: 600
B4: 45104 | C4: 2782872032 | D4: 1 | E4: Sandra De León | F4: Micreodermoabrasión | G4: Credomatic | H4: 600
E5: Total | H5: =SUM(H3:H4) -> 1200

Sheet Terapia Luminica
A1: Terapia Luminica | B1: Fecha | C1: No. de Factura | D1: Cantidad | E1: Nombre del Paciente | F1: Tratamiento | G1: Forma de Pago | H1: Total
B3: --- | C3: --- | D3: --- | E3: --- | F3: --- | G3: --- | H3: 0
E4: Total | H4: =SUM(H3:H3) -> 0

Sheet Oscilación
A1: Oscilación | B1: Fecha | C1: No. de Factura | D1: Cantidad | E1: Nombre del Paciente | F1: Tratamiento | G1: Forma de Pago | H1: Total
B3: 44930 | C3: 2375762778 | D3: 6 | E3: Maria Virginia Hernandez | F3: Oscilación profunda | G3: Visa | H3: 3000
B4: 44935 | C4: 1604799877 | D4: 6 | E4: Maria Fernanda Del Carmen Mejia | F4: Oscilación profunda | G4: Deposito | H4: 3000
B5: 44935 | C5: 1148078848 | D5: 10 | E5: Navin Solorzano | F5: Oscilación profunda | G5: Visa | H5: 5000
B6: 44937 | C6: 3177205311 | D6: 6 | E6: Karina Martinez | F6: Oscilación profunda | G6: Credomatic | H6: 3000
B7: 44937 | C7: 3954852998 | D7: 4 | E7: Alma Tobar | F7: Oscilación profunda | G7: Visa | H7: 2000
B8: 44938 | C8: 699679277 | D8: 10 | E8: Zarina Portillo | F8: Oscilación profunda | G8: Visa L. | H8: 5000
B9: 44943 | C9: 561334754 | D9: 6 | E9: Anabella Campollo | F9: Oscilación profunda | G9: Visa | H9: 3000
B10: 44944 | C10: 4227025192 | D10: 4 | E10: Anggie Gelvers | F10: Oscilación profunda | G10: Efectivo | H10: 2000
B11: 44945 | C11: 3610790942 | D11: 5 | E11: Maria Patricia Avila Lopez | F11: Oscilación profunda | G11: Visa | H11: 2500
B12: 44950 | C12: 3461956299 | D12: 6 | E12: Wendy Carías | F12: Oscilación profunda | G12: Visa L. | H12: 3000
B13: 44951 | C13: 2582724761 | D13: 10 | E13: Virginia de Gandara | F13: Oscilación profunda | G13: Visa | H13: 5000
B14: 44951 | C14: 251872218 | D14: 10 | E14: Hugo Gonzalez Garcia | F14: Oscilación profunda | G14: Deposito | H14: 5000
... B85: 45280 | C85: 3696904271 | D85: 1 | E85: Gabriela Pinto De Pontaza | F85: Oscilación profunda | G85: Credomatic | H85: 500
E86: Total | H86: =SUM(H3:H85) -> 262860

Sheet Sueros
A1: Sueros | B1: Fecha | C1: No. de Factura | D1: Cantidad | E1: Nombre del Paciente | F1: Tratamiento | G1: Forma de Pago | H1: Total
B3: 44943 | C3: 3513206765 | D3: 1 | E3: Claudia Tobar | F3: Suero glutation | G3: Credomatic | H3: 750
B4: 44944 | C4: 3725609617 | D4: 1 | E4: Stephanie Aizenstatd | F4: Suero glutation | G4: Visa | H4: 750
B5: 44951 | C5: 93996868 | D5: 1 | E5: Lida Herrarte | F5: Suero glutation | G5: Visa | H5: 750
B6: 44956 | C6: 2398702386 | D6: 1 | E6: Myra Leana Cortez | F6: Suero glutation | G6: Credomatic | H6: 750
B7: 44957 | C7: 3697464994 | D7: 1 | E7: Norma Pineda | F7: Suero glutation | G7: Efectivo | H7: 750
B8: 44958 | C8: 847267065 | D8: 1 | E8: Maria Teresa Sosa | F8: Suero glutation | G8: Visa L. | H8: 750
B9: 44965 | C9: 4145630009 | D9: 1 | E9: Marlin Johana De León | F9: Suero glutation | G9: Credomatic | H9: 750
B10: 44971 | C10: 3748743128 | D10: 1 | E10: Rony Caballeros | F10: Suero glutation | G10: Efectivo | H10: 750
B11: 44971 | C11: 1812808808 | D11: 1 | E11: Rafael Molina | F11: Suero glutation | G11: Efectivo | H11: 750
B12: 44979 | C12: 2689156193 | D12: 1 | E12: Samuel Reyes Garcia | F12: Suero glutation | G12: Visa | H12: 750
B13: 44980 | C13: 2869577749 | D13: 1 | E13: Iveth Bojorquez | F13: Suero glutation | G13: Visa | H13: 750
B14: 44992 | C14: 860048496 | D14: 1 | E14: Heidi Marisol Rodriguez | F14: Suero glutation | G14: Visa | H14: 750
... B44: 45139 | C44: 3469430033 | D44: 1 | E44: Norma De Barquin | F44: Suero glutation | G44: Credomatic | H44: 750
B45: 45145 | C45: recibo | D45: 1 | E45: Patricia Sandoval | F45: Suero glutation | G45: Efectivo | H45: 700
B46: 45149 | C46: 3492171739 | D46: 1 | E46: Yeaneth Rosmery Maria Romero | F46: Suero glutation | G46: Visa | H46: 750
B47: 45170 | C47: 2067680633 | D47: 1 | E47: Xilone Galo | F47: Abono a suero glutation | G47: Visa | H47: 215
B48: 45180 | C48: 2241154763 | D48: 2 | E48: Mabby Morales | F48: Suero Glutation | G48: Credomatic | H48: 1500
B49: 45181 | C49: 2581217481 | D49: 1 | E49: Yanira Chacon | F49: Suero Glutation | G49: Visa | H49: 750
B50: 45181 | C50: 2338406965 | D50: 1 | E50: Vanesa Smith de Vargas | F50: Suero Glutation | G50: Visa L. | H50: 750
B51: 45181 | C51: 1240350765 | D51: 1 | E51: Patricia Chew | F51: Suero Glutation | G51: Credomatic | H51: 750
B52: 45182 | C52: 52972872 | D52: 1 | E52: Ana Maria | F52: Suero Glutation | G52: Visa | H52: 750
B53: 45183 | C53: 3225175505 | D53: 2 | E53: Fabiola de Sanchez | F53: Suero Glutation | G53: Credomatic | H53: 1500
B54: 45196 | C54: 3038334620 | D54: 2 | E54: Amelia Smith | F54: Suero Glutation | G54: Deposito | H54: 1500
B55: 45197 | C55: 3880995100 | D55: 2 | E55: Maria Eugenia Madrid | F55: Suero Glutation | G55: Credomatic | H55: 1500
B56: 45198 | C56: 406865469 | D56: 2 | E56: Jose Miguel Rosa | F56: Suero Glutation | G56: Visa | H56: 1500
B57: 45203 | C57: 1574325904 | D57: 2 | E57: Ronald Garcia | F57: Suero glutation | G57: Efectivo $ | H57: 1500
... B69: 45272 | C69: 3216001885 | D69: 3 | E69: Wendy Gonzalez | F69: Suero glutation | G69: Credomatic | H69: 2100
E70: Total | H70: =SUM(H3:H69) -> 57138.6

Sheet Presoterapia
A1: Presoterapia | B1: Fecha | C1: No. de Factura | D1: Cantidad | E1: Nombre del Paciente | F1: Tratamiento | G1: Forma de Pago | H1: Total
B3: 44952 | C3: 4032643175 | D3: 10 | E3: Cristina Sanchez | F3: Presoterapia | G3: Visa | H3: 2000
B4: 44952 | C4: 618483502 | D4: 10 | E4: Ines Carolina Cruz | F4: Presoterapia | G4: Visa | H4: 2000
B5: 44995 | C5: 1638287857 | D5: 10 | E5: Ninoshtka Vargas | F5: Presoterapia | G5: Credomatic | H5: 2300
E6: Total | H6: =SUM(H3:H5) -> 6300

Sheet Nioo
A1: Nioo | B1: Fecha | C1: No. de Factura | D1: Cantidad | E1: Nombre del Paciente | F1: Tratamiento | G1: Forma de Pago | H1: Total
B3: 44972 | C3: 686837718 | D3: 10 | E3: Carla de Zelaya | F3: Nioo abdomen, cintura y medias piernas completas | G3: Visa | H3: 4000
B4: 44987 | C4: 138825459 | D4: 10 | E4: Anneliese Wintzer | F4: Nioo piernas | G4: Visa | H4: 4000
B5: 44999 | C5: 2015381660 | D5: 4 | E5: Dora De La Cruz | F5: Nioo abdomen, cintura y espalda | G5: Visa L. | H5: 2000
B6: 44999 | C6: 2015381660 | D6: 6 | E6: Dora De La Cruz | F6: Ems electroestimulación glúteos | G6: Visa L. | H6: 2400
B7: 45002 | C7: 508315760 | D7: 10 | E7: Mariana Lesca | F7: Nioo | G7: Visa | H7: 4000
B8: 45006 | C8: 1726104040 | D8: 5 | E8: Selena De Ordoñez | F8: Nioo abdomen, cintura y espalda | G8: Efectivo | H8: 2000
B9: 45013 | C9: 697386659 | D9: 10 | E9: Rosaura Fabiola Azurdia | F9: Nioo abdomen, cintura y medias piernas | G9: Visa | H9: 4000
B10: 45033 | C10: 3125299252 | D10: 6 | E10: Sissel Morales | F10: Nioo fitnes | G10: Credomatic | H10: 3000
B11: 45049 | C11: 1057702669 | D11: 6 | E11: Dora De La Cruz | F11: Nioo fitnes | G11: Visa L. | H11: 2700
B12: 45051 | C12: 2861254121 | D12: 5 | E12: Alvaro Francisco Ruata | F12: Nioo-trinity abdomen, cintura y espalda baja | G12: Credomatic | H12: 1865
B13: 45051 | C13: 2861254121 | D13: 1 | E13: Alvaro Francisco Ruata | F13: Nioo-trinity abdomen, cintura y espalda baja | G13: Credomatic | H13: 375
B14: 45061 | C14: 1533296782 | D14: 8 | E14: Olga De Sosa | F14: Nioo trinity abdomen, cintura, espalda completa | G14: Cheque | H14: 3000
... B39: 45278 | C39: 461981108 | D39: 8 | E39: Kirin Gangaramani | F39: Nioo trinity abdomen, cintura, espalda alta y parte posterior de la pierna | G39: Visa | H39: 2500
E40: Total | H40: =SUM(H3:H39) -> 116520

Sheet Sedación
A1: Sedación | B1: Fecha | C1: No. de Factura | D1: Cantidad | E1: Nombre del Paciente | F1: Tratamiento | G1: Forma de Pago | H1: Total
B3: 45133 | C3: 4271853280 | D3: 1 | E3: Meylin De Leon | F3: Por servicio de sedación | G3: Visa | H3: 350
E4: Total | H4: =SUM(H3:H3) -> 350
